{
    "seed": 0,
    "resourceTagColor": {},
    "pendingTriggers": [],
    "graph": {
        "stateEdges": {
            "51": {
                "stateFormula": {
                    "contents": [
                        "CGt",
                        {
                            "contents": 74,
                            "tag": "SFConstant"
                        }
                    ],
                    "tag": "SFCondition"
                },
                "to": 50,
                "active": false,
                "from": 36
            },
            "89": {
                "stateFormula": {
                    "contents": [
                        "CGt",
                        {
                            "contents": 74,
                            "tag": "SFConstant"
                        }
                    ],
                    "tag": "SFCondition"
                },
                "to": 44,
                "active": false,
                "from": 35
            },
            "133": {
                "stateFormula": {
                    "contents": [
                        "CGt",
                        {
                            "contents": 399,
                            "tag": "SFConstant"
                        }
                    ],
                    "tag": "SFCondition"
                },
                "to": 74,
                "active": false,
                "from": 132
            },
            "90": {
                "stateFormula": {
                    "contents": [
                        "CLt",
                        {
                            "contents": 16,
                            "tag": "SFConstant"
                        }
                    ],
                    "tag": "SFCondition"
                },
                "to": 84,
                "active": false,
                "from": 82
            },
            "19": {
                "stateFormula": {
                    "contents": [
                        "CLt",
                        {
                            "contents": 16,
                            "tag": "SFConstant"
                        }
                    ],
                    "tag": "SFCondition"
                },
                "to": 15,
                "active": false,
                "from": 13
            },
            "88": {
                "stateFormula": {
                    "contents": "a",
                    "tag": "SFVariable"
                },
                "to": 86,
                "active": false,
                "from": 82
            },
            "63": {
                "stateFormula": {
                    "contents": "a",
                    "tag": "SFVariable"
                },
                "to": 62,
                "active": false,
                "from": 58
            },
            "92": {
                "stateFormula": {
                    "contents": {
                        "contents": 5,
                        "tag": "SFConstant"
                    },
                    "tag": "SFAdd"
                },
                "to": 81,
                "active": false,
                "from": 86
            },
            "21": {
                "stateFormula": {
                    "contents": "a",
                    "tag": "SFVariable"
                },
                "to": 17,
                "active": false,
                "from": 13
            },
            "65": {
                "stateFormula": {
                    "contents": [
                        "CLt",
                        {
                            "contents": 6,
                            "tag": "SFConstant"
                        }
                    ],
                    "tag": "SFCondition"
                },
                "to": 60,
                "active": false,
                "from": 58
            },
            "64": {
                "stateFormula": {
                    "contents": {
                        "contents": 4,
                        "tag": "SFConstant"
                    },
                    "tag": "SFAdd"
                },
                "to": 57,
                "active": false,
                "from": 62
            },
            "20": {
                "stateFormula": {
                    "contents": {
                        "contents": 5,
                        "tag": "SFConstant"
                    },
                    "tag": "SFAdd"
                },
                "to": 12,
                "active": false,
                "from": 17
            }
        },
        "vertices": {
            "25": {
                "nodeColor": "black",
                "nodeLabel": "",
                "nodeTy": {
                    "activation": {
                        "tag": "Interactive"
                    },
                    "overflow": "OverflowBlock",
                    "resources": [],
                    "pushPullAction": {
                        "contents": "PullAll",
                        "tag": "Pulling"
                    },
                    "limit": 101,
                    "tag": "Pool"
                }
            },
            "96": {
                "nodeColor": "black",
                "nodeLabel": "",
                "nodeTy": {
                    "activation": {
                        "tag": "Interactive"
                    },
                    "overflow": "OverflowBlock",
                    "resources": [],
                    "pushPullAction": {
                        "contents": "PullAll",
                        "tag": "Pulling"
                    },
                    "limit": 251,
                    "tag": "Pool"
                }
            },
            "4": {
                "nodeColor": "black",
                "nodeLabel": "",
                "nodeTy": {
                    "resourceTypes": [
                        "Blue"
                    ],
                    "activation": {
                        "tag": "Automatic"
                    },
                    "tag": "Source"
                }
            },
            "48": {
                "nodeColor": "black",
                "nodeLabel": "",
                "nodeTy": {
                    "activation": {
                        "tag": "Passive"
                    },
                    "overflow": "OverflowBlock",
                    "resources": [],
                    "pushPullAction": {
                        "contents": "PushAny",
                        "tag": "Pushing"
                    },
                    "tag": "Pool"
                }
            },
            "15": {
                "nodeColor": "black",
                "nodeLabel": "",
                "nodeTy": {
                    "resourceTypes": [
                        "Orange"
                    ],
                    "pullAction": "PullAll",
                    "activation": {
                        "tag": "Interactive"
                    },
                    "storage": {},
                    "tag": "Converter"
                }
            },
            "84": {
                "nodeColor": "black",
                "nodeLabel": "",
                "nodeTy": {
                    "resourceTypes": [
                        "Orange"
                    ],
                    "pullAction": "PullAll",
                    "activation": {
                        "tag": "Interactive"
                    },
                    "storage": {},
                    "tag": "Converter"
                }
            },
            "111": {
                "nodeColor": "black",
                "nodeLabel": "",
                "nodeTy": {
                    "resourceTypes": [
                        "Black"
                    ],
                    "pullAction": "PullAll",
                    "activation": {
                        "tag": "Passive"
                    },
                    "storage": {},
                    "tag": "Converter"
                }
            },
            "9": {
                "nodeColor": "black",
                "nodeLabel": "",
                "nodeTy": {
                    "activation": {
                        "tag": "Passive"
                    },
                    "overflow": "OverflowBlock",
                    "resources": [],
                    "pushPullAction": {
                        "contents": "PushAny",
                        "tag": "Pushing"
                    },
                    "tag": "Pool"
                }
            },
            "45": {
                "nodeColor": "black",
                "nodeLabel": "",
                "nodeTy": {
                    "activation": {
                        "tag": "Passive"
                    },
                    "overflow": "OverflowBlock",
                    "resources": [],
                    "pushPullAction": {
                        "contents": "PushAny",
                        "tag": "Pushing"
                    },
                    "tag": "Pool"
                }
            },
            "23": {
                "nodeColor": "black",
                "nodeLabel": "",
                "nodeTy": {
                    "activation": {
                        "tag": "Interactive"
                    },
                    "overflow": "OverflowBlock",
                    "resources": [],
                    "pushPullAction": {
                        "contents": "PullAll",
                        "tag": "Pulling"
                    },
                    "limit": 151,
                    "tag": "Pool"
                }
            },
            "60": {
                "nodeColor": "black",
                "nodeLabel": "",
                "nodeTy": {
                    "resourceTypes": [
                        "Orange"
                    ],
                    "pullAction": "PullAll",
                    "activation": {
                        "tag": "Interactive"
                    },
                    "storage": {},
                    "tag": "Converter"
                }
            },
            "97": {
                "nodeColor": "black",
                "nodeLabel": "",
                "nodeTy": {
                    "activation": {
                        "tag": "Interactive"
                    },
                    "overflow": "OverflowBlock",
                    "resources": [],
                    "pushPullAction": {
                        "contents": "PullAll",
                        "tag": "Pulling"
                    },
                    "limit": 101,
                    "tag": "Pool"
                }
            },
            "24": {
                "nodeColor": "black",
                "nodeLabel": "",
                "nodeTy": {
                    "activation": {
                        "tag": "Interactive"
                    },
                    "overflow": "OverflowBlock",
                    "resources": [],
                    "pushPullAction": {
                        "contents": "PullAll",
                        "tag": "Pulling"
                    },
                    "limit": 101,
                    "tag": "Pool"
                }
            },
            "79": {
                "nodeColor": "black",
                "nodeLabel": "",
                "nodeTy": {
                    "resourceTypes": [
                        "Blue"
                    ],
                    "pullAction": "PullAny",
                    "activation": {
                        "tag": "Automatic"
                    },
                    "storage": {},
                    "tag": "Converter"
                }
            },
            "29": {
                "nodeColor": "black",
                "nodeLabel": "",
                "nodeTy": {
                    "activation": {
                        "tag": "Interactive"
                    },
                    "overflow": "OverflowBlock",
                    "resources": [],
                    "pushPullAction": {
                        "contents": "PullAll",
                        "tag": "Pulling"
                    },
                    "limit": 151,
                    "tag": "Pool"
                }
            },
            "74": {
                "nodeColor": "black",
                "nodeLabel": "",
                "nodeTy": {
                    "resourceTypes": [
                        "Blue"
                    ],
                    "activation": {
                        "tag": "Automatic"
                    },
                    "tag": "Source"
                }
            },
            "30": {
                "nodeColor": "black",
                "nodeLabel": "",
                "nodeTy": {
                    "activation": {
                        "tag": "Interactive"
                    },
                    "overflow": "OverflowBlock",
                    "resources": [],
                    "pushPullAction": {
                        "contents": "PullAll",
                        "tag": "Pulling"
                    },
                    "limit": 151,
                    "tag": "Pool"
                }
            },
            "102": {
                "nodeColor": "black",
                "nodeLabel": "",
                "nodeTy": {
                    "resourceTypes": [
                        "Black"
                    ],
                    "pullAction": "PullAll",
                    "activation": {
                        "tag": "Passive"
                    },
                    "storage": {},
                    "tag": "Converter"
                }
            },
            "109": {
                "nodeColor": "black",
                "nodeLabel": "",
                "nodeTy": {
                    "resourceTypes": [
                        "Black"
                    ],
                    "pullAction": "PullAll",
                    "activation": {
                        "tag": "Passive"
                    },
                    "storage": {},
                    "tag": "Converter"
                }
            },
            "44": {
                "nodeColor": "black",
                "nodeLabel": "",
                "nodeTy": {
                    "resourceTypes": [
                        "Black"
                    ],
                    "activation": {
                        "tag": "Automatic"
                    },
                    "tag": "Source"
                }
            },
            "22": {
                "nodeColor": "black",
                "nodeLabel": "",
                "nodeTy": {
                    "activation": {
                        "tag": "Interactive"
                    },
                    "overflow": "OverflowBlock",
                    "resources": [],
                    "pushPullAction": {
                        "contents": "PullAll",
                        "tag": "Pulling"
                    },
                    "limit": 101,
                    "tag": "Pool"
                }
            },
            "132": {
                "nodeColor": "black",
                "nodeLabel": "",
                "nodeTy": {
                    "activation": {
                        "tag": "Interactive"
                    },
                    "overflow": "OverflowBlock",
                    "resources": [],
                    "pushPullAction": {
                        "contents": "PullAll",
                        "tag": "Pulling"
                    },
                    "tag": "Pool"
                }
            },
            "110": {
                "nodeColor": "black",
                "nodeLabel": "",
                "nodeTy": {
                    "resourceTypes": [
                        "Black"
                    ],
                    "pullAction": "PullAll",
                    "activation": {
                        "tag": "Passive"
                    },
                    "storage": {},
                    "tag": "Converter"
                }
            },
            "41": {
                "nodeColor": "black",
                "nodeLabel": "",
                "nodeTy": {
                    "activation": {
                        "tag": "Interactive"
                    },
                    "overflow": "OverflowBlock",
                    "resources": [],
                    "pushPullAction": {
                        "contents": "PullAll",
                        "tag": "Pulling"
                    },
                    "limit": 151,
                    "tag": "Pool"
                }
            },
            "27": {
                "nodeColor": "black",
                "nodeLabel": "",
                "nodeTy": {
                    "activation": {
                        "tag": "Interactive"
                    },
                    "overflow": "OverflowBlock",
                    "resources": [],
                    "pushPullAction": {
                        "contents": "PullAll",
                        "tag": "Pulling"
                    },
                    "limit": 101,
                    "tag": "Pool"
                }
            },
            "58": {
                "nodeColor": "black",
                "nodeLabel": "",
                "nodeTy": {
                    "activation": {
                        "tag": "Passive"
                    },
                    "overflow": "OverflowBlock",
                    "resources": [],
                    "pushPullAction": {
                        "contents": "PullAny",
                        "tag": "Pulling"
                    },
                    "limit": 6,
                    "tag": "Pool"
                }
            },
            "94": {
                "nodeColor": "black",
                "nodeLabel": "",
                "nodeTy": {
                    "activation": {
                        "tag": "Interactive"
                    },
                    "overflow": "OverflowBlock",
                    "resources": [],
                    "pushPullAction": {
                        "contents": "PullAny",
                        "tag": "Pulling"
                    },
                    "tag": "Pool"
                }
            },
            "82": {
                "nodeColor": "black",
                "nodeLabel": "",
                "nodeTy": {
                    "activation": {
                        "tag": "Passive"
                    },
                    "overflow": "OverflowBlock",
                    "resources": [
                        {
                            "uUID": "571f2463-c2ca-4998-9891-1666b8853b7a",
                            "tag": "Orange"
                        },
                        {
                            "uUID": "a346a039-c7d1-4be4-990c-3e616ab22dd4",
                            "tag": "Orange"
                        },
                        {
                            "uUID": "b0ff4ff4-d299-482c-a708-2b825d35270e",
                            "tag": "Orange"
                        },
                        {
                            "uUID": "d8794e14-d63c-4540-9c4c-1c79d881d583",
                            "tag": "Orange"
                        },
                        {
                            "uUID": "df548d9f-3511-4222-8968-e12150a89d6e",
                            "tag": "Orange"
                        },
                        {
                            "uUID": "e0a6fd31-43a6-4ba8-b4da-10cd3b4e7913",
                            "tag": "Orange"
                        },
                        {
                            "uUID": "e635151c-8bac-44e3-a534-d2488fd55909",
                            "tag": "Orange"
                        },
                        {
                            "uUID": "fcb49ac6-d82a-4025-aab7-22fbbdac80c3",
                            "tag": "Orange"
                        }
                    ],
                    "pushPullAction": {
                        "contents": "PullAny",
                        "tag": "Pulling"
                    },
                    "limit": 16,
                    "tag": "Pool"
                }
            },
            "103": {
                "nodeColor": "black",
                "nodeLabel": "",
                "nodeTy": {
                    "resourceTypes": [
                        "Black"
                    ],
                    "pullAction": "PullAll",
                    "activation": {
                        "tag": "Passive"
                    },
                    "storage": {},
                    "tag": "Converter"
                }
            },
            "28": {
                "nodeColor": "black",
                "nodeLabel": "",
                "nodeTy": {
                    "activation": {
                        "tag": "Interactive"
                    },
                    "overflow": "OverflowBlock",
                    "resources": [],
                    "pushPullAction": {
                        "contents": "PullAll",
                        "tag": "Pulling"
                    },
                    "limit": 151,
                    "tag": "Pool"
                }
            },
            "75": {
                "nodeColor": "black",
                "nodeLabel": "",
                "nodeTy": {
                    "activation": {
                        "tag": "Passive"
                    },
                    "overflow": "OverflowBlock",
                    "resources": [],
                    "pushPullAction": {
                        "contents": "PushAny",
                        "tag": "Pushing"
                    },
                    "tag": "Pool"
                }
            },
            "31": {
                "nodeColor": "black",
                "nodeLabel": "",
                "nodeTy": {
                    "activation": {
                        "tag": "Interactive"
                    },
                    "overflow": "OverflowBlock",
                    "resources": [],
                    "pushPullAction": {
                        "contents": "PullAll",
                        "tag": "Pulling"
                    },
                    "limit": 151,
                    "tag": "Pool"
                }
            },
            "13": {
                "nodeColor": "black",
                "nodeLabel": "",
                "nodeTy": {
                    "activation": {
                        "tag": "Passive"
                    },
                    "overflow": "OverflowBlock",
                    "resources": [
                        {
                            "uUID": "4e2ff1e2-c5b2-4bc2-a5d0-2972bf6399fe",
                            "tag": "Orange"
                        },
                        {
                            "uUID": "64941f75-e1b0-41e8-b2f8-aca0925b1d59",
                            "tag": "Orange"
                        },
                        {
                            "uUID": "6ba33d4d-4fac-46fd-9ea7-0d6403673bf0",
                            "tag": "Orange"
                        },
                        {
                            "uUID": "83738308-d5c0-46c6-83f1-351b67dc34b4",
                            "tag": "Orange"
                        },
                        {
                            "uUID": "a2347aea-1ea4-432a-a972-8255293ba511",
                            "tag": "Orange"
                        },
                        {
                            "uUID": "aed8c0a7-3c9c-490f-afc4-7f60c89801fb",
                            "tag": "Orange"
                        },
                        {
                            "uUID": "c4bd6e9d-268a-4ff3-9bc7-42970683644b",
                            "tag": "Orange"
                        },
                        {
                            "uUID": "f2d6d8bc-8835-4aa9-b636-745a7d09b759",
                            "tag": "Orange"
                        }
                    ],
                    "pushPullAction": {
                        "contents": "PullAny",
                        "tag": "Pulling"
                    },
                    "limit": 16,
                    "tag": "Pool"
                }
            },
            "62": {
                "nodeColor": "black",
                "nodeLabel": "a",
                "nodeTy": {
                    "registerFormula": {
                        "contents": "a",
                        "tag": "FVar"
                    },
                    "limits": {},
                    "tag": "RegisterFn"
                }
            },
            "95": {
                "nodeColor": "black",
                "nodeLabel": "",
                "nodeTy": {
                    "activation": {
                        "tag": "Interactive"
                    },
                    "overflow": "OverflowBlock",
                    "resources": [],
                    "pushPullAction": {
                        "contents": "PullAll",
                        "tag": "Pulling"
                    },
                    "limit": 101,
                    "tag": "Pool"
                }
            },
            "26": {
                "nodeColor": "black",
                "nodeLabel": "",
                "nodeTy": {
                    "activation": {
                        "tag": "Interactive"
                    },
                    "overflow": "OverflowBlock",
                    "resources": [],
                    "pushPullAction": {
                        "contents": "PullAll",
                        "tag": "Pulling"
                    },
                    "limit": 101,
                    "tag": "Pool"
                }
            },
            "100": {
                "nodeColor": "black",
                "nodeLabel": "",
                "nodeTy": {
                    "activation": {
                        "tag": "Interactive"
                    },
                    "overflow": "OverflowBlock",
                    "resources": [],
                    "pushPullAction": {
                        "contents": "PullAny",
                        "tag": "Pulling"
                    },
                    "tag": "Pool"
                }
            },
            "76": {
                "nodeColor": "black",
                "nodeLabel": "",
                "nodeTy": {
                    "waitingResources": [],
                    "activation": {
                        "tag": "Passive"
                    },
                    "tag": "Queue"
                }
            },
            "32": {
                "nodeColor": "black",
                "nodeLabel": "",
                "nodeTy": {
                    "activation": {
                        "tag": "Interactive"
                    },
                    "overflow": "OverflowBlock",
                    "resources": [],
                    "pushPullAction": {
                        "contents": "PullAll",
                        "tag": "Pulling"
                    },
                    "limit": 151,
                    "tag": "Pool"
                }
            },
            "10": {
                "nodeColor": "black",
                "nodeLabel": "",
                "nodeTy": {
                    "resourceTypes": [
                        "Blue"
                    ],
                    "pullAction": "PullAny",
                    "activation": {
                        "tag": "Automatic"
                    },
                    "storage": {},
                    "tag": "Converter"
                }
            },
            "98": {
                "nodeColor": "black",
                "nodeLabel": "",
                "nodeTy": {
                    "activation": {
                        "tag": "Interactive"
                    },
                    "overflow": "OverflowBlock",
                    "resources": [],
                    "pushPullAction": {
                        "contents": "PullAll",
                        "tag": "Pulling"
                    },
                    "tag": "Pool"
                }
            },
            "6": {
                "nodeColor": "black",
                "nodeLabel": "",
                "nodeTy": {
                    "waitingResources": [],
                    "activation": {
                        "tag": "Passive"
                    },
                    "tag": "Queue"
                }
            },
            "35": {
                "nodeColor": "black",
                "nodeLabel": "",
                "nodeTy": {
                    "activation": {
                        "tag": "Interactive"
                    },
                    "overflow": "OverflowBlock",
                    "resources": [],
                    "pushPullAction": {
                        "contents": "PullAny",
                        "tag": "Pulling"
                    },
                    "limit": 75,
                    "tag": "Pool"
                }
            },
            "17": {
                "nodeColor": "black",
                "nodeLabel": "",
                "nodeTy": {
                    "registerFormula": {
                        "contents": 0,
                        "tag": "FConstant"
                    },
                    "limits": {},
                    "tag": "RegisterFn"
                }
            },
            "86": {
                "nodeColor": "black",
                "nodeLabel": "",
                "nodeTy": {
                    "registerFormula": {
                        "contents": 0,
                        "tag": "FConstant"
                    },
                    "limits": {},
                    "tag": "RegisterFn"
                }
            },
            "47": {
                "nodeColor": "black",
                "nodeLabel": "",
                "nodeTy": {
                    "resourceTypes": [
                        "Green"
                    ],
                    "pullAction": "PullAny",
                    "activation": {
                        "tag": "Automatic"
                    },
                    "storage": {},
                    "tag": "Converter"
                }
            },
            "33": {
                "nodeColor": "black",
                "nodeLabel": "",
                "nodeTy": {
                    "activation": {
                        "tag": "Interactive"
                    },
                    "overflow": "OverflowBlock",
                    "resources": [],
                    "pushPullAction": {
                        "contents": "PullAll",
                        "tag": "Pulling"
                    },
                    "limit": 151,
                    "tag": "Pool"
                }
            },
            "118": {
                "nodeColor": "black",
                "nodeLabel": "",
                "nodeTy": {
                    "activation": {
                        "tag": "Interactive"
                    },
                    "overflow": "OverflowBlock",
                    "resources": [],
                    "pushPullAction": {
                        "contents": "PullAny",
                        "tag": "Pulling"
                    },
                    "tag": "Pool"
                }
            },
            "99": {
                "nodeColor": "black",
                "nodeLabel": "",
                "nodeTy": {
                    "activation": {
                        "tag": "Interactive"
                    },
                    "overflow": "OverflowBlock",
                    "resources": [],
                    "pushPullAction": {
                        "contents": "PullAny",
                        "tag": "Pulling"
                    },
                    "tag": "Pool"
                }
            },
            "101": {
                "nodeColor": "black",
                "nodeLabel": "",
                "nodeTy": {
                    "activation": {
                        "tag": "Interactive"
                    },
                    "overflow": "OverflowBlock",
                    "resources": [],
                    "pushPullAction": {
                        "contents": "PullAny",
                        "tag": "Pulling"
                    },
                    "tag": "Pool"
                }
            },
            "50": {
                "nodeColor": "black",
                "nodeLabel": "",
                "nodeTy": {
                    "resourceTypes": [
                        "Black"
                    ],
                    "activation": {
                        "tag": "Automatic"
                    },
                    "tag": "Source"
                }
            },
            "36": {
                "nodeColor": "black",
                "nodeLabel": "",
                "nodeTy": {
                    "activation": {
                        "tag": "Interactive"
                    },
                    "overflow": "OverflowBlock",
                    "resources": [],
                    "pushPullAction": {
                        "contents": "PullAny",
                        "tag": "Pulling"
                    },
                    "limit": 75,
                    "tag": "Pool"
                }
            },
            "104": {
                "nodeColor": "black",
                "nodeLabel": "",
                "nodeTy": {
                    "resourceTypes": [
                        "Black"
                    ],
                    "pullAction": "PullAll",
                    "activation": {
                        "tag": "Passive"
                    },
                    "storage": {},
                    "tag": "Converter"
                }
            },
            "5": {
                "nodeColor": "black",
                "nodeLabel": "",
                "nodeTy": {
                    "activation": {
                        "tag": "Passive"
                    },
                    "overflow": "OverflowBlock",
                    "resources": [],
                    "pushPullAction": {
                        "contents": "PushAny",
                        "tag": "Pushing"
                    },
                    "tag": "Pool"
                }
            },
            "49": {
                "nodeColor": "black",
                "nodeLabel": "",
                "nodeTy": {
                    "waitingResources": [],
                    "activation": {
                        "tag": "Passive"
                    },
                    "tag": "Queue"
                }
            },
            "93": {
                "nodeColor": "black",
                "nodeLabel": "",
                "nodeTy": {
                    "activation": {
                        "tag": "Interactive"
                    },
                    "overflow": "OverflowBlock",
                    "resources": [],
                    "pushPullAction": {
                        "contents": "PullAny",
                        "tag": "Pulling"
                    },
                    "tag": "Pool"
                }
            },
            "46": {
                "nodeColor": "black",
                "nodeLabel": "",
                "nodeTy": {
                    "waitingResources": [],
                    "activation": {
                        "tag": "Passive"
                    },
                    "tag": "Queue"
                }
            }
        },
        "resourceEdges": {
            "43": {
                "to": 24,
                "interval": {
                    "counter": 0,
                    "formula": {
                        "contents": 1,
                        "tag": "RFConstant"
                    }
                },
                "resourceFormula": {
                    "contents": 100,
                    "tag": "RFConstant"
                },
                "from": 9,
                "limits": {},
                "shuffleOrigin": false,
                "transfer": "IntervalTransfer"
            },
            "78": {
                "to": 76,
                "interval": {
                    "counter": 0,
                    "formula": {
                        "contents": 1,
                        "tag": "RFConstant"
                    }
                },
                "resourceFormula": {
                    "contents": 1,
                    "tag": "RFConstant"
                },
                "from": 74,
                "limits": {},
                "shuffleOrigin": false,
                "transfer": "IntervalTransfer"
            },
            "61": {
                "to": 58,
                "interval": {
                    "counter": 0,
                    "formula": {
                        "contents": 1,
                        "tag": "RFConstant"
                    }
                },
                "resourceFormula": {
                    "contents": 1,
                    "tag": "RFConstant"
                },
                "from": 60,
                "limits": {},
                "shuffleOrigin": false,
                "transfer": "IntervalTransfer"
            },
            "117": {
                "to": 101,
                "interval": {
                    "counter": 0,
                    "formula": {
                        "contents": 1,
                        "tag": "RFConstant"
                    }
                },
                "resourceFormula": {
                    "contents": 1,
                    "tag": "RFConstant"
                },
                "from": 111,
                "limits": {},
                "shuffleOrigin": false,
                "transfer": "IntervalTransfer"
            },
            "127": {
                "to": 102,
                "interval": {
                    "counter": 0,
                    "formula": {
                        "contents": 1,
                        "tag": "RFConstant"
                    }
                },
                "resourceFormula": {
                    "contents": 25,
                    "tag": "RFConstant"
                },
                "from": 9,
                "limits": {},
                "shuffleOrigin": false,
                "transfer": "IntervalTransfer"
            },
            "105": {
                "to": 95,
                "interval": {
                    "counter": 0,
                    "formula": {
                        "contents": 1,
                        "tag": "RFConstant"
                    }
                },
                "resourceFormula": {
                    "contents": 100,
                    "tag": "RFConstant"
                },
                "from": 9,
                "limits": {},
                "shuffleOrigin": false,
                "transfer": "IntervalTransfer"
            },
            "73": {
                "to": 27,
                "interval": {
                    "counter": 0,
                    "formula": {
                        "contents": 1,
                        "tag": "RFConstant"
                    }
                },
                "resourceFormula": {
                    "contents": 100,
                    "tag": "RFConstant"
                },
                "from": 9,
                "limits": {},
                "shuffleOrigin": false,
                "transfer": "IntervalTransfer"
            },
            "37": {
                "to": 35,
                "interval": {
                    "counter": 0,
                    "formula": {
                        "contents": 1,
                        "tag": "RFConstant"
                    }
                },
                "resourceFormula": {
                    "contents": 75,
                    "tag": "RFConstant"
                },
                "from": 9,
                "limits": {},
                "shuffleOrigin": false,
                "transfer": "IntervalTransfer"
            },
            "108": {
                "to": 96,
                "interval": {
                    "counter": 0,
                    "formula": {
                        "contents": 1,
                        "tag": "RFConstant"
                    }
                },
                "resourceFormula": {
                    "contents": 100,
                    "tag": "RFConstant"
                },
                "from": 45,
                "limits": {},
                "shuffleOrigin": false,
                "transfer": "IntervalTransfer"
            },
            "67": {
                "to": 29,
                "interval": {
                    "counter": 0,
                    "formula": {
                        "contents": 1,
                        "tag": "RFConstant"
                    }
                },
                "resourceFormula": {
                    "contents": 150,
                    "tag": "RFConstant"
                },
                "from": 9,
                "limits": {},
                "shuffleOrigin": false,
                "transfer": "IntervalTransfer"
            },
            "134": {
                "to": 132,
                "interval": {
                    "counter": 0,
                    "formula": {
                        "contents": 1,
                        "tag": "RFConstant"
                    }
                },
                "resourceFormula": {
                    "contents": 400,
                    "tag": "RFConstant"
                },
                "from": 9,
                "limits": {},
                "shuffleOrigin": false,
                "transfer": "IntervalTransfer"
            },
            "116": {
                "to": 100,
                "interval": {
                    "counter": 0,
                    "formula": {
                        "contents": 1,
                        "tag": "RFConstant"
                    }
                },
                "resourceFormula": {
                    "contents": 1,
                    "tag": "RFConstant"
                },
                "from": 104,
                "limits": {},
                "shuffleOrigin": false,
                "transfer": "IntervalTransfer"
            },
            "42": {
                "to": 41,
                "interval": {
                    "counter": 0,
                    "formula": {
                        "contents": 1,
                        "tag": "RFConstant"
                    }
                },
                "resourceFormula": {
                    "contents": 150,
                    "tag": "RFConstant"
                },
                "from": 9,
                "limits": {},
                "shuffleOrigin": false,
                "transfer": "IntervalTransfer"
            },
            "56": {
                "to": 47,
                "interval": {
                    "counter": 0,
                    "formula": {
                        "contents": 1,
                        "tag": "RFConstant"
                    }
                },
                "resourceFormula": {
                    "contents": 1,
                    "tag": "RFConstant"
                },
                "from": 48,
                "limits": {},
                "shuffleOrigin": false,
                "transfer": "IntervalTransfer"
            },
            "12": {
                "to": 9,
                "interval": {
                    "counter": 0,
                    "formula": {
                        "contents": 1,
                        "tag": "RFConstant"
                    }
                },
                "resourceFormula": {
                    "contents": 0,
                    "tag": "RFConstant"
                },
                "from": 10,
                "limits": {},
                "shuffleOrigin": false,
                "transfer": "IntervalTransfer"
            },
            "83": {
                "to": 84,
                "interval": {
                    "counter": 0,
                    "formula": {
                        "contents": 1,
                        "tag": "RFConstant"
                    }
                },
                "resourceFormula": {
                    "contents": 50,
                    "tag": "RFConstant"
                },
                "from": 9,
                "limits": {},
                "shuffleOrigin": false,
                "transfer": "IntervalTransfer"
            },
            "120": {
                "to": 110,
                "interval": {
                    "counter": 0,
                    "formula": {
                        "contents": 1,
                        "tag": "RFConstant"
                    }
                },
                "resourceFormula": {
                    "contents": 100,
                    "tag": "RFConstant"
                },
                "from": 45,
                "limits": {},
                "shuffleOrigin": false,
                "transfer": "IntervalTransfer"
            },
            "8": {
                "to": 6,
                "interval": {
                    "counter": 0,
                    "formula": {
                        "contents": 1,
                        "tag": "RFConstant"
                    }
                },
                "resourceFormula": {
                    "contents": 1,
                    "tag": "RFConstant"
                },
                "from": 4,
                "limits": {},
                "shuffleOrigin": false,
                "transfer": "IntervalTransfer"
            },
            "66": {
                "to": 30,
                "interval": {
                    "counter": 0,
                    "formula": {
                        "contents": 1,
                        "tag": "RFConstant"
                    }
                },
                "resourceFormula": {
                    "contents": 150,
                    "tag": "RFConstant"
                },
                "from": 9,
                "limits": {},
                "shuffleOrigin": false,
                "transfer": "IntervalTransfer"
            },
            "115": {
                "to": 99,
                "interval": {
                    "counter": 0,
                    "formula": {
                        "contents": 1,
                        "tag": "RFConstant"
                    }
                },
                "resourceFormula": {
                    "contents": 1,
                    "tag": "RFConstant"
                },
                "from": 103,
                "limits": {},
                "shuffleOrigin": false,
                "transfer": "IntervalTransfer"
            },
            "121": {
                "to": 109,
                "interval": {
                    "counter": 0,
                    "formula": {
                        "contents": 1,
                        "tag": "RFConstant"
                    }
                },
                "resourceFormula": {
                    "contents": 50,
                    "tag": "RFConstant"
                },
                "from": 45,
                "limits": {},
                "shuffleOrigin": false,
                "transfer": "IntervalTransfer"
            },
            "57": {
                "to": 45,
                "interval": {
                    "counter": 0,
                    "formula": {
                        "contents": 1,
                        "tag": "RFConstant"
                    }
                },
                "resourceFormula": {
                    "contents": 0,
                    "tag": "RFConstant"
                },
                "from": 47,
                "limits": {},
                "shuffleOrigin": false,
                "transfer": "IntervalTransfer"
            },
            "34": {
                "to": 22,
                "interval": {
                    "counter": 0,
                    "formula": {
                        "contents": 1,
                        "tag": "RFConstant"
                    }
                },
                "resourceFormula": {
                    "contents": 100,
                    "tag": "RFConstant"
                },
                "from": 9,
                "limits": {},
                "shuffleOrigin": false,
                "transfer": "IntervalTransfer"
            },
            "16": {
                "to": 13,
                "interval": {
                    "counter": 0,
                    "formula": {
                        "contents": 1,
                        "tag": "RFConstant"
                    }
                },
                "resourceFormula": {
                    "contents": 1,
                    "tag": "RFConstant"
                },
                "from": 15,
                "limits": {},
                "shuffleOrigin": false,
                "transfer": "IntervalTransfer"
            },
            "69": {
                "to": 33,
                "interval": {
                    "counter": 0,
                    "formula": {
                        "contents": 1,
                        "tag": "RFConstant"
                    }
                },
                "resourceFormula": {
                    "contents": 150,
                    "tag": "RFConstant"
                },
                "from": 9,
                "limits": {},
                "shuffleOrigin": false,
                "transfer": "IntervalTransfer"
            },
            "124": {
                "to": 98,
                "interval": {
                    "counter": 0,
                    "formula": {
                        "contents": 1,
                        "tag": "RFConstant"
                    }
                },
                "resourceFormula": {
                    "contents": 100,
                    "tag": "RFConstant"
                },
                "from": 45,
                "limits": {},
                "shuffleOrigin": false,
                "transfer": "IntervalTransfer"
            },
            "106": {
                "to": 97,
                "interval": {
                    "counter": 0,
                    "formula": {
                        "contents": 1,
                        "tag": "RFConstant"
                    }
                },
                "resourceFormula": {
                    "contents": 100,
                    "tag": "RFConstant"
                },
                "from": 9,
                "limits": {},
                "shuffleOrigin": false,
                "transfer": "IntervalTransfer"
            },
            "7": {
                "to": 5,
                "interval": {
                    "counter": 0,
                    "formula": {
                        "contents": 1,
                        "tag": "RFConstant"
                    }
                },
                "resourceFormula": {
                    "contents": 5,
                    "tag": "RFConstant"
                },
                "from": 6,
                "limits": {},
                "shuffleOrigin": false,
                "transfer": "IntervalTransfer"
            },
            "70": {
                "to": 32,
                "interval": {
                    "counter": 0,
                    "formula": {
                        "contents": 1,
                        "tag": "RFConstant"
                    }
                },
                "resourceFormula": {
                    "contents": 150,
                    "tag": "RFConstant"
                },
                "from": 9,
                "limits": {},
                "shuffleOrigin": false,
                "transfer": "IntervalTransfer"
            },
            "52": {
                "to": 46,
                "interval": {
                    "counter": 0,
                    "formula": {
                        "contents": 1,
                        "tag": "RFConstant"
                    }
                },
                "resourceFormula": {
                    "contents": 1,
                    "tag": "RFConstant"
                },
                "from": 44,
                "limits": {},
                "shuffleOrigin": false,
                "transfer": "IntervalTransfer"
            },
            "59": {
                "to": 60,
                "interval": {
                    "counter": 0,
                    "formula": {
                        "contents": 1,
                        "tag": "RFConstant"
                    }
                },
                "resourceFormula": {
                    "contents": 50,
                    "tag": "RFConstant"
                },
                "from": 9,
                "limits": {},
                "shuffleOrigin": false,
                "transfer": "IntervalTransfer"
            },
            "114": {
                "to": 94,
                "interval": {
                    "counter": 0,
                    "formula": {
                        "contents": 1,
                        "tag": "RFConstant"
                    }
                },
                "resourceFormula": {
                    "contents": 1,
                    "tag": "RFConstant"
                },
                "from": 102,
                "limits": {},
                "shuffleOrigin": false,
                "transfer": "IntervalTransfer"
            },
            "40": {
                "to": 28,
                "interval": {
                    "counter": 0,
                    "formula": {
                        "contents": 1,
                        "tag": "RFConstant"
                    }
                },
                "resourceFormula": {
                    "contents": 150,
                    "tag": "RFConstant"
                },
                "from": 9,
                "limits": {},
                "shuffleOrigin": false,
                "transfer": "IntervalTransfer"
            },
            "54": {
                "to": 48,
                "interval": {
                    "counter": 0,
                    "formula": {
                        "contents": 1,
                        "tag": "RFConstant"
                    }
                },
                "resourceFormula": {
                    "contents": 6,
                    "tag": "RFConstant"
                },
                "from": 46,
                "limits": {},
                "shuffleOrigin": false,
                "transfer": "IntervalTransfer"
            },
            "81": {
                "to": 9,
                "interval": {
                    "counter": 0,
                    "formula": {
                        "contents": 1,
                        "tag": "RFConstant"
                    }
                },
                "resourceFormula": {
                    "contents": 0,
                    "tag": "RFConstant"
                },
                "from": 79,
                "limits": {},
                "shuffleOrigin": false,
                "transfer": "IntervalTransfer"
            },
            "119": {
                "to": 110,
                "interval": {
                    "counter": 0,
                    "formula": {
                        "contents": 1,
                        "tag": "RFConstant"
                    }
                },
                "resourceFormula": {
                    "contents": 50,
                    "tag": "RFConstant"
                },
                "from": 9,
                "limits": {},
                "shuffleOrigin": false,
                "transfer": "IntervalTransfer"
            },
            "122": {
                "to": 109,
                "interval": {
                    "counter": 0,
                    "formula": {
                        "contents": 1,
                        "tag": "RFConstant"
                    }
                },
                "resourceFormula": {
                    "contents": 125,
                    "tag": "RFConstant"
                },
                "from": 9,
                "limits": {},
                "shuffleOrigin": false,
                "transfer": "IntervalTransfer"
            },
            "125": {
                "to": 103,
                "interval": {
                    "counter": 0,
                    "formula": {
                        "contents": 1,
                        "tag": "RFConstant"
                    }
                },
                "resourceFormula": {
                    "contents": 100,
                    "tag": "RFConstant"
                },
                "from": 9,
                "limits": {},
                "shuffleOrigin": false,
                "transfer": "IntervalTransfer"
            },
            "107": {
                "to": 96,
                "interval": {
                    "counter": 0,
                    "formula": {
                        "contents": 1,
                        "tag": "RFConstant"
                    }
                },
                "resourceFormula": {
                    "contents": 150,
                    "tag": "RFConstant"
                },
                "from": 9,
                "limits": {},
                "shuffleOrigin": false,
                "transfer": "IntervalTransfer"
            },
            "71": {
                "to": 25,
                "interval": {
                    "counter": 0,
                    "formula": {
                        "contents": 1,
                        "tag": "RFConstant"
                    }
                },
                "resourceFormula": {
                    "contents": 100,
                    "tag": "RFConstant"
                },
                "from": 9,
                "limits": {},
                "shuffleOrigin": false,
                "transfer": "IntervalTransfer"
            },
            "53": {
                "to": 49,
                "interval": {
                    "counter": 0,
                    "formula": {
                        "contents": 1,
                        "tag": "RFConstant"
                    }
                },
                "resourceFormula": {
                    "contents": 1,
                    "tag": "RFConstant"
                },
                "from": 50,
                "limits": {},
                "shuffleOrigin": false,
                "transfer": "IntervalTransfer"
            },
            "68": {
                "to": 31,
                "interval": {
                    "counter": 0,
                    "formula": {
                        "contents": 1,
                        "tag": "RFConstant"
                    }
                },
                "resourceFormula": {
                    "contents": 150,
                    "tag": "RFConstant"
                },
                "from": 9,
                "limits": {},
                "shuffleOrigin": false,
                "transfer": "IntervalTransfer"
            },
            "128": {
                "to": 111,
                "interval": {
                    "counter": 0,
                    "formula": {
                        "contents": 1,
                        "tag": "RFConstant"
                    }
                },
                "resourceFormula": {
                    "contents": 100,
                    "tag": "RFConstant"
                },
                "from": 9,
                "limits": {},
                "shuffleOrigin": false,
                "transfer": "IntervalTransfer"
            },
            "38": {
                "to": 36,
                "interval": {
                    "counter": 0,
                    "formula": {
                        "contents": 1,
                        "tag": "RFConstant"
                    }
                },
                "resourceFormula": {
                    "contents": 75,
                    "tag": "RFConstant"
                },
                "from": 9,
                "limits": {},
                "shuffleOrigin": false,
                "transfer": "IntervalTransfer"
            },
            "131": {
                "to": 111,
                "interval": {
                    "counter": 0,
                    "formula": {
                        "contents": 1,
                        "tag": "RFConstant"
                    }
                },
                "resourceFormula": {
                    "contents": 25,
                    "tag": "RFConstant"
                },
                "from": 45,
                "limits": {},
                "shuffleOrigin": false,
                "transfer": "IntervalTransfer"
            },
            "113": {
                "to": 93,
                "interval": {
                    "counter": 0,
                    "formula": {
                        "contents": 1,
                        "tag": "RFConstant"
                    }
                },
                "resourceFormula": {
                    "contents": 1,
                    "tag": "RFConstant"
                },
                "from": 110,
                "limits": {},
                "shuffleOrigin": false,
                "transfer": "IntervalTransfer"
            },
            "11": {
                "to": 10,
                "interval": {
                    "counter": 0,
                    "formula": {
                        "contents": 1,
                        "tag": "RFConstant"
                    }
                },
                "resourceFormula": {
                    "contents": 1,
                    "tag": "RFConstant"
                },
                "from": 5,
                "limits": {},
                "shuffleOrigin": false,
                "transfer": "IntervalTransfer"
            },
            "80": {
                "to": 79,
                "interval": {
                    "counter": 0,
                    "formula": {
                        "contents": 1,
                        "tag": "RFConstant"
                    }
                },
                "resourceFormula": {
                    "contents": 1,
                    "tag": "RFConstant"
                },
                "from": 75,
                "limits": {},
                "shuffleOrigin": false,
                "transfer": "IntervalTransfer"
            },
            "123": {
                "to": 98,
                "interval": {
                    "counter": 0,
                    "formula": {
                        "contents": 1,
                        "tag": "RFConstant"
                    }
                },
                "resourceFormula": {
                    "contents": 100,
                    "tag": "RFConstant"
                },
                "from": 9,
                "limits": {},
                "shuffleOrigin": false,
                "transfer": "IntervalTransfer"
            },
            "77": {
                "to": 75,
                "interval": {
                    "counter": 0,
                    "formula": {
                        "contents": 1,
                        "tag": "RFConstant"
                    }
                },
                "resourceFormula": {
                    "contents": 5,
                    "tag": "RFConstant"
                },
                "from": 76,
                "limits": {},
                "shuffleOrigin": false,
                "transfer": "IntervalTransfer"
            },
            "55": {
                "to": 48,
                "interval": {
                    "counter": 0,
                    "formula": {
                        "contents": 1,
                        "tag": "RFConstant"
                    }
                },
                "resourceFormula": {
                    "contents": 6,
                    "tag": "RFConstant"
                },
                "from": 49,
                "limits": {},
                "shuffleOrigin": false,
                "transfer": "IntervalTransfer"
            },
            "72": {
                "to": 26,
                "interval": {
                    "counter": 0,
                    "formula": {
                        "contents": 1,
                        "tag": "RFConstant"
                    }
                },
                "resourceFormula": {
                    "contents": 100,
                    "tag": "RFConstant"
                },
                "from": 9,
                "limits": {},
                "shuffleOrigin": false,
                "transfer": "IntervalTransfer"
            },
            "14": {
                "to": 15,
                "interval": {
                    "counter": 0,
                    "formula": {
                        "contents": 1,
                        "tag": "RFConstant"
                    }
                },
                "resourceFormula": {
                    "contents": 50,
                    "tag": "RFConstant"
                },
                "from": 9,
                "limits": {},
                "shuffleOrigin": false,
                "transfer": "IntervalTransfer"
            },
            "85": {
                "to": 82,
                "interval": {
                    "counter": 0,
                    "formula": {
                        "contents": 1,
                        "tag": "RFConstant"
                    }
                },
                "resourceFormula": {
                    "contents": 1,
                    "tag": "RFConstant"
                },
                "from": 84,
                "limits": {},
                "shuffleOrigin": false,
                "transfer": "IntervalTransfer"
            },
            "126": {
                "to": 104,
                "interval": {
                    "counter": 0,
                    "formula": {
                        "contents": 1,
                        "tag": "RFConstant"
                    }
                },
                "resourceFormula": {
                    "contents": 275,
                    "tag": "RFConstant"
                },
                "from": 9,
                "limits": {},
                "shuffleOrigin": false,
                "transfer": "IntervalTransfer"
            },
            "39": {
                "to": 23,
                "interval": {
                    "counter": 0,
                    "formula": {
                        "contents": 1,
                        "tag": "RFConstant"
                    }
                },
                "resourceFormula": {
                    "contents": 150,
                    "tag": "RFConstant"
                },
                "from": 9,
                "limits": {},
                "shuffleOrigin": false,
                "transfer": "IntervalTransfer"
            },
            "130": {
                "to": 102,
                "interval": {
                    "counter": 0,
                    "formula": {
                        "contents": 1,
                        "tag": "RFConstant"
                    }
                },
                "resourceFormula": {
                    "contents": 75,
                    "tag": "RFConstant"
                },
                "from": 45,
                "limits": {},
                "shuffleOrigin": false,
                "transfer": "IntervalTransfer"
            },
            "112": {
                "to": 118,
                "interval": {
                    "counter": 0,
                    "formula": {
                        "contents": 1,
                        "tag": "RFConstant"
                    }
                },
                "resourceFormula": {
                    "contents": 1,
                    "tag": "RFConstant"
                },
                "from": 109,
                "limits": {},
                "shuffleOrigin": false,
                "transfer": "IntervalTransfer"
            },
            "129": {
                "to": 104,
                "interval": {
                    "counter": 0,
                    "formula": {
                        "contents": 1,
                        "tag": "RFConstant"
                    }
                },
                "resourceFormula": {
                    "contents": 100,
                    "tag": "RFConstant"
                },
                "from": 45,
                "limits": {},
                "shuffleOrigin": false,
                "transfer": "IntervalTransfer"
            }
        }
    },
    "time": 0
}