<?xml version="1.0"?>
<mxGraphModel dx="2323" dy="1698.25" grid="1" tooltips="1" fold="1" page="1" pageScale="0.75" pageWidth="1169" pageHeight="827" background="#ffffff" document_owner="Machinations Support" document_creation_date="1581934534791" document_last_change_date="1606308770623" time_interval="1" diagram_time_steps_limit="100" diagram_number_of_total_runs="20" zoomFactorProp="0.811789038262668" diagramScrollTop="1332" diagramScrollLeft="1583">
  <root>
    <mxCell id="0"/>
    <mxCell id="1" parent="0"/>
    <mxResourceConnectionCell id="2" value="&lt;span&gt;3&lt;/span&gt;&lt;span&gt;&lt;/span&gt;&lt;span&gt;&lt;/span&gt;&lt;span&gt;&lt;/span&gt;&lt;span&gt;&lt;/span&gt;" style="shape=resource-connection;endArrow=classic;html=1;strokeWidth=2;fontSize=16;fontColor=#000000;strokeColor=#000000;exitX=0.25;exitY=0.5;exitPerimeter=0;entryX=0.5;entryY=0;entryPerimeter=0;align=left;" title="Resource Connection" vertex="0" edge="1" parent="1" source="4" target="14" type="plain-arrow" resourceTransfer="interval-based" colorCoding="0" minValue="-9999" maxValue="9999" shuffleSource="0" isMachination="1" width="60" height="60" activation="passive" blinkStatus="0" connectable="1" visible="1" collapsed="0" label="&lt;span&gt;3&lt;/span&gt;&lt;span&gt;&lt;/span&gt;&lt;span&gt;&lt;/span&gt;&lt;span&gt;&lt;/span&gt;&lt;span&gt;&lt;/span&gt;">
      <mxGeometry x="-0.05434782608695652" y="9" width="60" height="60" relative="1" TRANSLATE_CONTROL_POINTS="1" as="geometry">
        <mxPoint x="0" y="0" as="offset"/>
        <Array as="points">
          <mxPoint x="280" y="60"/>
        </Array>
      </mxGeometry>
      <Resource name="Black" color="#000000" travelTime="0" as="resource"/>
    </mxResourceConnectionCell>
    <mxResourceConnectionCell id="3" value="&lt;span&gt;5&lt;/span&gt;&lt;span&gt;&lt;/span&gt;&lt;span&gt;&lt;/span&gt;&lt;span&gt;&lt;/span&gt;&lt;span&gt;&lt;/span&gt;" style="shape=resource-connection;endArrow=classic;html=1;strokeWidth=2;fontSize=16;fontColor=#000000;strokeColor=#000000;exitX=0.5;exitY=0.9;exitPerimeter=0;entryX=0.5;entryY=0;entryPerimeter=0;" title="Resource Connection" vertex="0" edge="1" parent="1" source="4" target="20" type="plain-arrow" resourceTransfer="interval-based" colorCoding="0" minValue="-9999" maxValue="9999" shuffleSource="0" isMachination="1" width="60" height="60" activation="passive" blinkStatus="0" connectable="1" visible="1" collapsed="0" label="&lt;span&gt;5&lt;/span&gt;&lt;span&gt;&lt;/span&gt;&lt;span&gt;&lt;/span&gt;&lt;span&gt;&lt;/span&gt;&lt;span&gt;&lt;/span&gt;">
      <mxGeometry x="0" y="0" width="60" height="60" relative="1" TRANSLATE_CONTROL_POINTS="1" as="geometry">
        <mxPoint x="20" y="20" as="offset"/>
      </mxGeometry>
      <Resource name="Black" color="#000000" travelTime="0" as="resource"/>
    </mxResourceConnectionCell>
    <mxSourceShapeCell id="4" style="shape=source-shape;whiteSpace=wrap;html=1;strokeWidth=2;aspect=fixed;resizable=0;fontSize=16;fontColor=#000000;strokeColor=#000000;" title="Source" vertex="1" edge="0" parent="1" activation="onstart" isMachination="1" blinkStatus="0" connectable="1" visible="1" collapsed="0" label="Gathering Ingredients">
      <mxGeometry x="597" y="37" width="46" height="46" TRANSLATE_CONTROL_POINTS="1" relative="0" vertexOrientation="top" as="geometry">
        <mxPoint x="-1.5" y="-58" as="offset"/>
      </mxGeometry>
      <Resource name="Black" color="#000000" travelTime="0" as="resource"/>
    </mxSourceShapeCell>
    <mxResourceConnectionCell id="5" value="&lt;span&gt;&lt;/span&gt;&lt;span&gt;&lt;/span&gt;&lt;span&gt;&lt;/span&gt;&lt;span&gt;&lt;/span&gt;&lt;span&gt;&lt;/span&gt;" style="shape=resource-connection;endArrow=classic;html=1;strokeWidth=2;fontSize=16;fontColor=#0066CC;strokeColor=#0066CC;exitX=0.5;exitY=1;exitPerimeter=0;entryX=0;entryY=0.5;entryPerimeter=0;" title="Resource Connection" vertex="0" edge="1" parent="1" source="6" target="16" type="plain-arrow" resourceTransfer="interval-based" colorCoding="0" minValue="-9999" maxValue="9999" shuffleSource="0" isMachination="1" width="60" height="60" activation="passive" blinkStatus="0" connectable="1" visible="1" collapsed="0" label="&lt;span&gt;&lt;/span&gt;&lt;span&gt;&lt;/span&gt;&lt;span&gt;&lt;/span&gt;&lt;span&gt;&lt;/span&gt;&lt;span&gt;&lt;/span&gt;">
      <mxGeometry x="0" y="0" width="60" height="60" relative="1" TRANSLATE_CONTROL_POINTS="1" as="geometry">
        <mxPoint x="20" y="20" as="offset"/>
        <Array as="points">
          <mxPoint x="120" y="430.5"/>
        </Array>
      </mxGeometry>
      <Resource name="Black" color="#000000" travelTime="0" as="resource"/>
    </mxResourceConnectionCell>
    <mxPoolShapeCell id="6" style="shape=pool-shape;whiteSpace=wrap;html=1;strokeWidth=2;aspect=fixed;resizable=0;fontSize=16;fontColor=#0066CC;strokeColor=#0066CC;" title="Pool" vertex="1" edge="0" parent="1" activation="passive" actionMode="push-any" number="0" capacity="-1" displayCapacity="0" overflow="block" isMachination="1" blinkStatus="0" connectable="1" visible="1" collapsed="0" label="White Myrtle Pettals">
      <mxGeometry x="97" y="267.5" width="46" height="46" TRANSLATE_CONTROL_POINTS="1" relative="0" vertexOrientation="left" as="geometry">
        <mxPoint x="-67.5" y="-3.5" as="offset"/>
      </mxGeometry>
      <Resource name="Black" color="#000000" travelTime="0" as="resource"/>
    </mxPoolShapeCell>
    <mxResourceConnectionCell id="7" value="&lt;span&gt;&lt;/span&gt;&lt;span&gt;&lt;/span&gt;&lt;span&gt;&lt;/span&gt;&lt;span&gt;&lt;/span&gt;&lt;span&gt;&lt;/span&gt;" style="shape=resource-connection;endArrow=classic;html=1;strokeWidth=2;fontSize=16;fontColor=#0066CC;strokeColor=#0066CC;exitX=0.5;exitY=1;exitPerimeter=0;entryX=0.5;entryY=0;entryPerimeter=0;" title="Resource Connection" vertex="0" edge="1" parent="1" source="8" target="16" type="plain-arrow" resourceTransfer="interval-based" colorCoding="0" minValue="-9999" maxValue="9999" shuffleSource="0" isMachination="1" width="60" height="60" activation="passive" blinkStatus="0" connectable="1" visible="1" collapsed="0" label="&lt;span&gt;&lt;/span&gt;&lt;span&gt;&lt;/span&gt;&lt;span&gt;&lt;/span&gt;&lt;span&gt;&lt;/span&gt;&lt;span&gt;&lt;/span&gt;">
      <mxGeometry x="0" y="0" width="60" height="60" relative="1" TRANSLATE_CONTROL_POINTS="1" as="geometry">
        <mxPoint x="20" y="20" as="offset"/>
      </mxGeometry>
      <Resource name="Black" color="#000000" travelTime="0" as="resource"/>
    </mxResourceConnectionCell>
    <mxPoolShapeCell id="8" style="shape=pool-shape;whiteSpace=wrap;html=1;strokeWidth=2;aspect=fixed;resizable=0;fontSize=16;fontColor=#0066CC;strokeColor=#0066CC;" title="Pool" vertex="1" edge="0" parent="1" activation="passive" actionMode="push-any" number="0" capacity="-1" displayCapacity="0" overflow="block" isMachination="1" blinkStatus="0" connectable="1" visible="1" collapsed="0" label="Mahakaman Spirit">
      <mxGeometry x="257" y="267.5" width="46" height="46" TRANSLATE_CONTROL_POINTS="1" relative="0" vertexOrientation="topRight" as="geometry">
        <mxPoint x="74" y="-28" as="offset"/>
      </mxGeometry>
      <Resource name="Black" color="#000000" travelTime="0" as="resource"/>
    </mxPoolShapeCell>
    <mxResourceConnectionCell id="9" value="&lt;span&gt;&lt;/span&gt;&lt;span&gt;&lt;/span&gt;&lt;span&gt;&lt;/span&gt;&lt;span&gt;&lt;/span&gt;&lt;span&gt;&lt;/span&gt;" style="shape=resource-connection;endArrow=classic;html=1;strokeWidth=2;fontSize=16;fontColor=#0066CC;strokeColor=#0066CC;exitX=0.5;exitY=1;exitPerimeter=0;entryX=0.9;entryY=0.5;entryPerimeter=0;" title="Resource Connection" vertex="0" edge="1" parent="1" source="10" target="16" type="plain-arrow" resourceTransfer="interval-based" colorCoding="0" minValue="-9999" maxValue="9999" shuffleSource="0" isMachination="1" width="60" height="60" activation="passive" blinkStatus="0" connectable="1" visible="1" collapsed="0" label="&lt;span&gt;&lt;/span&gt;&lt;span&gt;&lt;/span&gt;&lt;span&gt;&lt;/span&gt;&lt;span&gt;&lt;/span&gt;&lt;span&gt;&lt;/span&gt;">
      <mxGeometry x="0" y="0" width="60" height="60" relative="1" TRANSLATE_CONTROL_POINTS="1" as="geometry">
        <mxPoint x="20" y="20" as="offset"/>
        <Array as="points">
          <mxPoint x="450" y="430.5"/>
        </Array>
      </mxGeometry>
      <Resource name="Black" color="#000000" travelTime="0" as="resource"/>
    </mxResourceConnectionCell>
    <mxPoolShapeCell id="10" style="shape=pool-shape;whiteSpace=wrap;html=1;strokeWidth=2;aspect=fixed;resizable=0;fontSize=16;fontColor=#0066CC;strokeColor=#0066CC;" title="Pool" vertex="1" edge="0" parent="1" activation="passive" actionMode="push-any" number="0" capacity="-1" displayCapacity="0" overflow="block" isMachination="1" blinkStatus="0" connectable="1" visible="1" collapsed="0" label="Celandine">
      <mxGeometry x="427" y="267.5" width="46" height="46" TRANSLATE_CONTROL_POINTS="1" relative="0" vertexOrientation="topRight" as="geometry">
        <mxPoint x="60" y="-28.5" as="offset"/>
      </mxGeometry>
      <Resource name="Black" color="#000000" travelTime="0" as="resource"/>
    </mxPoolShapeCell>
    <mxResourceConnectionCell id="11" value="&lt;span&gt;1&lt;/span&gt;&lt;span&gt;&lt;/span&gt;&lt;span&gt;&lt;/span&gt;&lt;span&gt;&lt;/span&gt;&lt;span&gt;&lt;/span&gt;" style="shape=resource-connection;endArrow=classic;html=1;strokeWidth=2;fontSize=16;fontColor=#0066CC;strokeColor=#0066CC;exitX=0;exitY=0.5;exitPerimeter=0;entryX=0.5;entryY=0;entryPerimeter=0;align=center;" title="Resource Connection" vertex="0" edge="1" parent="1" source="14" target="6" type="plain-arrow" resourceTransfer="interval-based" colorCoding="0" minValue="-9999" maxValue="9999" shuffleSource="0" isMachination="1" width="60" height="60" activation="passive" blinkStatus="0" connectable="1" visible="1" collapsed="0" label="&lt;span&gt;1&lt;/span&gt;&lt;span&gt;&lt;/span&gt;&lt;span&gt;&lt;/span&gt;&lt;span&gt;&lt;/span&gt;&lt;span&gt;&lt;/span&gt;">
      <mxGeometry x="0.023809523809523808" y="19.5" width="60" height="60" relative="1" TRANSLATE_CONTROL_POINTS="1" as="geometry">
        <mxPoint x="0" y="0" as="offset"/>
        <Array as="points">
          <mxPoint x="120" y="180.5"/>
        </Array>
      </mxGeometry>
      <Resource name="Black" color="#000000" travelTime="0" as="resource"/>
    </mxResourceConnectionCell>
    <mxResourceConnectionCell id="12" value="&lt;span&gt;1&lt;/span&gt;&lt;span&gt;&lt;/span&gt;&lt;span&gt;&lt;/span&gt;&lt;span&gt;&lt;/span&gt;&lt;span&gt;&lt;/span&gt;" style="shape=resource-connection;endArrow=classic;html=1;strokeWidth=2;fontSize=16;fontColor=#0066CC;strokeColor=#0066CC;exitX=0.5;exitY=1;exitPerimeter=0;entryX=0.5;entryY=0;entryPerimeter=0;align=left;" title="Resource Connection" vertex="0" edge="1" parent="1" source="14" target="8" type="plain-arrow" resourceTransfer="interval-based" colorCoding="0" minValue="-9999" maxValue="9999" shuffleSource="0" isMachination="1" width="60" height="60" activation="passive" blinkStatus="0" connectable="1" visible="1" collapsed="0" label="&lt;span&gt;1&lt;/span&gt;&lt;span&gt;&lt;/span&gt;&lt;span&gt;&lt;/span&gt;&lt;span&gt;&lt;/span&gt;&lt;span&gt;&lt;/span&gt;">
      <mxGeometry x="-0.5" y="9" width="60" height="60" relative="1" TRANSLATE_CONTROL_POINTS="1" as="geometry">
        <mxPoint x="0" y="0" as="offset"/>
      </mxGeometry>
      <Resource name="Black" color="#000000" travelTime="0" as="resource"/>
    </mxResourceConnectionCell>
    <mxResourceConnectionCell id="13" value="&lt;span&gt;1&lt;/span&gt;&lt;span&gt;&lt;/span&gt;&lt;span&gt;&lt;/span&gt;&lt;span&gt;&lt;/span&gt;&lt;span&gt;&lt;/span&gt;" style="shape=resource-connection;endArrow=classic;html=1;strokeWidth=2;fontSize=16;fontColor=#0066CC;strokeColor=#0066CC;exitX=1;exitY=0.5;exitPerimeter=0;entryX=0.5;entryY=0;entryPerimeter=0;" title="Resource Connection" vertex="0" edge="1" parent="1" source="14" target="10" type="plain-arrow" resourceTransfer="interval-based" colorCoding="0" minValue="-9999" maxValue="9999" shuffleSource="0" isMachination="1" width="60" height="60" activation="passive" blinkStatus="0" connectable="1" visible="1" collapsed="0" label="&lt;span&gt;1&lt;/span&gt;&lt;span&gt;&lt;/span&gt;&lt;span&gt;&lt;/span&gt;&lt;span&gt;&lt;/span&gt;&lt;span&gt;&lt;/span&gt;">
      <mxGeometry x="0" y="0" width="60" height="60" relative="1" TRANSLATE_CONTROL_POINTS="1" as="geometry">
        <mxPoint x="20" y="20" as="offset"/>
        <Array as="points">
          <mxPoint x="450" y="180.5"/>
        </Array>
      </mxGeometry>
      <Resource name="Black" color="#000000" travelTime="0" as="resource"/>
    </mxResourceConnectionCell>
    <mxGateShapeCell id="14" style="shape=gate-shape;whiteSpace=wrap;html=1;strokeWidth=2;aspect=fixed;resizable=0;fontSize=16;fontColor=#0066CC;strokeColor=#0066CC;" title="Gate" vertex="1" edge="0" parent="1" actionMode="pull-any" distributionMode="deterministic" isMachination="1" activation="passive" blinkStatus="0" connectable="1" visible="1" collapsed="0" label="">
      <mxGeometry x="257" y="157.5" width="46" height="46" TRANSLATE_CONTROL_POINTS="1" relative="0" as="geometry">
        <mxPoint x="0" y="40" as="offset"/>
      </mxGeometry>
    </mxGateShapeCell>
    <mxResourceConnectionCell id="15" value="&lt;span&gt;&lt;/span&gt;&lt;span&gt;&lt;/span&gt;&lt;span&gt;&lt;/span&gt;&lt;span&gt;&lt;/span&gt;&lt;span&gt;&lt;/span&gt;" style="shape=resource-connection;endArrow=classic;html=1;strokeWidth=2;fontSize=16;fontColor=#0066CC;strokeColor=#0066CC;exitX=0.5;exitY=1;exitPerimeter=0;" title="Resource Connection" vertex="0" edge="1" parent="1" source="16" target="18" type="plain-arrow" resourceTransfer="interval-based" colorCoding="0" minValue="-9999" maxValue="9999" shuffleSource="0" isMachination="1" width="60" height="60" activation="passive" blinkStatus="0" connectable="1" visible="1" collapsed="0" label="&lt;span&gt;&lt;/span&gt;&lt;span&gt;&lt;/span&gt;&lt;span&gt;&lt;/span&gt;&lt;span&gt;&lt;/span&gt;&lt;span&gt;&lt;/span&gt;">
      <mxGeometry x="0" y="0" width="60" height="60" relative="1" TRANSLATE_CONTROL_POINTS="1" as="geometry">
        <mxPoint x="20" y="20" as="offset"/>
      </mxGeometry>
      <Resource name="Black" color="#000000" travelTime="0" as="resource"/>
    </mxResourceConnectionCell>
    <mxConverterShapeCell id="16" style="shape=converter-shape;whiteSpace=wrap;html=1;strokeWidth=2;aspect=fixed;resizable=0;fontSize=16;fontColor=#0066CC;strokeColor=#0066CC;" title="Converter" vertex="1" edge="0" parent="1" activation="automatic" actionMode="pull-all" isMachination="1" blinkStatus="0" connectable="1" visible="1" collapsed="0" label="">
      <mxGeometry x="257" y="407.5" width="46" height="46" TRANSLATE_CONTROL_POINTS="1" relative="0" as="geometry">
        <mxPoint x="0" y="40" as="offset"/>
      </mxGeometry>
      <Resource name="Black" color="#000000" travelTime="0" as="resource"/>
    </mxConverterShapeCell>
    <mxResourceConnectionCell id="17" value="&lt;span&gt;1&lt;/span&gt;&lt;span&gt;&lt;/span&gt;&lt;span&gt;&lt;/span&gt;&lt;span&gt;&lt;/span&gt;&lt;span&gt;&lt;/span&gt;" style="shape=resource-connection;endArrow=classic;html=1;strokeWidth=2;fontSize=16;fontColor=#000000;strokeColor=#000000;exitX=0.5;exitY=1;exitPerimeter=0;entryX=0;entryY=0.5;entryPerimeter=0;" title="Resource Connection" vertex="0" edge="1" parent="1" source="18" target="34" type="plain-arrow" resourceTransfer="interval-based" colorCoding="0" minValue="-9999" maxValue="9999" shuffleSource="0" isMachination="1" width="60" height="60" activation="passive" blinkStatus="0" connectable="1" visible="1" collapsed="0" label="&lt;span&gt;1&lt;/span&gt;&lt;span&gt;&lt;/span&gt;&lt;span&gt;&lt;/span&gt;&lt;span&gt;&lt;/span&gt;&lt;span&gt;&lt;/span&gt;">
      <mxGeometry x="0" y="0" width="60" height="60" relative="1" TRANSLATE_CONTROL_POINTS="1" as="geometry">
        <mxPoint x="580" y="770" as="targetPoint"/>
        <mxPoint x="20" y="20" as="offset"/>
        <Array as="points">
          <mxPoint x="280" y="710"/>
        </Array>
      </mxGeometry>
      <Resource name="Black" color="#000000" travelTime="0" as="resource"/>
    </mxResourceConnectionCell>
    <mxPoolShapeCell id="18" style="shape=pool-shape;whiteSpace=wrap;html=1;strokeWidth=2;aspect=fixed;resizable=0;fontSize=16;fontColor=#0066CC;strokeColor=#0066CC;" title="Pool" vertex="1" edge="0" parent="1" activation="passive" actionMode="push-any" number="0" capacity="-1" displayCapacity="0" overflow="block" isMachination="1" blinkStatus="0" connectable="1" visible="1" collapsed="0" label="Dwarven Spirit">
      <mxGeometry x="257" y="527.5" width="46" height="46" TRANSLATE_CONTROL_POINTS="1" relative="0" vertexOrientation="left" as="geometry">
        <mxPoint x="-71.5" y="-8" as="offset"/>
      </mxGeometry>
      <Resource name="Black" color="#000000" travelTime="0" as="resource"/>
    </mxPoolShapeCell>
    <mxResourceConnectionCell id="19" value="&lt;span&gt;5&lt;/span&gt;&lt;span&gt;&lt;/span&gt;&lt;span&gt;&lt;/span&gt;&lt;span&gt;&lt;/span&gt;&lt;span&gt;&lt;/span&gt;" style="shape=resource-connection;endArrow=classic;html=1;strokeWidth=2;fontSize=16;fontColor=#000000;strokeColor=#000000;exitX=0.5;exitY=1;exitPerimeter=0;entryX=0.5;entryY=0;entryPerimeter=0;" title="Resource Connection" vertex="0" edge="1" parent="1" source="20" target="34" type="plain-arrow" resourceTransfer="interval-based" colorCoding="0" minValue="-9999" maxValue="9999" shuffleSource="0" isMachination="1" width="60" height="60" activation="passive" blinkStatus="0" connectable="1" visible="1" collapsed="0" label="&lt;span&gt;5&lt;/span&gt;&lt;span&gt;&lt;/span&gt;&lt;span&gt;&lt;/span&gt;&lt;span&gt;&lt;/span&gt;&lt;span&gt;&lt;/span&gt;">
      <mxGeometry x="0" y="0" width="60" height="60" relative="1" TRANSLATE_CONTROL_POINTS="1" as="geometry">
        <mxPoint x="20" y="20" as="offset"/>
      </mxGeometry>
      <Resource name="Black" color="#000000" travelTime="0" as="resource"/>
    </mxResourceConnectionCell>
    <mxPoolShapeCell id="20" style="shape=pool-shape;whiteSpace=wrap;html=1;strokeWidth=2;aspect=fixed;resizable=0;fontSize=16;fontColor=#009900;strokeColor=#009900;" title="Pool" vertex="1" edge="0" parent="1" activation="passive" actionMode="push-any" number="0" capacity="-1" displayCapacity="0" overflow="block" isMachination="1" blinkStatus="0" connectable="1" visible="1" collapsed="0" label="Celandine">
      <mxGeometry x="597" y="527" width="46" height="46" TRANSLATE_CONTROL_POINTS="1" relative="0" vertexOrientation="left" as="geometry">
        <mxPoint x="-75" y="-7.5" as="offset"/>
      </mxGeometry>
      <Resource name="Black" color="#000000" travelTime="0" as="resource"/>
    </mxPoolShapeCell>
    <mxResourceConnectionCell id="21" value="&lt;span&gt;20&lt;/span&gt;&lt;span&gt;&lt;/span&gt;&lt;span&gt;&lt;/span&gt;&lt;span&gt;&lt;/span&gt;&lt;span&gt;&lt;/span&gt;" style="shape=resource-connection;endArrow=classic;html=1;strokeWidth=2;fontSize=16;fontColor=#FF0000;strokeColor=#FF0000;exitX=1;exitY=0.5;exitPerimeter=0;entryX=0.25;entryY=0.5;entryPerimeter=0;align=center;" title="Resource Connection" vertex="0" edge="1" parent="1" source="22" target="24" type="plain-arrow" resourceTransfer="interval-based" colorCoding="0" minValue="-9999" maxValue="9999" shuffleSource="0" isMachination="1" width="60" height="60" activation="passive" blinkStatus="0" connectable="1" visible="1" collapsed="0" label="&lt;span&gt;20&lt;/span&gt;&lt;span&gt;&lt;/span&gt;&lt;span&gt;&lt;/span&gt;&lt;span&gt;&lt;/span&gt;&lt;span&gt;&lt;/span&gt;">
      <mxGeometry x="0.1608695652173913" y="-19.5" width="60" height="60" relative="1" TRANSLATE_CONTROL_POINTS="1" as="geometry">
        <mxPoint x="0" y="0" as="offset"/>
      </mxGeometry>
      <Resource name="Black" color="#000000" travelTime="0" as="resource"/>
    </mxResourceConnectionCell>
    <mxPoolShapeCell id="22" style="shape=pool-shape;whiteSpace=wrap;html=1;strokeWidth=2;aspect=fixed;resizable=0;fontSize=16;fontColor=#FF0000;strokeColor=#FF0000;" title="Pool" vertex="1" edge="0" parent="1" activation="passive" actionMode="push-any" number="600" capacity="-1" displayCapacity="0" overflow="block" isMachination="1" blinkStatus="0" connectable="1" visible="1" collapsed="0" label="Geralt HP">
      <mxGeometry x="747" y="117" width="46" height="46" TRANSLATE_CONTROL_POINTS="1" relative="0" vertexOrientation="left" as="geometry">
        <mxPoint x="-67.5" y="-2" as="offset"/>
      </mxGeometry>
      <Resource name="Black" color="#000000" travelTime="0" as="resource"/>
    </mxPoolShapeCell>
    <mxDrainShapeCell id="23" style="shape=drain-shape;whiteSpace=wrap;html=1;strokeWidth=2;aspect=fixed;resizable=0;fontSize=16;fontColor=#FF0000;strokeColor=#FF0000;" title="Drain" vertex="1" edge="0" parent="1" activation="automatic" actionMode="pull-any" isMachination="1" blinkStatus="0" connectable="1" visible="1" collapsed="0" label="">
      <mxGeometry x="907" y="277" width="46" height="46" TRANSLATE_CONTROL_POINTS="1" relative="0" as="geometry">
        <mxPoint x="0" y="40" as="offset"/>
      </mxGeometry>
    </mxDrainShapeCell>
    <mxDrainShapeCell id="24" style="shape=drain-shape;whiteSpace=wrap;html=1;strokeWidth=2;aspect=fixed;resizable=0;fontSize=16;fontColor=#FF0000;strokeColor=#FF0000;" title="Drain" vertex="1" edge="0" parent="1" activation="automatic" actionMode="pull-any" isMachination="1" blinkStatus="0" connectable="1" visible="1" collapsed="0" label="">
      <mxGeometry x="907" y="117" width="46" height="46" TRANSLATE_CONTROL_POINTS="1" relative="0" as="geometry">
        <mxPoint x="0" y="40" as="offset"/>
      </mxGeometry>
    </mxDrainShapeCell>
    <mxStateConnectionCell id="25" value="&lt;span&gt;&gt;0&lt;/span&gt;&lt;span&gt;&lt;/span&gt;&lt;span&gt;&lt;/span&gt;&lt;span&gt;&lt;/span&gt;&lt;span&gt;&lt;/span&gt;" style="shape=state-connection;endArrow=classic;dashed=1;dashPattern=4 3;html=1;strokeWidth=2;fontSize=16;fontColor=#FF0000;strokeColor=#FF0000;entryX=0.25;entryY=0.5;entryPerimeter=0;exitX=0.5;exitY=1;exitPerimeter=0;align=left;" title="State Connection" vertex="0" edge="1" parent="1" source="22" target="23" type="4" colorCoding="0" isMachination="1" width="60" height="60" activation="passive" blinkStatus="0" connectable="1" visible="1" collapsed="0" label="&lt;span&gt;&amp;gt;0&lt;/span&gt;&lt;span&gt;&lt;/span&gt;&lt;span&gt;&lt;/span&gt;&lt;span&gt;&lt;/span&gt;&lt;span&gt;&lt;/span&gt;">
      <mxGeometry x="0.25445546902180316" y="11.78605453248111" width="60" height="60" relative="1" TRANSLATE_CONTROL_POINTS="1" as="geometry">
        <mxPoint x="740" y="310" as="sourcePoint"/>
        <mxPoint x="800" y="250" as="targetPoint"/>
        <mxPoint x="0" y="0" as="offset"/>
      </mxGeometry>
      <Resource name="Black" color="#000000" travelTime="0" as="resource"/>
    </mxStateConnectionCell>
    <mxResourceConnectionCell id="26" value="&lt;span&gt;30&lt;/span&gt;&lt;span&gt;&lt;/span&gt;&lt;span&gt;&lt;/span&gt;&lt;span&gt;&lt;/span&gt;&lt;span&gt;&lt;/span&gt;" style="shape=resource-connection;endArrow=classic;html=1;strokeWidth=2;fontSize=16;fontColor=#FF0000;strokeColor=#FF0000;exitX=0.5;exitY=1;exitPerimeter=0;entryX=0.75;entryY=0.5;entryPerimeter=0;" title="Resource Connection" vertex="0" edge="1" parent="1" source="27" target="23" type="plain-arrow" resourceTransfer="interval-based" colorCoding="0" minValue="-9999" maxValue="9999" shuffleSource="0" isMachination="1" width="60" height="60" activation="passive" blinkStatus="0" connectable="1" visible="1" collapsed="0" label="&lt;span&gt;30&lt;/span&gt;&lt;span&gt;&lt;/span&gt;&lt;span&gt;&lt;/span&gt;&lt;span&gt;&lt;/span&gt;&lt;span&gt;&lt;/span&gt;">
      <mxGeometry x="0" y="0" width="60" height="60" relative="1" TRANSLATE_CONTROL_POINTS="1" as="geometry">
        <mxPoint x="20" y="20" as="offset"/>
        <Array as="points">
          <mxPoint x="1110" y="300"/>
        </Array>
      </mxGeometry>
      <Resource name="Black" color="#000000" travelTime="0" as="resource"/>
    </mxResourceConnectionCell>
    <mxPoolShapeCell id="27" style="shape=pool-shape;whiteSpace=wrap;html=1;strokeWidth=2;aspect=fixed;resizable=0;fontSize=16;fontColor=#FF0000;strokeColor=#FF0000;" title="Pool" vertex="1" edge="0" parent="1" activation="passive" actionMode="push-any" number="150" capacity="-1" displayCapacity="25" overflow="block" isMachination="1" blinkStatus="0" connectable="1" visible="1" collapsed="0" label="Drowner HP">
      <mxGeometry x="1087" y="117" width="46" height="46" TRANSLATE_CONTROL_POINTS="1" relative="0" vertexOrientation="top" as="geometry">
        <mxPoint x="-7.5" y="-56" as="offset"/>
      </mxGeometry>
      <Resource name="Black" color="#000000" travelTime="0" as="resource"/>
    </mxPoolShapeCell>
    <mxStateConnectionCell id="28" value="&lt;span&gt;&gt;0&lt;/span&gt;&lt;span&gt;&lt;/span&gt;&lt;span&gt;&lt;/span&gt;&lt;span&gt;&lt;/span&gt;&lt;span&gt;&lt;/span&gt;" style="shape=state-connection;endArrow=classic;dashed=1;dashPattern=4 3;html=1;strokeWidth=2;fontSize=16;fontColor=#FF0000;strokeColor=#FF0000;entryX=0.75;entryY=0.5;entryPerimeter=0;exitX=0;exitY=0.5;exitPerimeter=0;align=center;" title="State Connection" vertex="0" edge="1" parent="1" source="27" target="24" type="4" colorCoding="0" isMachination="1" width="60" height="60" activation="passive" blinkStatus="0" connectable="1" visible="1" collapsed="0" label="&lt;span&gt;&amp;gt;0&lt;/span&gt;&lt;span&gt;&lt;/span&gt;&lt;span&gt;&lt;/span&gt;&lt;span&gt;&lt;/span&gt;&lt;span&gt;&lt;/span&gt;">
      <mxGeometry x="-0.23333333333333334" y="-19.5" width="60" height="60" relative="1" TRANSLATE_CONTROL_POINTS="1" as="geometry">
        <mxPoint x="1010" y="30" as="sourcePoint"/>
        <mxPoint x="1070" y="-30" as="targetPoint"/>
        <mxPoint x="0" y="0" as="offset"/>
      </mxGeometry>
      <Resource name="Black" color="#000000" travelTime="0" as="resource"/>
    </mxStateConnectionCell>
    <mxTextCell id="30" style="shape=text-shape;html=1;resizable=0;align=left;verticalAlign=middle;whiteSpace=wrap;rounded=0;fontSize=16;fontColor=#FF0000;strokeColor=none;fillColor=none;" title="Text" vertex="1" edge="0" label="Killing the Drowner&amp;nbsp;&lt;br&gt;allows looting and getting&lt;br&gt;'Drowner's brain' item&lt;br&gt;" prevLabel="Killing the Drowner&amp;nbsp;&lt;br&gt;allows looting and getting&lt;br&gt;'Drowner's brain' item&lt;br&gt;" parent="1" width="50" height="18" isMachination="0" activation="passive" blinkStatus="0" connectable="1" visible="1" collapsed="0">
      <mxGeometry x="950" y="440" width="200" height="60" TRANSLATE_CONTROL_POINTS="1" relative="0" as="geometry">
        <mxPoint x="0" y="0" as="offset"/>
      </mxGeometry>
    </mxTextCell>
    <mxResourceConnectionCell id="31" value="&lt;span&gt;1&lt;/span&gt;&lt;span&gt;&lt;/span&gt;&lt;span&gt;&lt;/span&gt;&lt;span&gt;&lt;/span&gt;&lt;span&gt;&lt;/span&gt;" style="shape=resource-connection;endArrow=classic;html=1;strokeWidth=2;fontSize=16;fontColor=#000000;strokeColor=#000000;exitX=0.5;exitY=1;exitPerimeter=0;entryX=0.9;entryY=0.5;entryPerimeter=0;" title="Resource Connection" vertex="0" edge="1" parent="1" source="32" target="34" type="plain-arrow" resourceTransfer="interval-based" colorCoding="0" minValue="-9999" maxValue="9999" shuffleSource="0" isMachination="1" width="60" height="60" activation="passive" blinkStatus="0" connectable="1" visible="1" collapsed="0" label="&lt;span&gt;1&lt;/span&gt;&lt;span&gt;&lt;/span&gt;&lt;span&gt;&lt;/span&gt;&lt;span&gt;&lt;/span&gt;&lt;span&gt;&lt;/span&gt;">
      <mxGeometry x="0" y="0" width="60" height="60" relative="1" TRANSLATE_CONTROL_POINTS="1" as="geometry">
        <mxPoint x="20" y="20" as="offset"/>
        <Array as="points">
          <mxPoint x="780" y="710"/>
        </Array>
      </mxGeometry>
      <Resource name="Black" color="#000000" travelTime="0" as="resource"/>
    </mxResourceConnectionCell>
    <mxPoolShapeCell id="32" style="shape=pool-shape;whiteSpace=wrap;html=1;strokeWidth=2;aspect=fixed;resizable=0;fontSize=16;fontColor=#FF0000FF;strokeColor=#FF0000FF;fillColor=none;" title="Pool" vertex="1" edge="0" parent="1" activation="passive" actionMode="push-any" number="0" capacity="1" displayCapacity="0" overflow="block" isMachination="1" blinkStatus="0" connectable="1" visible="1" collapsed="0" label="Drowner's Brain">
      <mxGeometry x="757" y="527" width="46" height="46" TRANSLATE_CONTROL_POINTS="1" relative="0" vertexOrientation="topLeft" as="geometry">
        <mxPoint x="-54.5" y="-41" as="offset"/>
      </mxGeometry>
      <Resource name="Black" color="#000000" travelTime="0" as="resource"/>
    </mxPoolShapeCell>
    <mxResourceConnectionCell id="33" value="&lt;span&gt;&lt;/span&gt;&lt;span&gt;&lt;/span&gt;&lt;span&gt;&lt;/span&gt;&lt;span&gt;&lt;/span&gt;&lt;span&gt;&lt;/span&gt;" style="shape=resource-connection;endArrow=classic;html=1;strokeWidth=2;fontSize=16;fontColor=#000000;strokeColor=#000000;exitX=0.5;exitY=1;exitPerimeter=0;entryX=0.5;entryY=0;entryPerimeter=0;" title="Resource Connection" vertex="0" edge="1" parent="1" source="34" target="36" type="plain-arrow" resourceTransfer="interval-based" colorCoding="0" minValue="-9999" maxValue="9999" shuffleSource="0" isMachination="1" width="60" height="60" activation="passive" blinkStatus="0" connectable="1" visible="1" collapsed="0" label="&lt;span&gt;&lt;/span&gt;&lt;span&gt;&lt;/span&gt;&lt;span&gt;&lt;/span&gt;&lt;span&gt;&lt;/span&gt;&lt;span&gt;&lt;/span&gt;">
      <mxGeometry x="0" y="0" width="60" height="60" relative="1" TRANSLATE_CONTROL_POINTS="1" as="geometry">
        <mxPoint x="20" y="20" as="offset"/>
      </mxGeometry>
      <Resource name="Black" color="#000000" travelTime="0" as="resource"/>
    </mxResourceConnectionCell>
    <mxConverterShapeCell id="34" style="shape=converter-shape;whiteSpace=wrap;html=1;strokeWidth=2;aspect=fixed;resizable=0;fontSize=16;fontColor=#000000;strokeColor=#000000;" title="Converter" vertex="1" edge="0" parent="1" activation="automatic" actionMode="pull-all" isMachination="1" blinkStatus="0" connectable="1" visible="1" collapsed="0" label="">
      <mxGeometry x="597" y="687" width="46" height="46" TRANSLATE_CONTROL_POINTS="1" relative="0" as="geometry">
        <mxPoint x="0" y="40" as="offset"/>
      </mxGeometry>
      <Resource name="Black" color="#000000" travelTime="0" as="resource"/>
    </mxConverterShapeCell>
    <mxResourceConnectionCell id="35" value="&lt;span&gt;1&lt;/span&gt;&lt;span&gt;&lt;/span&gt;&lt;span&gt;&lt;/span&gt;&lt;span&gt;&lt;/span&gt;&lt;span&gt;&lt;/span&gt;" style="shape=resource-connection;endArrow=classic;html=1;strokeWidth=2;fontSize=16;fontColor=#000000;strokeColor=#000000;exitX=1;exitY=0.5;exitPerimeter=0;entryX=0.5;entryY=1;entryPerimeter=0;" title="Resource Connection" vertex="0" edge="1" parent="1" source="36" target="38" type="plain-arrow" resourceTransfer="interval-based" colorCoding="0" minValue="-9999" maxValue="9999" shuffleSource="0" isMachination="1" width="60" height="60" activation="passive" blinkStatus="0" connectable="1" visible="1" collapsed="0" label="&lt;span&gt;1&lt;/span&gt;&lt;span&gt;&lt;/span&gt;&lt;span&gt;&lt;/span&gt;&lt;span&gt;&lt;/span&gt;&lt;span&gt;&lt;/span&gt;">
      <mxGeometry x="0" y="0" width="60" height="60" relative="1" TRANSLATE_CONTROL_POINTS="1" as="geometry">
        <mxPoint x="1400" y="860" as="targetPoint"/>
        <mxPoint x="20" y="20" as="offset"/>
        <Array as="points">
          <mxPoint x="1300" y="880"/>
        </Array>
      </mxGeometry>
      <Resource name="Black" color="#000000" travelTime="0" as="resource"/>
    </mxResourceConnectionCell>
    <mxPoolShapeCell id="36" style="shape=pool-shape;whiteSpace=wrap;html=1;strokeWidth=2;aspect=fixed;resizable=0;fontSize=16;fontColor=#990099;strokeColor=#990099;" title="Pool" vertex="1" edge="0" parent="1" activation="passive" actionMode="push-any" number="0" capacity="-1" displayCapacity="0" overflow="block" isMachination="1" blinkStatus="0" connectable="1" visible="1" collapsed="0" label="Swallow">
      <mxGeometry x="597" y="857" width="46" height="46" TRANSLATE_CONTROL_POINTS="1" relative="0" as="geometry">
        <mxPoint x="0" y="48.5" as="offset"/>
      </mxGeometry>
      <Resource name="Black" color="#000000" travelTime="0" as="resource"/>
    </mxPoolShapeCell>
    <mxResourceConnectionCell id="37" value="&lt;span&gt;+80&lt;/span&gt;&lt;span&gt;&lt;/span&gt;&lt;span&gt;&lt;/span&gt;&lt;span&gt;&lt;/span&gt;&lt;span&gt;&lt;/span&gt;" style="shape=resource-connection;endArrow=classic;html=1;strokeWidth=2;fontSize=16;fontColor=#000000;strokeColor=#000000;exitX=0.5;exitY=0;exitPerimeter=0;entryX=0.5;entryY=0;entryPerimeter=0;" title="Resource Connection" vertex="0" edge="1" parent="1" source="38" target="22" type="plain-arrow" resourceTransfer="interval-based" colorCoding="0" minValue="-9999" maxValue="9999" shuffleSource="0" isMachination="1" width="60" height="60" activation="passive" blinkStatus="0" connectable="1" visible="1" collapsed="0" label="&lt;span&gt;+80&lt;/span&gt;&lt;span&gt;&lt;/span&gt;&lt;span&gt;&lt;/span&gt;&lt;span&gt;&lt;/span&gt;&lt;span&gt;&lt;/span&gt;">
      <mxGeometry x="0" y="0" width="60" height="60" relative="1" TRANSLATE_CONTROL_POINTS="1" as="geometry">
        <mxPoint x="20" y="20" as="offset"/>
        <Array as="points">
          <mxPoint x="1300" y="0"/>
          <mxPoint x="770" y="0"/>
        </Array>
      </mxGeometry>
      <Resource name="Black" color="#000000" travelTime="0" as="resource"/>
    </mxResourceConnectionCell>
    <mxConverterShapeCell id="38" style="shape=converter-shape;whiteSpace=wrap;html=1;strokeWidth=2;aspect=fixed;resizable=0;fontSize=16;fontColor=#000000;strokeColor=#000000;" title="Converter" vertex="1" edge="0" parent="1" activation="automatic" actionMode="pull-any" isMachination="1" blinkStatus="0" connectable="1" visible="1" collapsed="0" label="">
      <mxGeometry x="1277" y="487" width="46" height="46" TRANSLATE_CONTROL_POINTS="1" relative="0" as="geometry">
        <mxPoint x="0" y="40" as="offset"/>
      </mxGeometry>
      <Resource name="Black" color="#000000" travelTime="0" as="resource"/>
    </mxConverterShapeCell>
    <mxTextCell id="39" style="shape=text-shape;html=1;resizable=0;align=left;verticalAlign=middle;whiteSpace=wrap;rounded=0;fontSize=16;strokeColor=none;fillColor=none;" title="Text" vertex="1" edge="0" label="Witcher 3&amp;nbsp; Wild Hunt - Creating Swallow potion&lt;br&gt;To be able to create this potion the user needs&amp;nbsp;&lt;br&gt;to collect 3 ingredients. Two of them can be found&amp;nbsp;&lt;br&gt;by exploring the world and fighting specific type of&lt;br&gt;monsters while the third one needs to be created.&lt;br&gt;After consuming the potion, users Health is regenerated&lt;br&gt;by certain amount.&lt;br&gt;" prevLabel="Witcher 3&amp;nbsp; Wild Hunt - Creating Swallow potion&lt;br&gt;To be able to create this potion the user needs&amp;nbsp;&lt;br&gt;to collect 3 ingredients. Two of them can be found&amp;nbsp;&lt;br&gt;by exploring the world and fighting specific type of&lt;br&gt;monsters while the third one needs to be created.&lt;br&gt;After consuming the potion, users Health is regenerated&lt;br&gt;by certain amount.&lt;br&gt;" parent="1" width="50" height="18" isMachination="0" activation="passive" blinkStatus="0" connectable="1" visible="1" collapsed="0">
      <mxGeometry x="0" y="810" width="410" height="140" TRANSLATE_CONTROL_POINTS="1" relative="0" as="geometry">
        <mxPoint x="0" y="0" as="offset"/>
      </mxGeometry>
    </mxTextCell>
    <mxPoolShapeCell id="2100" style="shape=pool-shape;whiteSpace=wrap;html=1;strokeWidth=2;aspect=fixed;resizable=0;fontSize=16;fontColor=#FF0000FF;strokeColor=#FF0000FF;fillColor=#FFFFFF;" title="Pool" vertex="1" edge="0" activation="passive" actionMode="push-any" number="1" capacity="-1" displayCapacity="25" overflow="block" isMachination="1" blinkStatus="0" connectable="1" visible="1" collapsed="0" parent="1">
      <mxGeometry x="1162" y="373" width="46" height="46" TRANSLATE_CONTROL_POINTS="1" relative="0" as="geometry">
        <mxPoint x="0" y="28.671147880041364" as="offset"/>
      </mxGeometry>
      <Resource name="Black" color="#000000" travelTime="0" as="resource"/>
    </mxPoolShapeCell>
    <mxResourceConnectionCell id="2300" value="1" style="shape=resource-connection;endArrow=classic;html=1;strokeWidth=2;fontSize=16;fontColor=#FF0000FF;strokeColor=#FF0000FF;edgeStyle=orthogonalEdgeStyle;fillColor=none;" title="Resource Connection" vertex="0" edge="1" width="46" height="46" type="plain-arrow" resourceTransfer="interval-based" colorCoding="0" minValue="-9999" maxValue="9999" shuffleSource="0" isMachination="1" activation="passive" blinkStatus="0" connectable="1" visible="1" collapsed="0" parent="1" source="2100" target="32">
      <mxGeometry x="0" y="0" width="46" height="46" relative="1" TRANSLATE_CONTROL_POINTS="1" as="geometry">
        <mxPoint x="1185" y="442" as="sourcePoint"/>
        <mxPoint x="1231" y="396" as="targetPoint"/>
        <Array as="points">
          <mxPoint x="1185" y="550"/>
        </Array>
        <mxPoint x="18.11789038262668" y="9.05894519131334" as="offset"/>
      </mxGeometry>
      <Resource name="Black" color="#000000" travelTime="0" as="resource"/>
    </mxResourceConnectionCell>
    <mxStateConnectionCell id="2500" value="!" style="shape=state-connection;endArrow=classic;dashed=1;dashPattern=4 3;html=1;strokeWidth=2;fontSize=16;fontColor=#000000;strokeColor=#000000;" title="State Connection" vertex="0" edge="1" width="46" height="46" colorCoding="0" type="5" isMachination="1" activation="passive" blinkStatus="0" connectable="1" visible="1" collapsed="0" parent="1" source="23" target="2100">
      <mxGeometry x="0" y="0" width="46" height="46" relative="1" TRANSLATE_CONTROL_POINTS="1" as="geometry">
        <mxPoint x="938" y="301" as="sourcePoint"/>
        <mxPoint x="984" y="301" as="targetPoint"/>
        <mxPoint x="-9.05894519131334" y="9.05894519131334" as="offset"/>
      </mxGeometry>
      <Resource name="Black" color="#000000" travelTime="0" as="resource"/>
    </mxStateConnectionCell>
  </root>
  <chart chartOpen="true" chartHeight="190"/>
</mxGraphModel>
