<?xml version="1.0"?>
<mxGraphModel dx="2286" dy="1275" grid="0" tooltips="1" fold="1" page="0" pageScale="0.75" pageWidth="1169" pageHeight="827" background="#ffffff" document_owner="Machinations Support" document_creation_date="1582114678184" document_last_change_date="1606311293274" time_interval="1" diagram_time_steps_limit="5000" diagram_number_of_total_runs="20" zoomFactorProp="1" diagramScrollTop="1053" diagramScrollLeft="1725">
  <root>
    <mxCell id="0"/>
    <mxCell id="1" style="strokeColor=#311B92;strokeWidth=2;fontColor=#311B92;" parent="0"/>
    <mxPoolShapeCell id="2" style="shape=pool-shape;whiteSpace=wrap;html=1;strokeWidth=2;aspect=fixed;resizable=0;fontSize=16;fontColor=#000000;strokeColor=#000000;fillColor=#CCE5FF;" title="Pool" vertex="1" edge="0" parent="1" activation="passive" actionMode="push-any" number="100" capacity="100" displayCapacity="0" overflow="block" isMachination="1" blinkStatus="0" connectable="1" visible="1" collapsed="0" label="Mana Pool" __latestValue="100" inChartProperties="{&quot;visible&quot;: &quot;true&quot;, &quot;onLeftScale&quot;: &quot;true&quot;, &quot;color&quot;: &quot;black&quot;, &quot;chartType&quot;: &quot;0&quot;}">
      <mxGeometry x="737" y="297" width="46" height="46" TRANSLATE_CONTROL_POINTS="1" relative="0" vertexOrientation="bottomRight" as="geometry">
        <mxPoint x="27.000000000000078" y="51.00000000000004" as="offset"/>
      </mxGeometry>
      <Resource name="Black" color="#000000" travelTime="0" as="resource"/>
    </mxPoolShapeCell>
    <mxSourceShapeCell id="10" style="shape=source-shape;whiteSpace=wrap;html=1;strokeWidth=2;aspect=fixed;resizable=0;fontSize=16;fontColor=#000000;strokeColor=#000000;align=right;fillColor=#CCFFCC;" title="Source" vertex="1" edge="0" parent="1" activation="automatic" isMachination="1" blinkStatus="0" connectable="1" visible="1" collapsed="0" label="Generator" inChartProperties="{&quot;visible&quot;: &quot;true&quot;, &quot;onLeftScale&quot;: &quot;true&quot;, &quot;color&quot;: &quot;black&quot;, &quot;chartType&quot;: &quot;0&quot;}">
      <mxGeometry x="737" y="137" width="46" height="46" TRANSLATE_CONTROL_POINTS="1" relative="0" vertexOrientation="right" as="geometry">
        <mxPoint x="80.6" y="-2.5" as="offset"/>
      </mxGeometry>
      <Resource name="Black" color="#000000" travelTime="0" as="resource"/>
    </mxSourceShapeCell>
    <mxPoolShapeCell id="11" style="shape=pool-shape;whiteSpace=wrap;html=1;strokeWidth=2;aspect=fixed;resizable=0;fontSize=16;fontColor=#000000;strokeColor=#000000;fillColor=#CC0000;" title="Pool" vertex="1" edge="0" parent="1" activation="passive" actionMode="push-any" number="0" capacity="-1" displayCapacity="0" overflow="block" isMachination="1" blinkStatus="0" connectable="1" visible="1" collapsed="0" label="Spell 5 Cooldown Timer" __latestValue="0" inChartProperties="{&quot;visible&quot;: &quot;true&quot;, &quot;onLeftScale&quot;: &quot;true&quot;, &quot;color&quot;: &quot;black&quot;, &quot;chartType&quot;: &quot;0&quot;}">
      <mxGeometry x="619" y="137" width="46" height="46" TRANSLATE_CONTROL_POINTS="1" relative="0" vertexOrientation="top" as="geometry">
        <mxPoint x="-1.5" y="-67.5" as="offset"/>
      </mxGeometry>
      <Resource name="Black" color="#000000" travelTime="0" as="resource"/>
    </mxPoolShapeCell>
    <mxPoolShapeCell id="12" style="shape=pool-shape;whiteSpace=wrap;html=1;strokeWidth=2;aspect=fixed;resizable=0;fontSize=16;fontColor=#000000;strokeColor=#000000;fillColor=#CC0000;" title="Pool" vertex="1" edge="0" parent="1" activation="passive" actionMode="push-any" number="0" capacity="-1" displayCapacity="0" overflow="block" isMachination="1" blinkStatus="0" connectable="1" visible="1" collapsed="0" label="Spell 4 Cooldown Timer" __latestValue="0" inChartProperties="{&quot;visible&quot;: &quot;true&quot;, &quot;onLeftScale&quot;: &quot;true&quot;, &quot;color&quot;: &quot;black&quot;, &quot;chartType&quot;: &quot;0&quot;}">
      <mxGeometry x="497" y="137" width="46" height="46" TRANSLATE_CONTROL_POINTS="1" relative="0" vertexOrientation="top" as="geometry">
        <mxPoint x="1.5" y="-67.5" as="offset"/>
      </mxGeometry>
      <Resource name="Black" color="#000000" travelTime="0" as="resource"/>
    </mxPoolShapeCell>
    <mxPoolShapeCell id="13" style="shape=pool-shape;whiteSpace=wrap;html=1;strokeWidth=2;aspect=fixed;resizable=0;fontSize=16;fontColor=#000000;strokeColor=#000000;fillColor=#CC0000;" title="Pool" vertex="1" edge="0" parent="1" activation="passive" actionMode="push-any" number="0" capacity="-1" displayCapacity="0" overflow="block" isMachination="1" blinkStatus="0" connectable="1" visible="1" collapsed="0" label="Spell 3 Cooldown Timer" __latestValue="0" inChartProperties="{&quot;visible&quot;: &quot;true&quot;, &quot;onLeftScale&quot;: &quot;true&quot;, &quot;color&quot;: &quot;black&quot;, &quot;chartType&quot;: &quot;0&quot;}">
      <mxGeometry x="377" y="137" width="46" height="46" TRANSLATE_CONTROL_POINTS="1" relative="0" vertexOrientation="top" as="geometry">
        <mxPoint x="-0.5" y="-67.5" as="offset"/>
      </mxGeometry>
      <Resource name="Black" color="#000000" travelTime="0" as="resource"/>
    </mxPoolShapeCell>
    <mxPoolShapeCell id="14" style="shape=pool-shape;whiteSpace=wrap;html=1;strokeWidth=2;aspect=fixed;resizable=0;fontSize=16;fontColor=#000000;strokeColor=#000000;fillColor=#CC0000;" title="Pool" vertex="1" edge="0" parent="1" activation="passive" actionMode="push-any" number="0" capacity="-1" displayCapacity="0" overflow="block" isMachination="1" blinkStatus="0" connectable="1" visible="1" collapsed="0" label="Spell 2 Cooldown Timer" __latestValue="0" inChartProperties="{&quot;visible&quot;: &quot;true&quot;, &quot;onLeftScale&quot;: &quot;true&quot;, &quot;color&quot;: &quot;black&quot;, &quot;chartType&quot;: &quot;0&quot;}">
      <mxGeometry x="257" y="137" width="46" height="46" TRANSLATE_CONTROL_POINTS="1" relative="0" vertexOrientation="top" as="geometry">
        <mxPoint x="1.5" y="-67.5" as="offset"/>
      </mxGeometry>
      <Resource name="Black" color="#000000" travelTime="0" as="resource"/>
    </mxPoolShapeCell>
    <mxResourceConnectionCell id="16" value="&lt;span&gt;100&lt;/span&gt;&lt;span&gt;&lt;/span&gt;&lt;span&gt;&lt;/span&gt;&lt;span&gt;&lt;/span&gt;&lt;span&gt;&lt;/span&gt;" style="shape=resource-connection;endArrow=classic;html=1;strokeWidth=2;fontSize=16;fontColor=#000000;strokeColor=#000000;align=left;entryX=0.5;entryY=1;entryPerimeter=0;" title="Resource Connection" vertex="0" edge="1" parent="1" source="2" target="35" type="plain-arrow" resourceTransfer="instantaneous" colorCoding="0" minValue="-9999" maxValue="9999" shuffleSource="0" isMachination="1" width="60" height="60" activation="passive" blinkStatus="0" connectable="1" visible="1" collapsed="0" label="&lt;span&gt;100&lt;/span&gt;&lt;span&gt;&lt;/span&gt;&lt;span&gt;&lt;/span&gt;&lt;span&gt;&lt;/span&gt;&lt;span&gt;&lt;/span&gt;" inChartProperties="{&quot;visible&quot;: &quot;true&quot;, &quot;onLeftScale&quot;: &quot;true&quot;, &quot;color&quot;: &quot;black&quot;, &quot;chartType&quot;: &quot;0&quot;}">
      <mxGeometry x="0.7282840927245344" y="-8.899381621569459" width="60" height="60" relative="1" TRANSLATE_CONTROL_POINTS="1" as="geometry">
        <mxPoint x="830" y="440" as="sourcePoint"/>
        <mxPoint x="670" y="350" as="targetPoint"/>
        <Array as="points">
          <mxPoint x="760" y="400"/>
          <mxPoint x="642" y="400"/>
        </Array>
        <mxPoint x="0" y="0" as="offset"/>
      </mxGeometry>
      <Resource name="Black" color="#000000" travelTime="0" as="resource"/>
    </mxResourceConnectionCell>
    <mxResourceConnectionCell id="17" value="&lt;span&gt;80&lt;/span&gt;&lt;span&gt;&lt;/span&gt;&lt;span&gt;&lt;/span&gt;&lt;span&gt;&lt;/span&gt;&lt;span&gt;&lt;/span&gt;" style="shape=resource-connection;endArrow=classic;html=1;strokeWidth=2;fontSize=16;fontColor=#000000;strokeColor=#000000;align=center;entryX=0.5;entryY=1;entryPerimeter=0;" title="Resource Connection" vertex="0" edge="1" parent="1" source="2" target="38" type="plain-arrow" resourceTransfer="instantaneous" colorCoding="0" minValue="-9999" maxValue="9999" shuffleSource="0" isMachination="1" width="60" height="60" activation="passive" blinkStatus="0" connectable="1" visible="1" collapsed="0" label="&lt;span&gt;80&lt;/span&gt;&lt;span&gt;&lt;/span&gt;&lt;span&gt;&lt;/span&gt;&lt;span&gt;&lt;/span&gt;&lt;span&gt;&lt;/span&gt;" inChartProperties="{&quot;visible&quot;: &quot;true&quot;, &quot;onLeftScale&quot;: &quot;true&quot;, &quot;color&quot;: &quot;black&quot;, &quot;chartType&quot;: &quot;0&quot;}">
      <mxGeometry x="0.8192985461219426" y="-17.56270861181469" width="60" height="60" relative="1" TRANSLATE_CONTROL_POINTS="1" as="geometry">
        <mxPoint x="790" y="500" as="sourcePoint"/>
        <mxPoint x="530" y="350" as="targetPoint"/>
        <Array as="points">
          <mxPoint x="760" y="400"/>
          <mxPoint x="520" y="400"/>
        </Array>
        <mxPoint x="0" y="0" as="offset"/>
      </mxGeometry>
      <Resource name="Black" color="#000000" travelTime="0" as="resource"/>
    </mxResourceConnectionCell>
    <mxResourceConnectionCell id="18" value="&lt;span&gt;45&lt;/span&gt;&lt;span&gt;&lt;/span&gt;&lt;span&gt;&lt;/span&gt;&lt;span&gt;&lt;/span&gt;&lt;span&gt;&lt;/span&gt;" style="shape=resource-connection;endArrow=classic;html=1;strokeWidth=2;fontSize=16;fontColor=#000000;strokeColor=#000000;align=center;entryX=0.5;entryY=1;entryPerimeter=0;" title="Resource Connection" vertex="0" edge="1" parent="1" source="2" target="41" type="plain-arrow" resourceTransfer="instantaneous" colorCoding="0" minValue="-9999" maxValue="9999" shuffleSource="0" isMachination="1" width="60" height="60" activation="passive" blinkStatus="0" connectable="1" visible="1" collapsed="0" label="&lt;span&gt;45&lt;/span&gt;&lt;span&gt;&lt;/span&gt;&lt;span&gt;&lt;/span&gt;&lt;span&gt;&lt;/span&gt;&lt;span&gt;&lt;/span&gt;" inChartProperties="{&quot;visible&quot;: &quot;true&quot;, &quot;onLeftScale&quot;: &quot;true&quot;, &quot;color&quot;: &quot;black&quot;, &quot;chartType&quot;: &quot;0&quot;}">
      <mxGeometry x="0.8650374060511644" y="-19.249191978302594" width="60" height="60" relative="1" TRANSLATE_CONTROL_POINTS="1" as="geometry">
        <mxPoint x="790" y="500" as="sourcePoint"/>
        <mxPoint x="430" y="350" as="targetPoint"/>
        <Array as="points">
          <mxPoint x="760" y="400"/>
          <mxPoint x="400" y="400"/>
        </Array>
        <mxPoint x="0" y="0" as="offset"/>
      </mxGeometry>
      <Resource name="Black" color="#000000" travelTime="0" as="resource"/>
    </mxResourceConnectionCell>
    <mxResourceConnectionCell id="19" value="&lt;span&gt;25&lt;/span&gt;&lt;span&gt;&lt;/span&gt;&lt;span&gt;&lt;/span&gt;&lt;span&gt;&lt;/span&gt;&lt;span&gt;&lt;/span&gt;" style="shape=resource-connection;endArrow=classic;html=1;strokeWidth=2;fontSize=16;fontColor=#000000;strokeColor=#000000;align=center;entryX=0.5;entryY=1;entryPerimeter=0;" title="Resource Connection" vertex="0" edge="1" parent="1" source="2" target="44" type="plain-arrow" resourceTransfer="instantaneous" colorCoding="0" minValue="-9999" maxValue="9999" shuffleSource="0" isMachination="1" width="60" height="60" activation="passive" blinkStatus="0" connectable="1" visible="1" collapsed="0" label="&lt;span&gt;25&lt;/span&gt;&lt;span&gt;&lt;/span&gt;&lt;span&gt;&lt;/span&gt;&lt;span&gt;&lt;/span&gt;&lt;span&gt;&lt;/span&gt;" inChartProperties="{&quot;visible&quot;: &quot;true&quot;, &quot;onLeftScale&quot;: &quot;true&quot;, &quot;color&quot;: &quot;black&quot;, &quot;chartType&quot;: &quot;0&quot;}">
      <mxGeometry x="0.7585030070819179" y="-19.33333333333337" width="60" height="60" relative="1" TRANSLATE_CONTROL_POINTS="1" as="geometry">
        <mxPoint x="790" y="500" as="sourcePoint"/>
        <mxPoint x="300" y="350" as="targetPoint"/>
        <Array as="points">
          <mxPoint x="760" y="400"/>
          <mxPoint x="280" y="400"/>
        </Array>
        <mxPoint x="0" y="0" as="offset"/>
      </mxGeometry>
      <Resource name="Black" color="#000000" travelTime="0" as="resource"/>
    </mxResourceConnectionCell>
    <mxResourceConnectionCell id="20" value="&lt;span&gt;15&lt;/span&gt;&lt;span&gt;&lt;/span&gt;&lt;span&gt;&lt;/span&gt;&lt;span&gt;&lt;/span&gt;&lt;span&gt;&lt;/span&gt;" style="shape=resource-connection;endArrow=classic;html=1;strokeWidth=2;fontSize=16;fontColor=#000000;strokeColor=#000000;align=center;entryX=0.5;entryY=0.9;entryPerimeter=0;" title="Resource Connection" vertex="0" edge="1" parent="1" source="2" target="49" type="plain-arrow" resourceTransfer="instantaneous" colorCoding="0" minValue="-9999" maxValue="9999" shuffleSource="0" isMachination="1" width="60" height="60" activation="passive" blinkStatus="0" connectable="1" visible="1" collapsed="0" label="&lt;span&gt;15&lt;/span&gt;&lt;span&gt;&lt;/span&gt;&lt;span&gt;&lt;/span&gt;&lt;span&gt;&lt;/span&gt;&lt;span&gt;&lt;/span&gt;" inChartProperties="{&quot;visible&quot;: &quot;true&quot;, &quot;onLeftScale&quot;: &quot;true&quot;, &quot;color&quot;: &quot;black&quot;, &quot;chartType&quot;: &quot;0&quot;}">
      <mxGeometry x="0.7781965031050021" y="-19.333333333333375" width="60" height="60" relative="1" TRANSLATE_CONTROL_POINTS="1" as="geometry">
        <mxPoint x="790" y="500" as="sourcePoint"/>
        <mxPoint x="180" y="350" as="targetPoint"/>
        <Array as="points">
          <mxPoint x="760" y="400"/>
          <mxPoint x="160" y="400"/>
        </Array>
        <mxPoint x="0" y="0" as="offset"/>
      </mxGeometry>
      <Resource name="Black" color="#000000" travelTime="0" as="resource"/>
    </mxResourceConnectionCell>
    <mxResourceConnectionCell id="21" value="&lt;span&gt;&lt;/span&gt;&lt;span&gt;&lt;/span&gt;&lt;span&gt;&lt;/span&gt;&lt;span&gt;&lt;/span&gt;&lt;span&gt;&lt;/span&gt;" style="shape=resource-connection;endArrow=classic;html=1;strokeWidth=2;fontSize=16;fontColor=#000000;strokeColor=#000000;align=left;" title="Resource Connection" vertex="0" edge="1" parent="1" source="10" target="2" type="plain-arrow" resourceTransfer="instantaneous" colorCoding="0" minValue="-9999" maxValue="9999" shuffleSource="0" isMachination="1" width="60" height="60" activation="passive" blinkStatus="0" connectable="1" visible="1" collapsed="0" label="&lt;span&gt;&lt;/span&gt;&lt;span&gt;&lt;/span&gt;&lt;span&gt;&lt;/span&gt;&lt;span&gt;&lt;/span&gt;&lt;span&gt;&lt;/span&gt;" inChartProperties="{&quot;visible&quot;: &quot;true&quot;, &quot;onLeftScale&quot;: &quot;true&quot;, &quot;color&quot;: &quot;black&quot;, &quot;chartType&quot;: &quot;0&quot;}">
      <mxGeometry x="0.5825438191416353" y="8.232558139534799" width="60" height="60" relative="1" TRANSLATE_CONTROL_POINTS="1" as="geometry">
        <mxPoint x="790" y="230" as="sourcePoint"/>
        <mxPoint x="874.8528137423857" y="170" as="targetPoint"/>
        <mxPoint x="0" y="0" as="offset"/>
      </mxGeometry>
      <Resource name="Black" color="#000000" travelTime="0" as="resource"/>
    </mxResourceConnectionCell>
    <mxStateConnectionCell id="22" value="&lt;span&gt;&lt;100&lt;/span&gt;&lt;span&gt;&lt;/span&gt;&lt;span&gt;&lt;/span&gt;&lt;span&gt;&lt;/span&gt;&lt;span&gt;&lt;/span&gt;" style="shape=state-connection;endArrow=classic;dashed=1;dashPattern=4 3;html=1;strokeWidth=2;fontSize=16;fontColor=#000000;strokeColor=#000000;exitX=1;exitY=0.5;exitPerimeter=0;align=right;" title="State Connection" vertex="0" edge="1" parent="1" source="2" target="21" type="4" colorCoding="0" isMachination="1" width="60" height="60" activation="passive" blinkStatus="0" connectable="1" visible="1" collapsed="0" label="&lt;span&gt;&amp;lt;100&lt;/span&gt;&lt;span&gt;&lt;/span&gt;&lt;span&gt;&lt;/span&gt;&lt;span&gt;&lt;/span&gt;&lt;span&gt;&lt;/span&gt;" inChartProperties="{&quot;visible&quot;: &quot;true&quot;, &quot;onLeftScale&quot;: &quot;true&quot;, &quot;color&quot;: &quot;black&quot;, &quot;chartType&quot;: &quot;0&quot;}">
      <mxGeometry x="-0.05286606466763545" y="8.232558139535008" width="60" height="60" relative="1" TRANSLATE_CONTROL_POINTS="1" as="geometry">
        <mxPoint x="840" y="285" as="sourcePoint"/>
        <mxPoint x="850" y="280" as="targetPoint"/>
        <Array as="points">
          <mxPoint x="840" y="320"/>
          <mxPoint x="840" y="270"/>
        </Array>
        <mxPoint x="0" y="0" as="offset"/>
      </mxGeometry>
      <Resource name="Black" color="#000000" travelTime="0" as="resource"/>
    </mxStateConnectionCell>
    <mxResourceConnectionCell id="31" value="&lt;span&gt;&lt;/span&gt;&lt;span&gt;&lt;/span&gt;&lt;span&gt;&lt;/span&gt;&lt;span&gt;&lt;/span&gt;&lt;span&gt;&lt;/span&gt;" style="shape=resource-connection;endArrow=classic;html=1;strokeWidth=2;fontSize=16;fontColor=#000000;strokeColor=#000000;entryX=0.5;entryY=0;entryPerimeter=0;exitX=0.5;exitY=0;exitPerimeter=0;" title="Resource Connection" vertex="0" edge="1" parent="1" source="14" target="9" type="plain-arrow" resourceTransfer="instantaneous" colorCoding="0" minValue="-9999" maxValue="9999" shuffleSource="0" isMachination="1" width="60" height="60" activation="passive" blinkStatus="0" connectable="1" visible="1" collapsed="0" label="&lt;span&gt;&lt;/span&gt;&lt;span&gt;&lt;/span&gt;&lt;span&gt;&lt;/span&gt;&lt;span&gt;&lt;/span&gt;&lt;span&gt;&lt;/span&gt;" inChartProperties="{&quot;visible&quot;: &quot;true&quot;, &quot;onLeftScale&quot;: &quot;true&quot;, &quot;color&quot;: &quot;black&quot;, &quot;chartType&quot;: &quot;0&quot;}">
      <mxGeometry x="0" y="0" width="60" height="60" relative="1" TRANSLATE_CONTROL_POINTS="1" as="geometry">
        <mxPoint x="310" y="220" as="sourcePoint"/>
        <mxPoint x="394.8528137423857" y="160" as="targetPoint"/>
        <mxPoint x="11" y="-11" as="offset"/>
      </mxGeometry>
      <Resource name="Black" color="#000000" travelTime="0" as="resource"/>
    </mxResourceConnectionCell>
    <mxResourceConnectionCell id="32" value="&lt;span&gt;&lt;/span&gt;&lt;span&gt;&lt;/span&gt;&lt;span&gt;&lt;/span&gt;&lt;span&gt;&lt;/span&gt;&lt;span&gt;&lt;/span&gt;" style="shape=resource-connection;endArrow=classic;html=1;strokeWidth=2;fontSize=16;fontColor=#000000;strokeColor=#000000;entryX=0.5;entryY=0;entryPerimeter=0;exitX=0.5;exitY=0;exitPerimeter=0;" title="Resource Connection" vertex="0" edge="1" parent="1" source="13" target="9" type="plain-arrow" resourceTransfer="instantaneous" colorCoding="0" minValue="-9999" maxValue="9999" shuffleSource="0" isMachination="1" width="60" height="60" activation="passive" blinkStatus="0" connectable="1" visible="1" collapsed="0" label="&lt;span&gt;&lt;/span&gt;&lt;span&gt;&lt;/span&gt;&lt;span&gt;&lt;/span&gt;&lt;span&gt;&lt;/span&gt;&lt;span&gt;&lt;/span&gt;" inChartProperties="{&quot;visible&quot;: &quot;true&quot;, &quot;onLeftScale&quot;: &quot;true&quot;, &quot;color&quot;: &quot;black&quot;, &quot;chartType&quot;: &quot;0&quot;}">
      <mxGeometry x="0" y="0" width="60" height="60" relative="1" TRANSLATE_CONTROL_POINTS="1" as="geometry">
        <mxPoint x="430" y="220" as="sourcePoint"/>
        <mxPoint x="514.8528137423857" y="160" as="targetPoint"/>
        <mxPoint x="11" y="-11" as="offset"/>
      </mxGeometry>
      <Resource name="Black" color="#000000" travelTime="0" as="resource"/>
    </mxResourceConnectionCell>
    <mxResourceConnectionCell id="33" value="&lt;span&gt;&lt;/span&gt;&lt;span&gt;&lt;/span&gt;&lt;span&gt;&lt;/span&gt;&lt;span&gt;&lt;/span&gt;&lt;span&gt;&lt;/span&gt;" style="shape=resource-connection;endArrow=classic;html=1;strokeWidth=2;fontSize=16;fontColor=#000000;strokeColor=#000000;entryX=0.5;entryY=0;entryPerimeter=0;exitX=0.5;exitY=0;exitPerimeter=0;" title="Resource Connection" vertex="0" edge="1" parent="1" source="12" target="9" type="plain-arrow" resourceTransfer="instantaneous" colorCoding="0" minValue="-9999" maxValue="9999" shuffleSource="0" isMachination="1" width="60" height="60" activation="passive" blinkStatus="0" connectable="1" visible="1" collapsed="0" label="&lt;span&gt;&lt;/span&gt;&lt;span&gt;&lt;/span&gt;&lt;span&gt;&lt;/span&gt;&lt;span&gt;&lt;/span&gt;&lt;span&gt;&lt;/span&gt;" inChartProperties="{&quot;visible&quot;: &quot;true&quot;, &quot;onLeftScale&quot;: &quot;true&quot;, &quot;color&quot;: &quot;black&quot;, &quot;chartType&quot;: &quot;0&quot;}">
      <mxGeometry x="0" y="0" width="60" height="60" relative="1" TRANSLATE_CONTROL_POINTS="1" as="geometry">
        <mxPoint x="550" y="220" as="sourcePoint"/>
        <mxPoint x="634.8528137423857" y="160" as="targetPoint"/>
        <mxPoint x="11" y="-11" as="offset"/>
      </mxGeometry>
      <Resource name="Black" color="#000000" travelTime="0" as="resource"/>
    </mxResourceConnectionCell>
    <mxResourceConnectionCell id="34" value="&lt;span&gt;&lt;/span&gt;&lt;span&gt;&lt;/span&gt;&lt;span&gt;&lt;/span&gt;&lt;span&gt;&lt;/span&gt;&lt;span&gt;&lt;/span&gt;" style="shape=resource-connection;endArrow=classic;html=1;strokeWidth=2;fontSize=16;fontColor=#000000;strokeColor=#000000;entryX=0.5;entryY=0;entryPerimeter=0;exitX=0.5;exitY=0;exitPerimeter=0;" title="Resource Connection" vertex="0" edge="1" parent="1" source="11" target="9" type="plain-arrow" resourceTransfer="instantaneous" colorCoding="0" minValue="-9999" maxValue="9999" shuffleSource="0" isMachination="1" width="60" height="60" activation="passive" blinkStatus="0" connectable="1" visible="1" collapsed="0" label="&lt;span&gt;&lt;/span&gt;&lt;span&gt;&lt;/span&gt;&lt;span&gt;&lt;/span&gt;&lt;span&gt;&lt;/span&gt;&lt;span&gt;&lt;/span&gt;" inChartProperties="{&quot;visible&quot;: &quot;true&quot;, &quot;onLeftScale&quot;: &quot;true&quot;, &quot;color&quot;: &quot;black&quot;, &quot;chartType&quot;: &quot;0&quot;}">
      <mxGeometry x="0" y="0" width="60" height="60" relative="1" TRANSLATE_CONTROL_POINTS="1" as="geometry">
        <mxPoint x="672" y="220" as="sourcePoint"/>
        <mxPoint x="756.8528137423857" y="160" as="targetPoint"/>
        <mxPoint x="11" y="-11" as="offset"/>
      </mxGeometry>
      <Resource name="Black" color="#000000" travelTime="0" as="resource"/>
    </mxResourceConnectionCell>
    <mxConverterShapeCell id="35" style="shape=converter-shape;whiteSpace=wrap;html=1;strokeWidth=2;aspect=fixed;resizable=0;fontSize=16;fontColor=#000000;strokeColor=#000000;align=right;fontStyle=1;fillColor=#CCE5FF;" title="Converter" vertex="1" edge="0" parent="1" activation="interactive" actionMode="pull-all" isMachination="1" blinkStatus="0" connectable="1" visible="1" collapsed="0" label="Spell 5" inChartProperties="{&quot;visible&quot;: &quot;true&quot;, &quot;onLeftScale&quot;: &quot;true&quot;, &quot;color&quot;: &quot;black&quot;, &quot;chartType&quot;: &quot;0&quot;}">
      <mxGeometry x="619" y="297" width="46" height="46" TRANSLATE_CONTROL_POINTS="1" relative="0" vertexOrientation="top" as="geometry">
        <mxPoint x="-2" y="-44.5" as="offset"/>
      </mxGeometry>
      <Resource name="Black" color="#000000" travelTime="0" as="resource"/>
    </mxConverterShapeCell>
    <mxResourceConnectionCell id="36" value="&lt;span&gt;60&lt;/span&gt;&lt;span&gt;&lt;/span&gt;&lt;span&gt;&lt;/span&gt;&lt;span&gt;&lt;/span&gt;&lt;span&gt;&lt;/span&gt;" style="shape=resource-connection;endArrow=classic;html=1;strokeWidth=2;fontSize=16;fontColor=#000000;strokeColor=#000000;entryX=1;entryY=0.5;entryPerimeter=0;exitX=0.9;exitY=0.5;exitPerimeter=0;align=left;" title="Resource Connection" vertex="0" edge="1" parent="1" source="35" target="11" type="plain-arrow" resourceTransfer="instantaneous" colorCoding="0" minValue="-9999" maxValue="9999" shuffleSource="0" isMachination="1" width="60" height="60" activation="passive" blinkStatus="0" connectable="1" visible="1" collapsed="0" label="&lt;span&gt;60&lt;/span&gt;&lt;span&gt;&lt;/span&gt;&lt;span&gt;&lt;/span&gt;&lt;span&gt;&lt;/span&gt;&lt;span&gt;&lt;/span&gt;" inChartProperties="{&quot;visible&quot;: &quot;true&quot;, &quot;onLeftScale&quot;: &quot;true&quot;, &quot;color&quot;: &quot;black&quot;, &quot;chartType&quot;: &quot;0&quot;}">
      <mxGeometry x="-0.7960558139134106" y="-8.580353950524211" width="60" height="60" relative="1" TRANSLATE_CONTROL_POINTS="1" as="geometry">
        <mxPoint x="672" y="380" as="sourcePoint"/>
        <mxPoint x="756.8528137423857" y="320" as="targetPoint"/>
        <Array as="points">
          <mxPoint x="672" y="320"/>
        </Array>
        <mxPoint x="0" y="0" as="offset"/>
      </mxGeometry>
      <Resource name="Black" color="#000000" travelTime="0" as="resource"/>
    </mxResourceConnectionCell>
    <mxStateConnectionCell id="37" value="&lt;span&gt;==0&lt;/span&gt;&lt;span&gt;&lt;/span&gt;&lt;span&gt;&lt;/span&gt;&lt;span&gt;&lt;/span&gt;&lt;span&gt;&lt;/span&gt;" style="shape=state-connection;endArrow=classic;dashed=1;dashPattern=4 3;html=1;strokeWidth=2;fontSize=16;fontColor=#000000;strokeColor=#000000;entryX=0;entryY=0;entryPerimeter=0;exitX=0;exitY=0.5;exitPerimeter=0;align=left;" title="State Connection" vertex="0" edge="1" parent="1" source="11" target="35" type="4" colorCoding="0" isMachination="1" width="60" height="60" activation="passive" blinkStatus="0" connectable="1" visible="1" collapsed="0" label="&lt;span&gt;==0&lt;/span&gt;&lt;span&gt;&lt;/span&gt;&lt;span&gt;&lt;/span&gt;&lt;span&gt;&lt;/span&gt;&lt;span&gt;&lt;/span&gt;" inChartProperties="{&quot;visible&quot;: &quot;true&quot;, &quot;onLeftScale&quot;: &quot;true&quot;, &quot;color&quot;: &quot;black&quot;, &quot;chartType&quot;: &quot;0&quot;}">
      <mxGeometry x="-0.4220273201925713" y="8.571428571428571" width="60" height="60" relative="1" TRANSLATE_CONTROL_POINTS="1" as="geometry">
        <mxPoint x="672" y="220" as="sourcePoint"/>
        <mxPoint x="756.8528137423857" y="160" as="targetPoint"/>
        <mxPoint x="0" y="0" as="offset"/>
      </mxGeometry>
      <Resource name="Black" color="#000000" travelTime="0" as="resource"/>
    </mxStateConnectionCell>
    <mxConverterShapeCell id="38" style="shape=converter-shape;whiteSpace=wrap;html=1;strokeWidth=2;aspect=fixed;resizable=0;fontSize=16;fontColor=#000000;strokeColor=#000000;align=right;fontStyle=1;fillColor=#CCE5FF;" title="Converter" vertex="1" edge="0" parent="1" activation="interactive" actionMode="pull-all" isMachination="1" blinkStatus="0" connectable="1" visible="1" collapsed="0" label="Spell 4" inChartProperties="{&quot;visible&quot;: &quot;true&quot;, &quot;onLeftScale&quot;: &quot;true&quot;, &quot;color&quot;: &quot;black&quot;, &quot;chartType&quot;: &quot;0&quot;}">
      <mxGeometry x="497" y="297" width="46" height="46" TRANSLATE_CONTROL_POINTS="1" relative="0" vertexOrientation="top" as="geometry">
        <mxPoint x="-2" y="-44.5" as="offset"/>
      </mxGeometry>
      <Resource name="Black" color="#000000" travelTime="0" as="resource"/>
    </mxConverterShapeCell>
    <mxResourceConnectionCell id="39" value="&lt;span&gt;25&lt;/span&gt;&lt;span&gt;&lt;/span&gt;&lt;span&gt;&lt;/span&gt;&lt;span&gt;&lt;/span&gt;&lt;span&gt;&lt;/span&gt;" style="shape=resource-connection;endArrow=classic;html=1;strokeWidth=2;fontSize=16;fontColor=#000000;strokeColor=#000000;entryX=1;entryY=0.5;entryPerimeter=0;exitX=0.9;exitY=0.5;exitPerimeter=0;align=left;" title="Resource Connection" vertex="0" edge="1" parent="1" source="38" target="12" type="plain-arrow" resourceTransfer="instantaneous" colorCoding="0" minValue="-9999" maxValue="9999" shuffleSource="0" isMachination="1" width="60" height="60" activation="passive" blinkStatus="0" connectable="1" visible="1" collapsed="0" label="&lt;span&gt;25&lt;/span&gt;&lt;span&gt;&lt;/span&gt;&lt;span&gt;&lt;/span&gt;&lt;span&gt;&lt;/span&gt;&lt;span&gt;&lt;/span&gt;" inChartProperties="{&quot;visible&quot;: &quot;true&quot;, &quot;onLeftScale&quot;: &quot;true&quot;, &quot;color&quot;: &quot;black&quot;, &quot;chartType&quot;: &quot;0&quot;}">
      <mxGeometry x="-0.8002704767315305" y="-8.580353950525042" width="60" height="60" relative="1" TRANSLATE_CONTROL_POINTS="1" as="geometry">
        <mxPoint x="550" y="380" as="sourcePoint"/>
        <mxPoint x="634.8528137423857" y="320" as="targetPoint"/>
        <Array as="points">
          <mxPoint x="550" y="320"/>
        </Array>
        <mxPoint x="0" y="0" as="offset"/>
      </mxGeometry>
      <Resource name="Black" color="#000000" travelTime="0" as="resource"/>
    </mxResourceConnectionCell>
    <mxStateConnectionCell id="40" value="&lt;span&gt;==0&lt;/span&gt;&lt;span&gt;&lt;/span&gt;&lt;span&gt;&lt;/span&gt;&lt;span&gt;&lt;/span&gt;&lt;span&gt;&lt;/span&gt;" style="shape=state-connection;endArrow=classic;dashed=1;dashPattern=4 3;html=1;strokeWidth=2;fontSize=16;fontColor=#000000;strokeColor=#000000;entryX=0;entryY=0;entryPerimeter=0;exitX=0;exitY=0.5;exitPerimeter=0;align=left;" title="State Connection" vertex="0" edge="1" parent="1" source="12" target="38" type="4" colorCoding="0" isMachination="1" width="60" height="60" activation="passive" blinkStatus="0" connectable="1" visible="1" collapsed="0" label="&lt;span&gt;==0&lt;/span&gt;&lt;span&gt;&lt;/span&gt;&lt;span&gt;&lt;/span&gt;&lt;span&gt;&lt;/span&gt;&lt;span&gt;&lt;/span&gt;" inChartProperties="{&quot;visible&quot;: &quot;true&quot;, &quot;onLeftScale&quot;: &quot;true&quot;, &quot;color&quot;: &quot;black&quot;, &quot;chartType&quot;: &quot;0&quot;}">
      <mxGeometry x="-0.4127071447539748" y="8.571428571428571" width="60" height="60" relative="1" TRANSLATE_CONTROL_POINTS="1" as="geometry">
        <mxPoint x="550" y="220" as="sourcePoint"/>
        <mxPoint x="634.8528137423857" y="160" as="targetPoint"/>
        <mxPoint x="0" y="0" as="offset"/>
      </mxGeometry>
      <Resource name="Black" color="#000000" travelTime="0" as="resource"/>
    </mxStateConnectionCell>
    <mxConverterShapeCell id="41" style="shape=converter-shape;whiteSpace=wrap;html=1;strokeWidth=2;aspect=fixed;resizable=0;fontSize=16;fontColor=#000000;strokeColor=#000000;align=right;fontStyle=1;fillColor=#CCE5FF;" title="Converter" vertex="1" edge="0" parent="1" activation="interactive" actionMode="pull-all" isMachination="1" blinkStatus="0" connectable="1" visible="1" collapsed="0" label="Spell 3" inChartProperties="{&quot;visible&quot;: &quot;true&quot;, &quot;onLeftScale&quot;: &quot;true&quot;, &quot;color&quot;: &quot;black&quot;, &quot;chartType&quot;: &quot;0&quot;}">
      <mxGeometry x="377" y="297" width="46" height="46" TRANSLATE_CONTROL_POINTS="1" relative="0" vertexOrientation="top" as="geometry">
        <mxPoint x="-1" y="-44.5" as="offset"/>
      </mxGeometry>
      <Resource name="Black" color="#000000" travelTime="0" as="resource"/>
    </mxConverterShapeCell>
    <mxResourceConnectionCell id="42" value="&lt;span&gt;12&lt;/span&gt;&lt;span&gt;&lt;/span&gt;&lt;span&gt;&lt;/span&gt;&lt;span&gt;&lt;/span&gt;&lt;span&gt;&lt;/span&gt;" style="shape=resource-connection;endArrow=classic;html=1;strokeWidth=2;fontSize=16;fontColor=#000000;strokeColor=#000000;entryX=1;entryY=0.5;entryPerimeter=0;exitX=0.9;exitY=0.5;exitPerimeter=0;align=left;" title="Resource Connection" vertex="0" edge="1" parent="1" source="41" target="13" type="plain-arrow" resourceTransfer="instantaneous" colorCoding="0" minValue="-9999" maxValue="9999" shuffleSource="0" isMachination="1" width="60" height="60" activation="passive" blinkStatus="0" connectable="1" visible="1" collapsed="0" label="&lt;span&gt;12&lt;/span&gt;&lt;span&gt;&lt;/span&gt;&lt;span&gt;&lt;/span&gt;&lt;span&gt;&lt;/span&gt;&lt;span&gt;&lt;/span&gt;" inChartProperties="{&quot;visible&quot;: &quot;true&quot;, &quot;onLeftScale&quot;: &quot;true&quot;, &quot;color&quot;: &quot;black&quot;, &quot;chartType&quot;: &quot;0&quot;}">
      <mxGeometry x="-0.8156251001922513" y="-8.580353950525042" width="60" height="60" relative="1" TRANSLATE_CONTROL_POINTS="1" as="geometry">
        <mxPoint x="430" y="380" as="sourcePoint"/>
        <mxPoint x="514.8528137423857" y="320" as="targetPoint"/>
        <Array as="points">
          <mxPoint x="430" y="320"/>
        </Array>
        <mxPoint x="0" y="0" as="offset"/>
      </mxGeometry>
      <Resource name="Black" color="#000000" travelTime="0" as="resource"/>
    </mxResourceConnectionCell>
    <mxStateConnectionCell id="43" value="&lt;span&gt;==0&lt;/span&gt;&lt;span&gt;&lt;/span&gt;&lt;span&gt;&lt;/span&gt;&lt;span&gt;&lt;/span&gt;&lt;span&gt;&lt;/span&gt;" style="shape=state-connection;endArrow=classic;dashed=1;dashPattern=4 3;html=1;strokeWidth=2;fontSize=16;fontColor=#000000;strokeColor=#000000;entryX=0;entryY=0;entryPerimeter=0;exitX=0;exitY=0.5;exitPerimeter=0;align=left;" title="State Connection" vertex="0" edge="1" parent="1" source="13" target="41" type="4" colorCoding="0" isMachination="1" width="60" height="60" activation="passive" blinkStatus="0" connectable="1" visible="1" collapsed="0" label="&lt;span&gt;==0&lt;/span&gt;&lt;span&gt;&lt;/span&gt;&lt;span&gt;&lt;/span&gt;&lt;span&gt;&lt;/span&gt;&lt;span&gt;&lt;/span&gt;" inChartProperties="{&quot;visible&quot;: &quot;true&quot;, &quot;onLeftScale&quot;: &quot;true&quot;, &quot;color&quot;: &quot;black&quot;, &quot;chartType&quot;: &quot;0&quot;}">
      <mxGeometry x="-0.4322003816303454" y="8.571428571428502" width="60" height="60" relative="1" TRANSLATE_CONTROL_POINTS="1" as="geometry">
        <mxPoint x="430" y="220" as="sourcePoint"/>
        <mxPoint x="514.8528137423857" y="160" as="targetPoint"/>
        <mxPoint x="0" y="0" as="offset"/>
      </mxGeometry>
      <Resource name="Black" color="#000000" travelTime="0" as="resource"/>
    </mxStateConnectionCell>
    <mxDrainShapeCell id="9" style="shape=drain-shape;whiteSpace=wrap;html=1;strokeWidth=2;aspect=fixed;resizable=0;fontSize=16;fontColor=#000000;strokeColor=#000000;fillColor=#000000;" title="Drain" vertex="1" edge="0" parent="1" activation="automatic" actionMode="pull-any" isMachination="1" blinkStatus="0" connectable="1" visible="1" collapsed="0" label="Cooldown Drain" inChartProperties="{&quot;visible&quot;: &quot;true&quot;, &quot;onLeftScale&quot;: &quot;true&quot;, &quot;color&quot;: &quot;black&quot;, &quot;chartType&quot;: &quot;0&quot;}">
      <mxGeometry x="137" y="137" width="46" height="46" TRANSLATE_CONTROL_POINTS="1" relative="0" vertexOrientation="top" as="geometry">
        <mxPoint x="-3.4999999999998486" y="-56.999999999999986" as="offset"/>
      </mxGeometry>
    </mxDrainShapeCell>
    <mxConverterShapeCell id="44" style="shape=converter-shape;whiteSpace=wrap;html=1;strokeWidth=2;aspect=fixed;resizable=0;fontSize=16;fontColor=#000000;strokeColor=#000000;align=right;fontStyle=1;fillColor=#CCE5FF;" title="Converter" vertex="1" edge="0" parent="1" activation="interactive" actionMode="pull-all" isMachination="1" blinkStatus="0" connectable="1" visible="1" collapsed="0" label="Spell 2" inChartProperties="{&quot;visible&quot;: &quot;true&quot;, &quot;onLeftScale&quot;: &quot;true&quot;, &quot;color&quot;: &quot;black&quot;, &quot;chartType&quot;: &quot;0&quot;}">
      <mxGeometry x="257" y="297" width="46" height="46" TRANSLATE_CONTROL_POINTS="1" relative="0" vertexOrientation="top" as="geometry">
        <mxPoint x="-2.9999999999999245" y="-47.499999999999815" as="offset"/>
      </mxGeometry>
      <Resource name="Black" color="#000000" travelTime="0" as="resource"/>
    </mxConverterShapeCell>
    <mxResourceConnectionCell id="45" value="&lt;span&gt;7&lt;/span&gt;&lt;span&gt;&lt;/span&gt;&lt;span&gt;&lt;/span&gt;&lt;span&gt;&lt;/span&gt;&lt;span&gt;&lt;/span&gt;" style="shape=resource-connection;endArrow=classic;html=1;strokeWidth=2;fontSize=16;fontColor=#000000;strokeColor=#000000;entryX=1;entryY=0.5;entryPerimeter=0;exitX=0.9;exitY=0.5;exitPerimeter=0;align=left;" title="Resource Connection" vertex="0" edge="1" parent="1" source="44" target="14" type="plain-arrow" resourceTransfer="instantaneous" colorCoding="0" minValue="-9999" maxValue="9999" shuffleSource="0" isMachination="1" width="60" height="60" activation="passive" blinkStatus="0" connectable="1" visible="1" collapsed="0" label="&lt;span&gt;7&lt;/span&gt;&lt;span&gt;&lt;/span&gt;&lt;span&gt;&lt;/span&gt;&lt;span&gt;&lt;/span&gt;&lt;span&gt;&lt;/span&gt;" inChartProperties="{&quot;visible&quot;: &quot;true&quot;, &quot;onLeftScale&quot;: &quot;true&quot;, &quot;color&quot;: &quot;black&quot;, &quot;chartType&quot;: &quot;0&quot;}">
      <mxGeometry x="-0.7898745958794687" y="-8.84372401586632" width="60" height="60" relative="1" TRANSLATE_CONTROL_POINTS="1" as="geometry">
        <mxPoint x="310" y="380" as="sourcePoint"/>
        <mxPoint x="394.8528137423857" y="320" as="targetPoint"/>
        <Array as="points">
          <mxPoint x="310" y="320"/>
        </Array>
        <mxPoint x="0" y="0" as="offset"/>
      </mxGeometry>
      <Resource name="Black" color="#000000" travelTime="0" as="resource"/>
    </mxResourceConnectionCell>
    <mxStateConnectionCell id="46" value="&lt;span&gt;==0&lt;/span&gt;&lt;span&gt;&lt;/span&gt;&lt;span&gt;&lt;/span&gt;&lt;span&gt;&lt;/span&gt;&lt;span&gt;&lt;/span&gt;" style="shape=state-connection;endArrow=classic;dashed=1;dashPattern=4 3;html=1;strokeWidth=2;fontSize=16;fontColor=#000000;strokeColor=#000000;entryX=0;entryY=0;entryPerimeter=0;exitX=0;exitY=0.5;exitPerimeter=0;align=left;" title="State Connection" vertex="0" edge="1" parent="1" source="14" target="44" type="4" colorCoding="0" isMachination="1" width="60" height="60" activation="passive" blinkStatus="0" connectable="1" visible="1" collapsed="0" label="&lt;span&gt;==0&lt;/span&gt;&lt;span&gt;&lt;/span&gt;&lt;span&gt;&lt;/span&gt;&lt;span&gt;&lt;/span&gt;&lt;span&gt;&lt;/span&gt;" inChartProperties="{&quot;visible&quot;: &quot;true&quot;, &quot;onLeftScale&quot;: &quot;true&quot;, &quot;color&quot;: &quot;black&quot;, &quot;chartType&quot;: &quot;0&quot;}">
      <mxGeometry x="-0.42906008989382954" y="8.833333333333357" width="60" height="60" relative="1" TRANSLATE_CONTROL_POINTS="1" as="geometry">
        <mxPoint x="310" y="220" as="sourcePoint"/>
        <mxPoint x="394.8528137423857" y="160" as="targetPoint"/>
        <mxPoint x="0" y="0" as="offset"/>
      </mxGeometry>
      <Resource name="Black" color="#000000" travelTime="0" as="resource"/>
    </mxStateConnectionCell>
    <mxDrainShapeCell id="49" style="shape=drain-shape;whiteSpace=wrap;html=1;strokeWidth=2;aspect=fixed;resizable=0;fontSize=16;fontColor=#000000;strokeColor=#000000;align=right;fontStyle=1;fillColor=#CCE5FF;" title="Drain" vertex="1" edge="0" parent="1" activation="interactive" actionMode="pull-all" isMachination="1" blinkStatus="0" connectable="1" visible="1" collapsed="0" label="Spell 1" inChartProperties="{&quot;visible&quot;: &quot;true&quot;, &quot;onLeftScale&quot;: &quot;true&quot;, &quot;color&quot;: &quot;black&quot;, &quot;chartType&quot;: &quot;0&quot;}">
      <mxGeometry x="137" y="297" width="46" height="46" TRANSLATE_CONTROL_POINTS="1" relative="0" vertexOrientation="top" as="geometry">
        <mxPoint x="0.9999999999998485" y="-47.499999999999815" as="offset"/>
      </mxGeometry>
    </mxDrainShapeCell>
    <mxTextCell id="600" style="shape=text-shape;html=1;resizable=0;align=left;verticalAlign=middle;whiteSpace=wrap;rounded=0;fontSize=16;fontColor=#000000;strokeColor=none;fillColor=none;" title="Text" vertex="1" edge="0" label="&lt;div style=&quot;font-size: 20px&quot;&gt;&lt;font style=&quot;font-size: 20px&quot;&gt;Mana and Spells System&lt;/font&gt;&lt;/div&gt;&lt;div style=&quot;font-size: 20px&quot;&gt;&lt;br&gt;&lt;/div&gt;&lt;div&gt;The &quot;Mana Pool&quot; Node has a limit of 100.&lt;/div&gt;&lt;div&gt;If a spell is used, the mana is replenished&lt;/div&gt;&lt;div&gt;at a rate of 1 per second by the &quot;Generator&quot; Node.&lt;/div&gt;&lt;div&gt;&lt;br&gt;&lt;/div&gt;&lt;div&gt;Each spell has a different mana cost and&lt;/div&gt;&lt;div&gt;a different cooldown (except Spell 1, which&lt;/div&gt;&lt;div&gt;can be cast continuously, as long as&lt;/div&gt;&lt;div&gt;there's enough mana).&lt;/div&gt;&lt;div&gt;&lt;br&gt;&lt;/div&gt;&lt;div&gt;The spells pull mana from the &quot;Mana Pool&quot; and&lt;/div&gt;&lt;div&gt;either drain the resources (Spell 1) or convert them&lt;/div&gt;&lt;div&gt;in the cooldown amount designed for each spell.&lt;/div&gt;&lt;div&gt;&lt;br&gt;&lt;/div&gt;&lt;div&gt;While amount in the cooldown pool&lt;/div&gt;&lt;div&gt;assigned to each spell is higher than 0,&lt;/div&gt;&lt;div&gt;the spell can't be used.&lt;/div&gt;&lt;div&gt;&lt;br&gt;&lt;/div&gt;&lt;div&gt;The cooldown pools are drained constantly&lt;/div&gt;&lt;div&gt;at a rate of 1 per second.&lt;/div&gt;" prevLabel="&lt;div style=&quot;font-size: 20px&quot;&gt;&lt;font style=&quot;font-size: 20px&quot;&gt;Mana and Spells System&lt;/font&gt;&lt;/div&gt;&lt;div style=&quot;font-size: 20px&quot;&gt;&lt;br&gt;&lt;/div&gt;&lt;div&gt;The &quot;Mana Pool&quot; Node has a limit of 100.&lt;/div&gt;&lt;div&gt;If a spell is used, the mana is replenished&lt;/div&gt;&lt;div&gt;at a rate of 1 per second by the &quot;Generator&quot; Node.&lt;/div&gt;&lt;div&gt;&lt;br&gt;&lt;/div&gt;&lt;div&gt;Each spell has a different mana cost and&lt;/div&gt;&lt;div&gt;a different cooldown (except Spell 1, which&lt;/div&gt;&lt;div&gt;can be cast continuously, as long as&lt;/div&gt;&lt;div&gt;there's enough mana).&lt;/div&gt;&lt;div&gt;&lt;br&gt;&lt;/div&gt;&lt;div&gt;The spells pull mana from the &quot;Mana Pool&quot; and&lt;/div&gt;&lt;div&gt;either drain the resources (Spell 1) or convert them&lt;/div&gt;&lt;div&gt;in the cooldown amount designed for each spell.&lt;/div&gt;&lt;div&gt;&lt;br&gt;&lt;/div&gt;&lt;div&gt;While amount in the cooldown pool&lt;/div&gt;&lt;div&gt;assigned to each spell is higher than 0,&lt;/div&gt;&lt;div&gt;the spell can't be used.&lt;/div&gt;&lt;div&gt;&lt;br&gt;&lt;/div&gt;&lt;div&gt;The cooldown pools are drained constantly&lt;/div&gt;&lt;div&gt;at a rate of 1 per second.&lt;/div&gt;" parent="1" isMachination="0" width="60" height="60" activation="passive" blinkStatus="0" inChartProperties="{&quot;visible&quot;: &quot;true&quot;, &quot;onLeftScale&quot;: &quot;true&quot;, &quot;color&quot;: &quot;black&quot;, &quot;chartType&quot;: &quot;0&quot;}" connectable="1" visible="1" collapsed="0">
      <mxGeometry x="-300.5" y="46.5" width="375" height="403" TRANSLATE_CONTROL_POINTS="1" relative="0" as="geometry">
        <mxPoint x="0" y="0" as="offset"/>
      </mxGeometry>
    </mxTextCell>
    <mxTextCell id="601" style="shape=text-shape;html=1;resizable=0;align=left;verticalAlign=middle;whiteSpace=wrap;rounded=0;fontSize=16;fontColor=#000000;strokeColor=none;fillColor=none;" title="Text" vertex="1" edge="0" label="&lt;div&gt;* Click the Run button (in the horizontal toolbar below the diagram),&amp;nbsp;&lt;/div&gt;&lt;div&gt;then Click on double edged Nodes to activate them manually&lt;/div&gt;" prevLabel="&lt;div&gt;* Click the Run button (in the horizontal toolbar below the diagram),&amp;nbsp;&lt;/div&gt;&lt;div&gt;then Click on double edged Nodes to activate them manually&lt;/div&gt;" parent="1" isMachination="0" width="60" height="60" activation="passive" blinkStatus="0" inChartProperties="{&quot;visible&quot;: &quot;true&quot;, &quot;onLeftScale&quot;: &quot;true&quot;, &quot;color&quot;: &quot;black&quot;, &quot;chartType&quot;: &quot;0&quot;}" connectable="1" visible="1" collapsed="0">
      <mxGeometry x="-300.5" y="-63.5" width="498" height="42" TRANSLATE_CONTROL_POINTS="1" relative="0" as="geometry">
        <mxPoint x="0" y="0" as="offset"/>
      </mxGeometry>
    </mxTextCell>
  </root>
  <chart/>
</mxGraphModel>
