<?xml version="1.0"?>
<mxGraphModel>
  <root>
    <mxCell id="0"/>
    <mxCell id="1" parent="0"/>
    <mxCell id="2" style="strokeColor=#000000;strokeWidth=1;fontFamily=Roboto;fontSize=12;fontColor=#000000;align=left;" parent="1"/>
    <mxPoolShapeCell id="3" style="shape=pool-shape;whiteSpace=wrap;html=1;strokeWidth=4;aspect=fixed;resizable=0;fontSize=18;fontColor=#B266FF;strokeColor=#B266FF;align=center;fontStyle=1" title="Pool" vertex="1" edge="0" activation="interactive" actionMode="pull-any" number="0" capacity="-1" displayCapacity="25" overflow="block" isMachination="1" blinkStatus="0" connectable="1" visible="1" collapsed="0" label="Stop" parent="2">
      <mxGeometry x="-603" y="-358" width="46" height="46" TRANSLATE_CONTROL_POINTS="1" relative="0" as="geometry">
        <mxPoint x="0" y="48.5" as="offset"/>
      </mxGeometry>
      <Resource name="Black" color="#000000" travelTime="0" as="resource"/>
    </mxPoolShapeCell>
    <mxPoolShapeCell id="4" style="shape=pool-shape;whiteSpace=wrap;html=1;strokeWidth=4;aspect=fixed;resizable=0;fontSize=18;fontColor=#B266FF;strokeColor=#B266FF;align=center;fontStyle=1" title="Pool" vertex="1" edge="0" activation="interactive" actionMode="pull-any" number="0" capacity="-1" displayCapacity="25" overflow="block" isMachination="1" blinkStatus="0" connectable="1" visible="1" collapsed="0" label="Contact" parent="2">
      <mxGeometry x="-603" y="-198" width="46" height="46" TRANSLATE_CONTROL_POINTS="1" relative="0" as="geometry">
        <mxPoint x="0" y="48.5" as="offset"/>
      </mxGeometry>
      <Resource name="Black" color="#000000" travelTime="0" as="resource"/>
    </mxPoolShapeCell>
    <mxPoolShapeCell id="5" style="shape=pool-shape;whiteSpace=wrap;html=1;strokeWidth=4;aspect=fixed;resizable=0;fontSize=18;fontColor=#B266FF;strokeColor=#B266FF;align=center;fontStyle=1" title="Pool" vertex="1" edge="0" activation="interactive" actionMode="pull-any" number="0" capacity="-1" displayCapacity="25" overflow="block" isMachination="1" blinkStatus="0" connectable="1" visible="1" collapsed="0" label="Proceed " parent="2">
      <mxGeometry x="-603" y="-38" width="46" height="46" TRANSLATE_CONTROL_POINTS="1" relative="0" as="geometry">
        <mxPoint x="0" y="48.5" as="offset"/>
      </mxGeometry>
      <Resource name="Black" color="#000000" travelTime="0" as="resource"/>
    </mxPoolShapeCell>
    <mxPoolShapeCell id="6" style="shape=pool-shape;whiteSpace=wrap;html=1;strokeWidth=3;aspect=fixed;resizable=0;fontSize=16;fontColor=#CCCC00;strokeColor=#CCCC00;align=center;fillColor=#FFFF99;" title="Pool" vertex="1" edge="0" activation="automatic" actionMode="pull-any" number="0" capacity="3" displayCapacity="25" overflow="block" isMachination="1" blinkStatus="0" connectable="1" visible="1" collapsed="0" label="" parent="2">
      <mxGeometry x="-473" y="-198" width="46" height="46" TRANSLATE_CONTROL_POINTS="1" relative="0" as="geometry">
        <mxPoint x="0" y="40" as="offset"/>
      </mxGeometry>
      <Resource name="Black" color="#000000" travelTime="0" as="resource"/>
    </mxPoolShapeCell>
    <mxPoolShapeCell id="7" style="shape=pool-shape;whiteSpace=wrap;html=1;strokeWidth=3;aspect=fixed;resizable=0;fontSize=16;fontColor=#CCCC00;strokeColor=#CCCC00;align=center;fillColor=#FFFF99;" title="Pool" vertex="1" edge="0" activation="automatic" actionMode="pull-any" number="0" capacity="3" displayCapacity="25" overflow="block" isMachination="1" blinkStatus="0" connectable="1" visible="1" collapsed="0" label="" parent="2">
      <mxGeometry x="-313" y="-198" width="46" height="46" TRANSLATE_CONTROL_POINTS="1" relative="0" as="geometry">
        <mxPoint x="0" y="40" as="offset"/>
      </mxGeometry>
      <Resource name="Black" color="#000000" travelTime="0" as="resource"/>
    </mxPoolShapeCell>
    <mxSourceShapeCell id="8" style="shape=source-shape;whiteSpace=wrap;html=1;strokeWidth=3;aspect=fixed;resizable=0;fontSize=16;fontColor=#333333;strokeColor=#333333;align=center;" title="Source" vertex="1" edge="0" activation="passive" isMachination="1" blinkStatus="0" connectable="1" visible="1" collapsed="0" label="" parent="2">
      <mxGeometry x="-782.833251953125" y="-358" width="46" height="46" TRANSLATE_CONTROL_POINTS="1" relative="0" as="geometry">
        <mxPoint x="0" y="40" as="offset"/>
      </mxGeometry>
      <Resource name="Black" color="#000000" travelTime="0" as="resource"/>
    </mxSourceShapeCell>
    <mxSourceShapeCell id="9" style="shape=source-shape;whiteSpace=wrap;html=1;strokeWidth=3;aspect=fixed;resizable=0;fontSize=16;fontColor=#0066CC;strokeColor=#0066CC;align=center;" title="Source" vertex="1" edge="0" activation="passive" isMachination="1" blinkStatus="0" connectable="1" visible="1" collapsed="0" label="" parent="2">
      <mxGeometry x="-782.833251953125" y="-278" width="46" height="46" TRANSLATE_CONTROL_POINTS="1" relative="0" as="geometry">
        <mxPoint x="0" y="40" as="offset"/>
      </mxGeometry>
      <Resource name="Blue" color="#0060e0" travelTime="0" as="resource"/>
    </mxSourceShapeCell>
    <mxSourceShapeCell id="10" style="shape=source-shape;whiteSpace=wrap;html=1;strokeWidth=3;aspect=fixed;resizable=0;fontSize=16;fontColor=#009900;strokeColor=#009900;align=center;" title="Source" vertex="1" edge="0" activation="passive" isMachination="1" blinkStatus="0" connectable="1" visible="1" collapsed="0" label="" parent="2">
      <mxGeometry x="-782.833251953125" y="-198" width="46" height="46" TRANSLATE_CONTROL_POINTS="1" relative="0" as="geometry">
        <mxPoint x="0" y="40" as="offset"/>
      </mxGeometry>
      <Resource name="Green" color="#009900" travelTime="0" as="resource"/>
    </mxSourceShapeCell>
    <mxSourceShapeCell id="11" style="shape=source-shape;whiteSpace=wrap;html=1;strokeWidth=3;aspect=fixed;resizable=0;fontSize=16;fontColor=#FF8000;strokeColor=#FF8000;align=center;" title="Source" vertex="1" edge="0" activation="passive" isMachination="1" blinkStatus="0" connectable="1" visible="1" collapsed="0" label="" parent="2">
      <mxGeometry x="-783" y="-118" width="46" height="46" TRANSLATE_CONTROL_POINTS="1" relative="0" as="geometry">
        <mxPoint x="0" y="40" as="offset"/>
      </mxGeometry>
      <Resource name="Orange" color="#ff9900" travelTime="0" as="resource"/>
    </mxSourceShapeCell>
    <mxSourceShapeCell id="12" style="shape=source-shape;whiteSpace=wrap;html=1;strokeWidth=3;aspect=fixed;resizable=0;fontSize=16;fontColor=#CC0000;strokeColor=#CC0000;align=center;" title="Source" vertex="1" edge="0" activation="passive" isMachination="1" blinkStatus="0" connectable="1" visible="1" collapsed="0" label="" parent="2">
      <mxGeometry x="-783" y="-38" width="46" height="46" TRANSLATE_CONTROL_POINTS="1" relative="0" as="geometry">
        <mxPoint x="0" y="40" as="offset"/>
      </mxGeometry>
      <Resource name="Red" color="#e00000" travelTime="0" as="resource"/>
    </mxSourceShapeCell>
    <mxResourceConnectionCell id="13" value="&lt;span&gt;1&lt;/span&gt;&lt;span&gt;&lt;/span&gt;&lt;span&gt;&lt;/span&gt;&lt;span&gt;&lt;/span&gt;&lt;span&gt;&lt;/span&gt;" style="shape=resource-connection;endArrow=classic;html=1;strokeWidth=2;fontSize=16;fontColor=#000000;strokeColor=#000000;align=center;" title="Resource Connection" vertex="0" edge="1" type="plain-arrow" resourceTransfer="interval-based" colorCoding="0" minValue="-9999" maxValue="9999" shuffleSource="0" isMachination="1" width="60" height="60" activation="passive" blinkStatus="0" connectable="1" visible="1" collapsed="0" label="&lt;span&gt;1&lt;/span&gt;&lt;span&gt;&lt;/span&gt;&lt;span&gt;&lt;/span&gt;&lt;span&gt;&lt;/span&gt;&lt;span&gt;&lt;/span&gt;" parent="2" source="8" target="3">
      <mxGeometry x="-0.7448478876195487" y="-19.5" width="60" height="60" relative="1" TRANSLATE_CONTROL_POINTS="1" as="geometry">
        <mxPoint x="-709.833251953125" y="-275" as="sourcePoint"/>
        <mxPoint x="-624.9804382107393" y="-335" as="targetPoint"/>
        <mxPoint x="0" y="0" as="offset"/>
      </mxGeometry>
      <Resource name="Black" color="#000000" travelTime="0" as="resource"/>
    </mxResourceConnectionCell>
    <mxResourceConnectionCell id="14" value="&lt;span&gt;1&lt;/span&gt;&lt;span&gt;&lt;/span&gt;&lt;span&gt;&lt;/span&gt;&lt;span&gt;&lt;/span&gt;&lt;span&gt;&lt;/span&gt;" style="shape=resource-connection;endArrow=classic;html=1;strokeWidth=2;fontSize=16;fontColor=#0066CC;strokeColor=#0066CC;align=left;" title="Resource Connection" vertex="0" edge="1" type="plain-arrow" resourceTransfer="interval-based" colorCoding="0" minValue="-9999" maxValue="9999" shuffleSource="0" isMachination="1" width="60" height="60" activation="passive" blinkStatus="0" connectable="1" visible="1" collapsed="0" label="&lt;span&gt;1&lt;/span&gt;&lt;span&gt;&lt;/span&gt;&lt;span&gt;&lt;/span&gt;&lt;span&gt;&lt;/span&gt;&lt;span&gt;&lt;/span&gt;" parent="2" source="9" target="3">
      <mxGeometry x="-0.9223754385835726" y="-13.074094013969622" width="60" height="60" relative="1" TRANSLATE_CONTROL_POINTS="1" as="geometry">
        <mxPoint x="-709.833251953125" y="-195" as="sourcePoint"/>
        <mxPoint x="-624.9804382107393" y="-255" as="targetPoint"/>
        <mxPoint x="0" y="0" as="offset"/>
      </mxGeometry>
      <Resource name="Black" color="#000000" travelTime="0" as="resource"/>
    </mxResourceConnectionCell>
    <mxResourceConnectionCell id="15" value="&lt;span&gt;1&lt;/span&gt;&lt;span&gt;&lt;/span&gt;&lt;span&gt;&lt;/span&gt;&lt;span&gt;&lt;/span&gt;&lt;span&gt;&lt;/span&gt;" style="shape=resource-connection;endArrow=classic;html=1;strokeWidth=2;fontSize=16;fontColor=#CC6600;strokeColor=#CC6600;align=right;" title="Resource Connection" vertex="0" edge="1" type="plain-arrow" resourceTransfer="interval-based" colorCoding="0" minValue="-9999" maxValue="9999" shuffleSource="0" isMachination="1" width="60" height="60" activation="passive" blinkStatus="0" connectable="1" visible="1" collapsed="0" label="&lt;span&gt;1&lt;/span&gt;&lt;span&gt;&lt;/span&gt;&lt;span&gt;&lt;/span&gt;&lt;span&gt;&lt;/span&gt;&lt;span&gt;&lt;/span&gt;" parent="2" source="11" target="5">
      <mxGeometry x="-0.6740574653960599" y="-13.073132966591691" width="60" height="60" relative="1" TRANSLATE_CONTROL_POINTS="1" as="geometry">
        <mxPoint x="-709.833251953125" y="-115" as="sourcePoint"/>
        <mxPoint x="-624.9804382107393" y="-175" as="targetPoint"/>
        <mxPoint x="0" y="0" as="offset"/>
      </mxGeometry>
      <Resource name="Black" color="#000000" travelTime="0" as="resource"/>
    </mxResourceConnectionCell>
    <mxResourceConnectionCell id="16" value="&lt;span&gt;1&lt;/span&gt;&lt;span&gt;&lt;/span&gt;&lt;span&gt;&lt;/span&gt;&lt;span&gt;&lt;/span&gt;&lt;span&gt;&lt;/span&gt;" style="shape=resource-connection;endArrow=classic;html=1;strokeWidth=2;fontSize=16;fontColor=#990000;strokeColor=#990000;align=center;" title="Resource Connection" vertex="0" edge="1" type="plain-arrow" resourceTransfer="interval-based" colorCoding="0" minValue="-9999" maxValue="9999" shuffleSource="0" isMachination="1" width="60" height="60" activation="passive" blinkStatus="0" connectable="1" visible="1" collapsed="0" label="&lt;span&gt;1&lt;/span&gt;&lt;span&gt;&lt;/span&gt;&lt;span&gt;&lt;/span&gt;&lt;span&gt;&lt;/span&gt;&lt;span&gt;&lt;/span&gt;" parent="2" source="12" target="5">
      <mxGeometry x="-0.718954288258272" y="-19.5" width="60" height="60" relative="1" TRANSLATE_CONTROL_POINTS="1" as="geometry">
        <mxPoint x="-710" y="45" as="sourcePoint"/>
        <mxPoint x="-625.1471862576143" y="-15" as="targetPoint"/>
        <mxPoint x="0" y="0" as="offset"/>
      </mxGeometry>
      <Resource name="Black" color="#000000" travelTime="0" as="resource"/>
    </mxResourceConnectionCell>
    <mxResourceConnectionCell id="17" value="&lt;span&gt;1&lt;/span&gt;&lt;span&gt;&lt;/span&gt;&lt;span&gt;&lt;/span&gt;&lt;span&gt;&lt;/span&gt;&lt;span&gt;&lt;/span&gt;" style="shape=resource-connection;endArrow=classic;html=1;strokeWidth=2;fontSize=16;fontColor=#CC6600;strokeColor=#CC6600;align=left;" title="Resource Connection" vertex="0" edge="1" type="plain-arrow" resourceTransfer="interval-based" colorCoding="0" minValue="-9999" maxValue="9999" shuffleSource="0" isMachination="1" width="60" height="60" activation="passive" blinkStatus="0" connectable="1" visible="1" collapsed="0" label="&lt;span&gt;1&lt;/span&gt;&lt;span&gt;&lt;/span&gt;&lt;span&gt;&lt;/span&gt;&lt;span&gt;&lt;/span&gt;&lt;span&gt;&lt;/span&gt;" parent="2" source="11" target="4">
      <mxGeometry x="-0.9128440832865731" y="-13.073132966591553" width="60" height="60" relative="1" TRANSLATE_CONTROL_POINTS="1" as="geometry">
        <mxPoint x="-710" y="-35" as="sourcePoint"/>
        <mxPoint x="-625.1471862576143" y="-95" as="targetPoint"/>
        <mxPoint x="0" y="0" as="offset"/>
      </mxGeometry>
      <Resource name="Black" color="#000000" travelTime="0" as="resource"/>
    </mxResourceConnectionCell>
    <mxResourceConnectionCell id="18" value="&lt;span&gt;1&lt;/span&gt;&lt;span&gt;&lt;/span&gt;&lt;span&gt;&lt;/span&gt;&lt;span&gt;&lt;/span&gt;&lt;span&gt;&lt;/span&gt;" style="shape=resource-connection;endArrow=classic;html=1;strokeWidth=2;fontSize=16;fontColor=#0066CC;strokeColor=#0066CC;align=right;" title="Resource Connection" vertex="0" edge="1" type="plain-arrow" resourceTransfer="interval-based" colorCoding="0" minValue="-9999" maxValue="9999" shuffleSource="0" isMachination="1" width="60" height="60" activation="passive" blinkStatus="0" connectable="1" visible="1" collapsed="0" label="&lt;span&gt;1&lt;/span&gt;&lt;span&gt;&lt;/span&gt;&lt;span&gt;&lt;/span&gt;&lt;span&gt;&lt;/span&gt;&lt;span&gt;&lt;/span&gt;" parent="2" source="9" target="4">
      <mxGeometry x="-0.6970399974642361" y="-13.074094013969761" width="60" height="60" relative="1" TRANSLATE_CONTROL_POINTS="1" as="geometry">
        <mxPoint x="-709.833251953125" y="-195" as="sourcePoint"/>
        <mxPoint x="-624.9804382107393" y="-255" as="targetPoint"/>
        <mxPoint x="0" y="0" as="offset"/>
      </mxGeometry>
      <Resource name="Black" color="#000000" travelTime="0" as="resource"/>
    </mxResourceConnectionCell>
    <mxResourceConnectionCell id="19" value="&lt;span&gt;1&lt;/span&gt;&lt;span&gt;&lt;/span&gt;&lt;span&gt;&lt;/span&gt;&lt;span&gt;&lt;/span&gt;&lt;span&gt;&lt;/span&gt;" style="shape=resource-connection;endArrow=classic;html=1;strokeWidth=2;fontSize=16;fontColor=#009900;strokeColor=#009900;align=left;" title="Resource Connection" vertex="0" edge="1" type="plain-arrow" resourceTransfer="interval-based" colorCoding="0" minValue="-9999" maxValue="9999" shuffleSource="0" isMachination="1" width="60" height="60" activation="passive" blinkStatus="0" connectable="1" visible="1" collapsed="0" label="&lt;span&gt;1&lt;/span&gt;&lt;span&gt;&lt;/span&gt;&lt;span&gt;&lt;/span&gt;&lt;span&gt;&lt;/span&gt;&lt;span&gt;&lt;/span&gt;" parent="2" source="10" target="3">
      <mxGeometry x="-0.9068125184493031" y="-13.777858457395542" width="60" height="60" relative="1" TRANSLATE_CONTROL_POINTS="1" as="geometry">
        <mxPoint x="-709.833251953125" y="-115" as="sourcePoint"/>
        <mxPoint x="-624.9804382107393" y="-175" as="targetPoint"/>
        <mxPoint x="0" y="0" as="offset"/>
      </mxGeometry>
      <Resource name="Black" color="#000000" travelTime="0" as="resource"/>
    </mxResourceConnectionCell>
    <mxResourceConnectionCell id="20" value="&lt;span&gt;1&lt;/span&gt;&lt;span&gt;&lt;/span&gt;&lt;span&gt;&lt;/span&gt;&lt;span&gt;&lt;/span&gt;&lt;span&gt;&lt;/span&gt;" style="shape=resource-connection;endArrow=classic;html=1;strokeWidth=2;fontSize=16;fontColor=#0066CC;strokeColor=#0066CC;align=right;" title="Resource Connection" vertex="0" edge="1" type="plain-arrow" resourceTransfer="interval-based" colorCoding="0" minValue="-9999" maxValue="9999" shuffleSource="0" isMachination="1" width="60" height="60" activation="passive" blinkStatus="0" connectable="1" visible="1" collapsed="0" label="&lt;span&gt;1&lt;/span&gt;&lt;span&gt;&lt;/span&gt;&lt;span&gt;&lt;/span&gt;&lt;span&gt;&lt;/span&gt;&lt;span&gt;&lt;/span&gt;" parent="2" source="9" target="5">
      <mxGeometry x="-0.6686386117746517" y="-13.69434810644744" width="60" height="60" relative="1" TRANSLATE_CONTROL_POINTS="1" as="geometry">
        <mxPoint x="-709.833251953125" y="-275" as="sourcePoint"/>
        <mxPoint x="-624.9804382107393" y="-335" as="targetPoint"/>
        <mxPoint x="0" y="0" as="offset"/>
      </mxGeometry>
      <Resource name="Black" color="#000000" travelTime="0" as="resource"/>
    </mxResourceConnectionCell>
    <mxResourceConnectionCell id="21" value="&lt;span&gt;1&lt;/span&gt;&lt;span&gt;&lt;/span&gt;&lt;span&gt;&lt;/span&gt;&lt;span&gt;&lt;/span&gt;&lt;span&gt;&lt;/span&gt;" style="shape=resource-connection;endArrow=classic;html=1;strokeWidth=2;fontSize=16;fontColor=#009900;strokeColor=#009900;align=center;" title="Resource Connection" vertex="0" edge="1" type="plain-arrow" resourceTransfer="interval-based" colorCoding="0" minValue="-9999" maxValue="9999" shuffleSource="0" isMachination="1" width="60" height="60" activation="passive" blinkStatus="0" connectable="1" visible="1" collapsed="0" label="&lt;span&gt;1&lt;/span&gt;&lt;span&gt;&lt;/span&gt;&lt;span&gt;&lt;/span&gt;&lt;span&gt;&lt;/span&gt;&lt;span&gt;&lt;/span&gt;" parent="2" source="10" target="4">
      <mxGeometry x="-0.7841021969791716" y="-19.5" width="60" height="60" relative="1" TRANSLATE_CONTROL_POINTS="1" as="geometry">
        <mxPoint x="-709.833251953125" y="-275" as="sourcePoint"/>
        <mxPoint x="-624.9804382107393" y="-335" as="targetPoint"/>
        <mxPoint x="0" y="0" as="offset"/>
      </mxGeometry>
      <Resource name="Black" color="#000000" travelTime="0" as="resource"/>
    </mxResourceConnectionCell>
    <mxResourceConnectionCell id="22" value="&lt;span&gt;all&lt;/span&gt;&lt;span&gt;&lt;/span&gt;&lt;span&gt;&lt;/span&gt;&lt;span&gt;&lt;/span&gt;&lt;span&gt;&lt;/span&gt;" style="shape=resource-connection;endArrow=classic;html=1;strokeWidth=2;fontSize=16;fontColor=#000000;strokeColor=#000000;" title="Resource Connection" vertex="0" edge="1" type="plain-arrow" resourceTransfer="interval-based" colorCoding="0" minValue="-9999" maxValue="9999" shuffleSource="0" isMachination="1" width="60" height="60" activation="passive" blinkStatus="0" connectable="1" visible="1" collapsed="0" label="&lt;span&gt;all&lt;/span&gt;&lt;span&gt;&lt;/span&gt;&lt;span&gt;&lt;/span&gt;&lt;span&gt;&lt;/span&gt;&lt;span&gt;&lt;/span&gt;" parent="2" source="3" target="6">
      <mxGeometry x="0" y="0" width="60" height="60" relative="1" TRANSLATE_CONTROL_POINTS="1" as="geometry">
        <mxPoint x="-520" y="-275" as="sourcePoint"/>
        <mxPoint x="-435.1471862576143" y="-335" as="targetPoint"/>
        <mxPoint x="0" y="20" as="offset"/>
      </mxGeometry>
      <Resource name="Black" color="#000000" travelTime="0" as="resource"/>
    </mxResourceConnectionCell>
    <mxResourceConnectionCell id="23" value="&lt;span&gt;all&lt;/span&gt;&lt;span&gt;&lt;/span&gt;&lt;span&gt;&lt;/span&gt;&lt;span&gt;&lt;/span&gt;&lt;span&gt;&lt;/span&gt;" style="shape=resource-connection;endArrow=classic;html=1;strokeWidth=2;fontSize=16;fontColor=#000000;strokeColor=#000000;" title="Resource Connection" vertex="0" edge="1" type="plain-arrow" resourceTransfer="interval-based" colorCoding="0" minValue="-9999" maxValue="9999" shuffleSource="0" isMachination="1" width="60" height="60" activation="passive" blinkStatus="0" connectable="1" visible="1" collapsed="0" label="&lt;span&gt;all&lt;/span&gt;&lt;span&gt;&lt;/span&gt;&lt;span&gt;&lt;/span&gt;&lt;span&gt;&lt;/span&gt;&lt;span&gt;&lt;/span&gt;" parent="2" source="4" target="6">
      <mxGeometry x="0" y="0" width="60" height="60" relative="1" TRANSLATE_CONTROL_POINTS="1" as="geometry">
        <mxPoint x="-520" y="-115" as="sourcePoint"/>
        <mxPoint x="-435.1471862576143" y="-175" as="targetPoint"/>
        <mxPoint x="0" y="20" as="offset"/>
      </mxGeometry>
      <Resource name="Black" color="#000000" travelTime="0" as="resource"/>
    </mxResourceConnectionCell>
    <mxResourceConnectionCell id="24" value="&lt;span&gt;all&lt;/span&gt;&lt;span&gt;&lt;/span&gt;&lt;span&gt;&lt;/span&gt;&lt;span&gt;&lt;/span&gt;&lt;span&gt;&lt;/span&gt;" style="shape=resource-connection;endArrow=classic;html=1;strokeWidth=2;fontSize=16;fontColor=#000000;strokeColor=#000000;" title="Resource Connection" vertex="0" edge="1" type="plain-arrow" resourceTransfer="interval-based" colorCoding="0" minValue="-9999" maxValue="9999" shuffleSource="0" isMachination="1" width="60" height="60" activation="passive" blinkStatus="0" connectable="1" visible="1" collapsed="0" label="&lt;span&gt;all&lt;/span&gt;&lt;span&gt;&lt;/span&gt;&lt;span&gt;&lt;/span&gt;&lt;span&gt;&lt;/span&gt;&lt;span&gt;&lt;/span&gt;" parent="2" source="5" target="6">
      <mxGeometry x="0" y="0" width="60" height="60" relative="1" TRANSLATE_CONTROL_POINTS="1" as="geometry">
        <mxPoint x="-520" y="45" as="sourcePoint"/>
        <mxPoint x="-400" y="-15" as="targetPoint"/>
        <mxPoint x="0" y="20" as="offset"/>
      </mxGeometry>
      <Resource name="Black" color="#000000" travelTime="0" as="resource"/>
    </mxResourceConnectionCell>
    <mxResourceConnectionCell id="25" value="&lt;span&gt;all&lt;/span&gt;&lt;span&gt;&lt;/span&gt;&lt;span&gt;&lt;/span&gt;&lt;span&gt;&lt;/span&gt;&lt;span&gt;&lt;/span&gt;" style="shape=resource-connection;endArrow=classic;html=1;strokeWidth=3;fontSize=16;fontColor=#CCCC00;strokeColor=#CCCC00;align=center;" title="Resource Connection" vertex="0" edge="1" type="plain-arrow" resourceTransfer="interval-based" colorCoding="0" minValue="-9999" maxValue="3" shuffleSource="0" isMachination="1" width="60" height="60" activation="passive" blinkStatus="0" connectable="1" visible="1" collapsed="0" label="&lt;span&gt;all&lt;/span&gt;&lt;span&gt;&lt;/span&gt;&lt;span&gt;&lt;/span&gt;&lt;span&gt;&lt;/span&gt;&lt;span&gt;&lt;/span&gt;" parent="2" source="6" target="7">
      <mxGeometry x="0.8316446395663678" y="-19.5" width="60" height="60" relative="1" TRANSLATE_CONTROL_POINTS="1" as="geometry">
        <mxPoint x="-270" y="-95" as="sourcePoint"/>
        <mxPoint x="-185.1471862576143" y="-155" as="targetPoint"/>
        <mxPoint x="0" y="0" as="offset"/>
        <Array as="points">
          <mxPoint x="-390" y="-175"/>
          <mxPoint x="-380" y="-110"/>
          <mxPoint x="-360" y="-230"/>
          <mxPoint x="-350" y="-175"/>
        </Array>
      </mxGeometry>
      <Resource name="Black" color="#000000" travelTime="0" as="resource"/>
    </mxResourceConnectionCell>
    <mxResourceConnectionCell id="26" value="&lt;span&gt;3&lt;/span&gt;&lt;span&gt;&lt;/span&gt;&lt;span&gt;&lt;/span&gt;&lt;span&gt;&lt;/span&gt;&lt;span&gt;&lt;/span&gt;" style="shape=resource-connection;endArrow=classic;html=1;strokeWidth=2;fontSize=16;fontColor=#000000;strokeColor=#000000;" title="Resource Connection" vertex="0" edge="1" type="plain-arrow" resourceTransfer="interval-based" colorCoding="0" minValue="-9999" maxValue="9999" shuffleSource="0" isMachination="1" width="60" height="60" activation="passive" blinkStatus="0" connectable="1" visible="1" collapsed="0" label="&lt;span&gt;3&lt;/span&gt;&lt;span&gt;&lt;/span&gt;&lt;span&gt;&lt;/span&gt;&lt;span&gt;&lt;/span&gt;&lt;span&gt;&lt;/span&gt;" parent="2" source="7" target="71">
      <mxGeometry x="0" y="0" width="60" height="60" relative="1" TRANSLATE_CONTROL_POINTS="1" as="geometry">
        <mxPoint x="-677" y="510" as="sourcePoint"/>
        <mxPoint x="-685.7249999999999" y="280" as="targetPoint"/>
        <mxPoint x="20" y="10" as="offset"/>
      </mxGeometry>
      <Resource name="Black" color="#000000" travelTime="0" as="resource"/>
    </mxResourceConnectionCell>
    <mxResourceConnectionCell id="27" value="&lt;span&gt;3&lt;/span&gt;&lt;span&gt;&lt;/span&gt;&lt;span&gt;&lt;/span&gt;&lt;span&gt;&lt;/span&gt;&lt;span&gt;&lt;/span&gt;" style="shape=resource-connection;endArrow=classic;html=1;strokeWidth=2;fontSize=16;fontColor=#000000;strokeColor=#000000;align=left;" title="Resource Connection" vertex="0" edge="1" type="plain-arrow" resourceTransfer="interval-based" colorCoding="0" minValue="-9999" maxValue="9999" shuffleSource="0" isMachination="1" width="60" height="60" activation="passive" blinkStatus="0" connectable="1" visible="1" collapsed="0" label="&lt;span&gt;3&lt;/span&gt;&lt;span&gt;&lt;/span&gt;&lt;span&gt;&lt;/span&gt;&lt;span&gt;&lt;/span&gt;&lt;span&gt;&lt;/span&gt;" parent="2" source="7" target="73">
      <mxGeometry x="-0.030134737415589467" y="9.031210785199253" width="60" height="60" relative="1" TRANSLATE_CONTROL_POINTS="1" as="geometry">
        <mxPoint x="-839.5" y="505" as="sourcePoint"/>
        <mxPoint x="-789.5" y="535" as="targetPoint"/>
        <mxPoint x="0" y="0" as="offset"/>
      </mxGeometry>
      <Resource name="Black" color="#000000" travelTime="0" as="resource"/>
    </mxResourceConnectionCell>
    <mxPoolShapeCell id="28" style="shape=pool-shape;whiteSpace=wrap;html=1;strokeWidth=2;aspect=fixed;resizable=0;fontSize=16;fontColor=#000000;strokeColor=#000000;align=center;" title="Pool" vertex="1" edge="0" activation="passive" actionMode="push-any" number="0" capacity="-1" displayCapacity="25" overflow="block" isMachination="1" blinkStatus="0" connectable="1" visible="1" collapsed="0" label="" parent="2">
      <mxGeometry x="-141" y="-423" width="46" height="46" TRANSLATE_CONTROL_POINTS="1" relative="0" as="geometry">
        <mxPoint x="0" y="40" as="offset"/>
      </mxGeometry>
      <Resource name="Black" color="#000000" travelTime="0" as="resource"/>
    </mxPoolShapeCell>
    <mxPoolShapeCell id="29" style="shape=pool-shape;whiteSpace=wrap;html=1;strokeWidth=2;aspect=fixed;resizable=0;fontSize=16;fontColor=#000000;strokeColor=#000000;align=center;" title="Pool" vertex="1" edge="0" activation="passive" actionMode="push-any" number="0" capacity="-1" displayCapacity="25" overflow="block" isMachination="1" blinkStatus="0" connectable="1" visible="1" collapsed="0" label="" parent="2">
      <mxGeometry x="-81" y="-403" width="46" height="46" TRANSLATE_CONTROL_POINTS="1" relative="0" as="geometry">
        <mxPoint x="0" y="40" as="offset"/>
      </mxGeometry>
      <Resource name="Black" color="#000000" travelTime="0" as="resource"/>
    </mxPoolShapeCell>
    <mxPoolShapeCell id="30" style="shape=pool-shape;whiteSpace=wrap;html=1;strokeWidth=2;aspect=fixed;resizable=0;fontSize=16;fontColor=#000000;strokeColor=#000000;align=center;" title="Pool" vertex="1" edge="0" activation="passive" actionMode="push-any" number="0" capacity="-1" displayCapacity="25" overflow="block" isMachination="1" blinkStatus="0" connectable="1" visible="1" collapsed="0" label="" parent="2">
      <mxGeometry x="-61" y="-343" width="46" height="46" TRANSLATE_CONTROL_POINTS="1" relative="0" as="geometry">
        <mxPoint x="0" y="40" as="offset"/>
      </mxGeometry>
      <Resource name="Black" color="#000000" travelTime="0" as="resource"/>
    </mxPoolShapeCell>
    <mxPoolShapeCell id="31" style="shape=pool-shape;whiteSpace=wrap;html=1;strokeWidth=2;aspect=fixed;resizable=0;fontSize=16;fontColor=#000000;strokeColor=#000000;align=center;" title="Pool" vertex="1" edge="0" activation="passive" actionMode="push-any" number="0" capacity="-1" displayCapacity="25" overflow="block" isMachination="1" blinkStatus="0" connectable="1" visible="1" collapsed="0" label="" parent="2">
      <mxGeometry x="-81" y="-283" width="46" height="46" TRANSLATE_CONTROL_POINTS="1" relative="0" as="geometry">
        <mxPoint x="0" y="40" as="offset"/>
      </mxGeometry>
      <Resource name="Black" color="#000000" travelTime="0" as="resource"/>
    </mxPoolShapeCell>
    <mxPoolShapeCell id="32" style="shape=pool-shape;whiteSpace=wrap;html=1;strokeWidth=2;aspect=fixed;resizable=0;fontSize=16;fontColor=#000000;strokeColor=#000000;align=center;" title="Pool" vertex="1" edge="0" activation="passive" actionMode="push-any" number="0" capacity="-1" displayCapacity="25" overflow="block" isMachination="1" blinkStatus="0" connectable="1" visible="1" collapsed="0" label="" parent="2">
      <mxGeometry x="-141" y="-263" width="46" height="46" TRANSLATE_CONTROL_POINTS="1" relative="0" as="geometry">
        <mxPoint x="0" y="40" as="offset"/>
      </mxGeometry>
      <Resource name="Black" color="#000000" travelTime="0" as="resource"/>
    </mxPoolShapeCell>
    <mxResourceConnectionCell id="33" value="&lt;span&gt;1&lt;/span&gt;&lt;span&gt;&lt;/span&gt;&lt;span&gt;&lt;/span&gt;&lt;span&gt;&lt;/span&gt;&lt;span&gt;&lt;/span&gt;" style="shape=resource-connection;endArrow=classic;html=1;strokeWidth=2;fontSize=16;fontColor=#000000;strokeColor=#000000;" title="Resource Connection" vertex="0" edge="1" type="plain-arrow" resourceTransfer="interval-based" colorCoding="1" minValue="-9999" maxValue="9999" shuffleSource="0" isMachination="1" width="60" height="60" activation="passive" blinkStatus="0" connectable="1" visible="1" collapsed="0" label="&lt;span&gt;1&lt;/span&gt;&lt;span&gt;&lt;/span&gt;&lt;span&gt;&lt;/span&gt;&lt;span&gt;&lt;/span&gt;&lt;span&gt;&lt;/span&gt;" parent="2" source="56" target="28">
      <mxGeometry x="0" y="0" width="60" height="60" relative="1" TRANSLATE_CONTROL_POINTS="1" as="geometry">
        <mxPoint x="-226.5" y="-339.20000000000005" as="sourcePoint"/>
        <mxPoint x="-106.6471862576143" y="-320" as="targetPoint"/>
        <mxPoint x="20" y="10" as="offset"/>
      </mxGeometry>
      <Resource name="Black" color="#000000" travelTime="0" as="resource"/>
    </mxResourceConnectionCell>
    <mxResourceConnectionCell id="34" value="&lt;span&gt;1&lt;/span&gt;&lt;span&gt;&lt;/span&gt;&lt;span&gt;&lt;/span&gt;&lt;span&gt;&lt;/span&gt;&lt;span&gt;&lt;/span&gt;" style="shape=resource-connection;endArrow=classic;html=1;strokeWidth=2;fontSize=16;fontColor=#0060e0;strokeColor=#0060e0;" title="Resource Connection" vertex="0" edge="1" type="plain-arrow" resourceTransfer="interval-based" colorCoding="1" minValue="-9999" maxValue="9999" shuffleSource="0" isMachination="1" width="60" height="60" activation="passive" blinkStatus="0" connectable="1" visible="1" collapsed="0" label="&lt;span&gt;1&lt;/span&gt;&lt;span&gt;&lt;/span&gt;&lt;span&gt;&lt;/span&gt;&lt;span&gt;&lt;/span&gt;&lt;span&gt;&lt;/span&gt;" parent="2" source="56" target="29">
      <mxGeometry x="0" y="0" width="60" height="60" relative="1" TRANSLATE_CONTROL_POINTS="1" as="geometry">
        <mxPoint x="-226.5" y="-329.7297297297298" as="sourcePoint"/>
        <mxPoint x="-106.6471862576143" y="-320" as="targetPoint"/>
        <mxPoint x="20" y="10" as="offset"/>
      </mxGeometry>
      <Resource name="Blue" color="#0060e0" travelTime="0" as="resource"/>
    </mxResourceConnectionCell>
    <mxResourceConnectionCell id="35" value="&lt;span&gt;1&lt;/span&gt;&lt;span&gt;&lt;/span&gt;&lt;span&gt;&lt;/span&gt;&lt;span&gt;&lt;/span&gt;&lt;span&gt;&lt;/span&gt;" style="shape=resource-connection;endArrow=classic;html=1;strokeWidth=2;fontSize=16;fontColor=#009900;strokeColor=#009900;" title="Resource Connection" vertex="0" edge="1" type="plain-arrow" resourceTransfer="interval-based" colorCoding="1" minValue="-9999" maxValue="9999" shuffleSource="0" isMachination="1" width="60" height="60" activation="passive" blinkStatus="0" connectable="1" visible="1" collapsed="0" label="&lt;span&gt;1&lt;/span&gt;&lt;span&gt;&lt;/span&gt;&lt;span&gt;&lt;/span&gt;&lt;span&gt;&lt;/span&gt;&lt;span&gt;&lt;/span&gt;" parent="2" source="56" target="30">
      <mxGeometry x="0" y="0" width="60" height="60" relative="1" TRANSLATE_CONTROL_POINTS="1" as="geometry">
        <mxPoint x="-226.5" y="-320" as="sourcePoint"/>
        <mxPoint x="-106.6471862576143" y="-320" as="targetPoint"/>
        <mxPoint x="0" y="20" as="offset"/>
      </mxGeometry>
      <Resource name="Green" color="#009900" travelTime="0" as="resource"/>
    </mxResourceConnectionCell>
    <mxResourceConnectionCell id="36" value="&lt;span&gt;1&lt;/span&gt;&lt;span&gt;&lt;/span&gt;&lt;span&gt;&lt;/span&gt;&lt;span&gt;&lt;/span&gt;&lt;span&gt;&lt;/span&gt;" style="shape=resource-connection;endArrow=classic;html=1;strokeWidth=2;fontSize=16;fontColor=#ff9900;strokeColor=#ff9900;" title="Resource Connection" vertex="0" edge="1" type="plain-arrow" resourceTransfer="interval-based" colorCoding="1" minValue="-9999" maxValue="9999" shuffleSource="0" isMachination="1" width="60" height="60" activation="passive" blinkStatus="0" connectable="1" visible="1" collapsed="0" label="&lt;span&gt;1&lt;/span&gt;&lt;span&gt;&lt;/span&gt;&lt;span&gt;&lt;/span&gt;&lt;span&gt;&lt;/span&gt;&lt;span&gt;&lt;/span&gt;" parent="2" source="56" target="31">
      <mxGeometry x="0" y="0" width="60" height="60" relative="1" TRANSLATE_CONTROL_POINTS="1" as="geometry">
        <mxPoint x="-226.5" y="-310.2702702702702" as="sourcePoint"/>
        <mxPoint x="-106.6471862576143" y="-320" as="targetPoint"/>
        <mxPoint x="-10" y="10" as="offset"/>
      </mxGeometry>
      <Resource name="Orange" color="#ff9900" travelTime="0" as="resource"/>
    </mxResourceConnectionCell>
    <mxResourceConnectionCell id="37" value="&lt;span&gt;1&lt;/span&gt;&lt;span&gt;&lt;/span&gt;&lt;span&gt;&lt;/span&gt;&lt;span&gt;&lt;/span&gt;&lt;span&gt;&lt;/span&gt;" style="shape=resource-connection;endArrow=classic;html=1;strokeWidth=2;fontSize=16;fontColor=#e00000;strokeColor=#e00000;" title="Resource Connection" vertex="0" edge="1" type="plain-arrow" resourceTransfer="interval-based" colorCoding="1" minValue="-9999" maxValue="9999" shuffleSource="0" isMachination="1" width="60" height="60" activation="passive" blinkStatus="0" connectable="1" visible="1" collapsed="0" label="&lt;span&gt;1&lt;/span&gt;&lt;span&gt;&lt;/span&gt;&lt;span&gt;&lt;/span&gt;&lt;span&gt;&lt;/span&gt;&lt;span&gt;&lt;/span&gt;" parent="2" source="56" target="32">
      <mxGeometry x="0" y="0" width="60" height="60" relative="1" TRANSLATE_CONTROL_POINTS="1" as="geometry">
        <mxPoint x="-226.5" y="-300.79999999999995" as="sourcePoint"/>
        <mxPoint x="-106.6471862576143" y="-320" as="targetPoint"/>
        <mxPoint x="-10" y="10" as="offset"/>
      </mxGeometry>
      <Resource name="Red" color="#e00000" travelTime="0" as="resource"/>
    </mxResourceConnectionCell>
    <mxPoolShapeCell id="38" style="shape=pool-shape;whiteSpace=wrap;html=1;strokeWidth=2;aspect=fixed;resizable=0;fontSize=16;fontColor=#000000;strokeColor=#000000;align=center;" title="Pool" vertex="1" edge="0" activation="automatic" actionMode="pull-any" number="0" capacity="-1" displayCapacity="25" overflow="block" isMachination="1" blinkStatus="0" connectable="1" visible="1" collapsed="0" label="" parent="2">
      <mxGeometry x="87" y="-443" width="46" height="46" TRANSLATE_CONTROL_POINTS="1" relative="0" as="geometry">
        <mxPoint x="0" y="40" as="offset"/>
      </mxGeometry>
      <Resource name="Black" color="#000000" travelTime="0" as="resource"/>
    </mxPoolShapeCell>
    <mxStateConnectionCell id="39" value="&lt;span&gt;&gt;0&lt;/span&gt;&lt;span&gt;&lt;/span&gt;&lt;span&gt;&lt;/span&gt;&lt;span&gt;&lt;/span&gt;&lt;span&gt;&lt;/span&gt;" style="shape=state-connection;endArrow=classic;dashed=1;dashPattern=4 3;html=1;strokeWidth=2;fontSize=16;fontColor=#000000;strokeColor=#000000;" title="State Connection" vertex="0" edge="1" type="0" colorCoding="0" isMachination="1" width="60" height="60" activation="passive" blinkStatus="0" connectable="1" visible="1" collapsed="0" label="&lt;span&gt;&amp;gt;0&lt;/span&gt;&lt;span&gt;&lt;/span&gt;&lt;span&gt;&lt;/span&gt;&lt;span&gt;&lt;/span&gt;&lt;span&gt;&lt;/span&gt;" parent="2" source="29" target="38">
      <mxGeometry x="0" y="0" width="60" height="60" relative="1" TRANSLATE_CONTROL_POINTS="1" as="geometry">
        <mxPoint x="-28" y="-320" as="sourcePoint"/>
        <mxPoint x="56.852813742385706" y="-380" as="targetPoint"/>
        <Array as="points">
          <mxPoint x="37" y="-350"/>
        </Array>
        <mxPoint x="-10" y="10" as="offset"/>
      </mxGeometry>
      <Resource name="Black" color="#000000" travelTime="0" as="resource"/>
    </mxStateConnectionCell>
    <mxResourceConnectionCell id="40" value="&lt;span&gt;1&lt;/span&gt;&lt;span&gt;&lt;/span&gt;&lt;span&gt;&lt;/span&gt;&lt;span&gt;&lt;/span&gt;&lt;span&gt;&lt;/span&gt;" style="shape=resource-connection;endArrow=classic;html=1;strokeWidth=2;fontSize=16;fontColor=#0060e0;strokeColor=#0060e0;" title="Resource Connection" vertex="0" edge="1" type="plain-arrow" resourceTransfer="interval-based" colorCoding="1" minValue="-9999" maxValue="9999" shuffleSource="0" isMachination="1" width="60" height="60" activation="passive" blinkStatus="0" connectable="1" visible="1" collapsed="0" label="&lt;span&gt;1&lt;/span&gt;&lt;span&gt;&lt;/span&gt;&lt;span&gt;&lt;/span&gt;&lt;span&gt;&lt;/span&gt;&lt;span&gt;&lt;/span&gt;" parent="2" source="29" target="38">
      <mxGeometry x="0" y="0" width="60" height="60" relative="1" TRANSLATE_CONTROL_POINTS="1" as="geometry">
        <mxPoint x="-28" y="-320" as="sourcePoint"/>
        <mxPoint x="56.852813742385706" y="-380" as="targetPoint"/>
        <mxPoint x="-10" y="10" as="offset"/>
      </mxGeometry>
      <Resource name="Blue" color="#0060e0" travelTime="0" as="resource"/>
    </mxResourceConnectionCell>
    <mxPoolShapeCell id="41" style="shape=pool-shape;whiteSpace=wrap;html=1;strokeWidth=2;aspect=fixed;resizable=0;fontSize=16;fontColor=#000000;strokeColor=#000000;align=left;" title="Pool" vertex="1" edge="0" activation="automatic" actionMode="pull-any" number="0" capacity="-1" displayCapacity="25" overflow="block" isMachination="1" blinkStatus="0" connectable="1" visible="1" collapsed="0" label="" parent="2">
      <mxGeometry x="87" y="-243" width="46" height="46" TRANSLATE_CONTROL_POINTS="1" relative="0" as="geometry">
        <mxPoint x="0" y="40" as="offset"/>
      </mxGeometry>
      <Resource name="Black" color="#000000" travelTime="0" as="resource"/>
    </mxPoolShapeCell>
    <mxResourceConnectionCell id="42" value="&lt;span&gt;1&lt;/span&gt;&lt;span&gt;&lt;/span&gt;&lt;span&gt;&lt;/span&gt;&lt;span&gt;&lt;/span&gt;&lt;span&gt;&lt;/span&gt;" style="shape=resource-connection;endArrow=classic;html=1;strokeWidth=2;fontSize=16;fontColor=#ff9900;strokeColor=#ff9900;align=center;" title="Resource Connection" vertex="0" edge="1" type="plain-arrow" resourceTransfer="interval-based" colorCoding="1" minValue="-9999" maxValue="9999" shuffleSource="0" isMachination="1" width="60" height="60" activation="passive" blinkStatus="0" connectable="1" visible="1" collapsed="0" label="&lt;span&gt;1&lt;/span&gt;&lt;span&gt;&lt;/span&gt;&lt;span&gt;&lt;/span&gt;&lt;span&gt;&lt;/span&gt;&lt;span&gt;&lt;/span&gt;" parent="2" source="31" target="41">
      <mxGeometry x="-0.10781882957175926" y="-19.5" width="60" height="60" relative="1" TRANSLATE_CONTROL_POINTS="1" as="geometry">
        <mxPoint x="-28" y="-200" as="sourcePoint"/>
        <mxPoint x="56.852813742385706" y="-260" as="targetPoint"/>
        <mxPoint x="0" y="0" as="offset"/>
      </mxGeometry>
      <Resource name="Orange" color="#ff9900" travelTime="0" as="resource"/>
    </mxResourceConnectionCell>
    <mxPoolShapeCell id="43" style="shape=pool-shape;whiteSpace=wrap;html=1;strokeWidth=2;aspect=fixed;resizable=0;fontSize=16;fontColor=#000000;strokeColor=#000000;align=left;" title="Pool" vertex="1" edge="0" activation="automatic" actionMode="pull-any" number="0" capacity="-1" displayCapacity="25" overflow="block" isMachination="1" blinkStatus="0" connectable="1" visible="1" collapsed="0" label="" parent="2">
      <mxGeometry x="87" y="-343" width="46" height="46" TRANSLATE_CONTROL_POINTS="1" relative="0" as="geometry">
        <mxPoint x="0" y="40" as="offset"/>
      </mxGeometry>
      <Resource name="Black" color="#000000" travelTime="0" as="resource"/>
    </mxPoolShapeCell>
    <mxResourceConnectionCell id="44" value="&lt;span&gt;1&lt;/span&gt;&lt;span&gt;&lt;/span&gt;&lt;span&gt;&lt;/span&gt;&lt;span&gt;&lt;/span&gt;&lt;span&gt;&lt;/span&gt;" style="shape=resource-connection;endArrow=classic;html=1;strokeWidth=2;fontSize=16;fontColor=#009900;strokeColor=#009900;align=center;" title="Resource Connection" vertex="0" edge="1" type="plain-arrow" resourceTransfer="interval-based" colorCoding="1" minValue="-9999" maxValue="9999" shuffleSource="0" isMachination="1" width="60" height="60" activation="passive" blinkStatus="0" connectable="1" visible="1" collapsed="0" label="&lt;span&gt;1&lt;/span&gt;&lt;span&gt;&lt;/span&gt;&lt;span&gt;&lt;/span&gt;&lt;span&gt;&lt;/span&gt;&lt;span&gt;&lt;/span&gt;" parent="2" source="30" target="43">
      <mxGeometry x="-0.5276192801339286" y="-19.5" width="60" height="60" relative="1" TRANSLATE_CONTROL_POINTS="1" as="geometry">
        <mxPoint x="-8" y="-260" as="sourcePoint"/>
        <mxPoint x="76.8528137423857" y="-320" as="targetPoint"/>
        <mxPoint x="0" y="0" as="offset"/>
      </mxGeometry>
      <Resource name="Green" color="#009900" travelTime="0" as="resource"/>
    </mxResourceConnectionCell>
    <mxStateConnectionCell id="45" value="&lt;span&gt;&gt;0&lt;/span&gt;&lt;span&gt;&lt;/span&gt;&lt;span&gt;&lt;/span&gt;&lt;span&gt;&lt;/span&gt;&lt;span&gt;&lt;/span&gt;" style="shape=state-connection;endArrow=classic;dashed=1;dashPattern=4 3;html=1;strokeWidth=2;fontSize=16;fontColor=#000000;strokeColor=#000000;align=right;" title="State Connection" vertex="0" edge="1" type="0" colorCoding="0" isMachination="1" width="60" height="60" activation="passive" blinkStatus="0" connectable="1" visible="1" collapsed="0" label="&lt;span&gt;&amp;gt;0&lt;/span&gt;&lt;span&gt;&lt;/span&gt;&lt;span&gt;&lt;/span&gt;&lt;span&gt;&lt;/span&gt;&lt;span&gt;&lt;/span&gt;" parent="2" source="38" target="41">
      <mxGeometry x="0.607250180706196" y="-13.288478807785749" width="60" height="60" relative="1" TRANSLATE_CONTROL_POINTS="1" as="geometry">
        <mxPoint x="140" y="-320" as="sourcePoint"/>
        <mxPoint x="224.8528137423857" y="-380" as="targetPoint"/>
        <Array as="points">
          <mxPoint x="40" y="-320"/>
        </Array>
        <mxPoint x="0" y="0" as="offset"/>
      </mxGeometry>
      <Resource name="Black" color="#000000" travelTime="0" as="resource"/>
    </mxStateConnectionCell>
    <mxStateConnectionCell id="46" value="&lt;span&gt;&gt;0&lt;/span&gt;&lt;span&gt;&lt;/span&gt;&lt;span&gt;&lt;/span&gt;&lt;span&gt;&lt;/span&gt;&lt;span&gt;&lt;/span&gt;" style="shape=state-connection;endArrow=classic;dashed=1;dashPattern=4 3;html=1;strokeWidth=2;fontSize=16;fontColor=#000000;strokeColor=#000000;align=left;" title="State Connection" vertex="0" edge="1" type="0" colorCoding="0" isMachination="1" width="60" height="60" activation="passive" blinkStatus="0" connectable="1" visible="1" collapsed="0" label="&lt;span&gt;&amp;gt;0&lt;/span&gt;&lt;span&gt;&lt;/span&gt;&lt;span&gt;&lt;/span&gt;&lt;span&gt;&lt;/span&gt;&lt;span&gt;&lt;/span&gt;" parent="2" source="38" target="43">
      <mxGeometry x="-0.18992681826741956" y="13.387223214630145" width="60" height="60" relative="1" TRANSLATE_CONTROL_POINTS="1" as="geometry">
        <mxPoint x="140" y="-320" as="sourcePoint"/>
        <mxPoint x="240" y="-440" as="targetPoint"/>
        <Array as="points">
          <mxPoint x="190" y="-380"/>
        </Array>
        <mxPoint x="0" y="0" as="offset"/>
      </mxGeometry>
      <Resource name="Black" color="#000000" travelTime="0" as="resource"/>
    </mxStateConnectionCell>
    <mxPoolShapeCell id="47" style="shape=pool-shape;whiteSpace=wrap;html=1;strokeWidth=6;aspect=fixed;resizable=0;fontSize=18;fontColor=#B266FF;strokeColor=#B266FF;fontStyle=1;align=left;" title="Pool" vertex="1" edge="0" activation="automatic" actionMode="pull-any" number="0" capacity="-1" displayCapacity="25" overflow="block" isMachination="1" blinkStatus="0" connectable="1" visible="1" collapsed="0" label="Proceed" parent="2">
      <mxGeometry x="357" y="-263" width="46" height="46" TRANSLATE_CONTROL_POINTS="1" relative="0" vertexOrientation="right" as="geometry">
        <mxPoint x="68.25" y="-0.75" as="offset"/>
      </mxGeometry>
      <Resource name="Black" color="#000000" travelTime="0" as="resource"/>
    </mxPoolShapeCell>
    <mxStateConnectionCell id="48" value="&lt;span&gt;&gt;0&lt;/span&gt;&lt;span&gt;&lt;/span&gt;&lt;span&gt;&lt;/span&gt;&lt;span&gt;&lt;/span&gt;&lt;span&gt;&lt;/span&gt;" style="shape=state-connection;endArrow=classic;dashed=1;dashPattern=4 3;html=1;strokeWidth=2;fontSize=16;fontColor=#000000;strokeColor=#000000;align=right;" title="State Connection" vertex="0" edge="1" type="0" colorCoding="0" isMachination="1" width="60" height="60" activation="passive" blinkStatus="0" connectable="1" visible="1" collapsed="0" label="&lt;span&gt;&amp;gt;0&lt;/span&gt;&lt;span&gt;&lt;/span&gt;&lt;span&gt;&lt;/span&gt;&lt;span&gt;&lt;/span&gt;&lt;span&gt;&lt;/span&gt;" parent="2" source="41" target="91">
      <mxGeometry x="-0.1926812567361965" y="-11.82228955533503" width="60" height="60" relative="1" TRANSLATE_CONTROL_POINTS="1" as="geometry">
        <mxPoint x="140" y="-200" as="sourcePoint"/>
        <mxPoint x="224.8528137423857" y="-260" as="targetPoint"/>
        <Array as="points">
          <mxPoint x="180" y="-290"/>
        </Array>
        <mxPoint x="0" y="0" as="offset"/>
      </mxGeometry>
      <Resource name="Black" color="#000000" travelTime="0" as="resource"/>
    </mxStateConnectionCell>
    <mxResourceConnectionCell id="49" value="&lt;span&gt;1&lt;/span&gt;&lt;span&gt;&lt;/span&gt;&lt;span&gt;&lt;/span&gt;&lt;span&gt;&lt;/span&gt;&lt;span&gt;&lt;/span&gt;" style="shape=resource-connection;endArrow=classic;html=1;strokeWidth=2;fontSize=16;fontColor=#e00000;strokeColor=#e00000;align=center;" title="Resource Connection" vertex="0" edge="1" type="plain-arrow" resourceTransfer="interval-based" colorCoding="1" minValue="-9999" maxValue="9999" shuffleSource="0" isMachination="1" width="60" height="60" activation="passive" blinkStatus="0" connectable="1" visible="1" collapsed="0" label="&lt;span&gt;1&lt;/span&gt;&lt;span&gt;&lt;/span&gt;&lt;span&gt;&lt;/span&gt;&lt;span&gt;&lt;/span&gt;&lt;span&gt;&lt;/span&gt;" parent="2" source="32" target="90">
      <mxGeometry x="-0.08940024889529954" y="19.5" width="60" height="60" relative="1" TRANSLATE_CONTROL_POINTS="1" as="geometry">
        <mxPoint x="-88" y="-180" as="sourcePoint"/>
        <mxPoint x="-3.147186257614294" y="-240" as="targetPoint"/>
        <Array as="points">
          <mxPoint x="50" y="-180"/>
        </Array>
        <mxPoint x="0" y="0" as="offset"/>
      </mxGeometry>
      <Resource name="Red" color="#e00000" travelTime="0" as="resource"/>
    </mxResourceConnectionCell>
    <mxPoolShapeCell id="50" style="shape=pool-shape;whiteSpace=wrap;html=1;strokeWidth=5;aspect=fixed;resizable=0;fontSize=18;fontColor=#B266FF;strokeColor=#B266FF;fontStyle=1;align=left;" title="Pool" vertex="1" edge="0" activation="automatic" actionMode="pull-any" number="0" capacity="-1" displayCapacity="25" overflow="block" isMachination="1" blinkStatus="0" connectable="1" visible="1" collapsed="0" label="Stop" parent="2">
      <mxGeometry x="357" y="-423" width="46" height="46" TRANSLATE_CONTROL_POINTS="1" relative="0" vertexOrientation="right" as="geometry">
        <mxPoint x="57.25" y="1.25" as="offset"/>
      </mxGeometry>
      <Resource name="Black" color="#000000" travelTime="0" as="resource"/>
    </mxPoolShapeCell>
    <mxResourceConnectionCell id="51" value="&lt;span&gt;1&lt;/span&gt;&lt;span&gt;&lt;/span&gt;&lt;span&gt;&lt;/span&gt;&lt;span&gt;&lt;/span&gt;&lt;span&gt;&lt;/span&gt;" style="shape=resource-connection;endArrow=classic;html=1;strokeWidth=2;fontSize=16;fontColor=#000000;strokeColor=#000000;" title="Resource Connection" vertex="0" edge="1" type="plain-arrow" resourceTransfer="interval-based" colorCoding="1" minValue="-9999" maxValue="9999" shuffleSource="0" isMachination="1" width="60" height="60" activation="passive" blinkStatus="0" connectable="1" visible="1" collapsed="0" label="&lt;span&gt;1&lt;/span&gt;&lt;span&gt;&lt;/span&gt;&lt;span&gt;&lt;/span&gt;&lt;span&gt;&lt;/span&gt;&lt;span&gt;&lt;/span&gt;" parent="2" source="28" target="92">
      <mxGeometry x="0" y="0" width="60" height="60" relative="1" TRANSLATE_CONTROL_POINTS="1" as="geometry">
        <mxPoint x="-88" y="-340" as="sourcePoint"/>
        <mxPoint x="-3.147186257614294" y="-400" as="targetPoint"/>
        <Array as="points">
          <mxPoint x="50" y="-460"/>
        </Array>
        <mxPoint x="0" y="20" as="offset"/>
      </mxGeometry>
      <Resource name="Black" color="#000000" travelTime="0" as="resource"/>
    </mxResourceConnectionCell>
    <mxStateConnectionCell id="52" value="&lt;span&gt;&gt;0&lt;/span&gt;&lt;span&gt;&lt;/span&gt;&lt;span&gt;&lt;/span&gt;&lt;span&gt;&lt;/span&gt;&lt;span&gt;&lt;/span&gt;" style="shape=state-connection;endArrow=classic;dashed=1;dashPattern=4 3;html=1;strokeWidth=2;fontSize=16;fontColor=#000000;strokeColor=#000000;align=left;" title="State Connection" vertex="0" edge="1" type="0" colorCoding="0" isMachination="1" width="60" height="60" activation="passive" blinkStatus="0" connectable="1" visible="1" collapsed="0" label="&lt;span&gt;&amp;gt;0&lt;/span&gt;&lt;span&gt;&lt;/span&gt;&lt;span&gt;&lt;/span&gt;&lt;span&gt;&lt;/span&gt;&lt;span&gt;&lt;/span&gt;" parent="2" source="43" target="92">
      <mxGeometry x="-0.30700622422257595" y="-13.521980673998796" width="60" height="60" relative="1" TRANSLATE_CONTROL_POINTS="1" as="geometry">
        <mxPoint x="200" y="-260" as="sourcePoint"/>
        <mxPoint x="284.8528137423857" y="-320" as="targetPoint"/>
        <Array as="points">
          <mxPoint x="210" y="-370"/>
        </Array>
        <mxPoint x="0" y="0" as="offset"/>
      </mxGeometry>
      <Resource name="Black" color="#000000" travelTime="0" as="resource"/>
    </mxStateConnectionCell>
    <mxPoolShapeCell id="53" style="shape=pool-shape;whiteSpace=wrap;html=1;strokeWidth=5;aspect=fixed;resizable=0;fontSize=18;fontColor=#B266FF;strokeColor=#B266FF;fontStyle=1;align=left;" title="Pool" vertex="1" edge="0" activation="automatic" actionMode="pull-any" number="0" capacity="-1" displayCapacity="25" overflow="block" isMachination="1" blinkStatus="0" connectable="1" visible="1" collapsed="0" label="Contact" parent="2">
      <mxGeometry x="357" y="-343" width="46" height="46" TRANSLATE_CONTROL_POINTS="1" relative="0" vertexOrientation="right" as="geometry">
        <mxPoint x="66.75" y="3.25" as="offset"/>
      </mxGeometry>
      <Resource name="Black" color="#000000" travelTime="0" as="resource"/>
    </mxPoolShapeCell>
    <mxResourceConnectionCell id="54" value="&lt;span&gt;1&lt;/span&gt;&lt;span&gt;&lt;/span&gt;&lt;span&gt;&lt;/span&gt;&lt;span&gt;&lt;/span&gt;&lt;span&gt;&lt;/span&gt;" style="shape=resource-connection;endArrow=classic;html=1;strokeWidth=2;fontSize=16;fontColor=#009900;strokeColor=#009900;" title="Resource Connection" vertex="0" edge="1" type="plain-arrow" resourceTransfer="interval-based" colorCoding="1" minValue="-9999" maxValue="9999" shuffleSource="0" isMachination="1" width="60" height="60" activation="passive" blinkStatus="0" connectable="1" visible="1" collapsed="0" label="&lt;span&gt;1&lt;/span&gt;&lt;span&gt;&lt;/span&gt;&lt;span&gt;&lt;/span&gt;&lt;span&gt;&lt;/span&gt;&lt;span&gt;&lt;/span&gt;" parent="2" source="43" target="91">
      <mxGeometry x="0" y="0" width="60" height="60" relative="1" TRANSLATE_CONTROL_POINTS="1" as="geometry">
        <mxPoint x="200" y="-260" as="sourcePoint"/>
        <mxPoint x="284.8528137423857" y="-320" as="targetPoint"/>
        <mxPoint x="0" y="20" as="offset"/>
      </mxGeometry>
      <Resource name="Green" color="#009900" travelTime="0" as="resource"/>
    </mxResourceConnectionCell>
    <mxStateConnectionCell id="55" value="&lt;span&gt;&gt;0&lt;/span&gt;&lt;span&gt;&lt;/span&gt;&lt;span&gt;&lt;/span&gt;&lt;span&gt;&lt;/span&gt;&lt;span&gt;&lt;/span&gt;" style="shape=state-connection;endArrow=classic;dashed=1;dashPattern=4 3;html=1;strokeWidth=2;fontSize=16;fontColor=#000000;strokeColor=#000000;" title="State Connection" vertex="0" edge="1" type="0" colorCoding="0" isMachination="1" width="60" height="60" activation="passive" blinkStatus="0" connectable="1" visible="1" collapsed="0" label="&lt;span&gt;&amp;gt;0&lt;/span&gt;&lt;span&gt;&lt;/span&gt;&lt;span&gt;&lt;/span&gt;&lt;span&gt;&lt;/span&gt;&lt;span&gt;&lt;/span&gt;" parent="2" source="41" target="90">
      <mxGeometry x="0" y="0" width="60" height="60" relative="1" TRANSLATE_CONTROL_POINTS="1" as="geometry">
        <mxPoint x="140" y="-200" as="sourcePoint"/>
        <mxPoint x="150" y="-160" as="targetPoint"/>
        <Array as="points">
          <mxPoint x="190" y="-260"/>
        </Array>
        <mxPoint x="-10" y="10" as="offset"/>
      </mxGeometry>
      <Resource name="Black" color="#000000" travelTime="0" as="resource"/>
    </mxStateConnectionCell>
    <mxGateShapeCell id="56" style="shape=gate-shape;whiteSpace=wrap;html=1;strokeWidth=2;aspect=fixed;resizable=0;fontSize=16;fontColor=#000000;strokeColor=#000000;align=left;" title="Gate" vertex="1" edge="0" actionMode="pull-any" distributionMode="deterministic" isMachination="1" activation="automatic" blinkStatus="0" connectable="1" visible="1" collapsed="0" label="" parent="2">
      <mxGeometry x="-281" y="-343" width="46" height="46" TRANSLATE_CONTROL_POINTS="1" relative="0" as="geometry">
        <mxPoint x="0" y="40" as="offset"/>
      </mxGeometry>
    </mxGateShapeCell>
    <mxPoolShapeCell id="57" style="shape=pool-shape;whiteSpace=wrap;html=1;strokeWidth=2;aspect=fixed;resizable=0;fontSize=16;fontColor=#000000;strokeColor=#000000;align=center;" title="Pool" vertex="1" edge="0" activation="passive" actionMode="push-any" number="0" capacity="-1" displayCapacity="25" overflow="block" isMachination="1" blinkStatus="0" connectable="1" visible="1" collapsed="0" label="" parent="2">
      <mxGeometry x="-143.5" y="-133" width="46" height="46" TRANSLATE_CONTROL_POINTS="1" relative="0" as="geometry">
        <mxPoint x="0" y="40" as="offset"/>
      </mxGeometry>
      <Resource name="Black" color="#000000" travelTime="0" as="resource"/>
    </mxPoolShapeCell>
    <mxPoolShapeCell id="58" style="shape=pool-shape;whiteSpace=wrap;html=1;strokeWidth=2;aspect=fixed;resizable=0;fontSize=16;fontColor=#000000;strokeColor=#000000;align=center;" title="Pool" vertex="1" edge="0" activation="passive" actionMode="push-any" number="0" capacity="-1" displayCapacity="25" overflow="block" isMachination="1" blinkStatus="0" connectable="1" visible="1" collapsed="0" label="" parent="2">
      <mxGeometry x="-83.5" y="-103" width="46" height="46" TRANSLATE_CONTROL_POINTS="1" relative="0" as="geometry">
        <mxPoint x="0" y="40" as="offset"/>
      </mxGeometry>
      <Resource name="Black" color="#000000" travelTime="0" as="resource"/>
    </mxPoolShapeCell>
    <mxPoolShapeCell id="59" style="shape=pool-shape;whiteSpace=wrap;html=1;strokeWidth=2;aspect=fixed;resizable=0;fontSize=16;fontColor=#000000;strokeColor=#000000;align=center;" title="Pool" vertex="1" edge="0" activation="passive" actionMode="push-any" number="0" capacity="-1" displayCapacity="25" overflow="block" isMachination="1" blinkStatus="0" connectable="1" visible="1" collapsed="0" label="" parent="2">
      <mxGeometry x="-63.5" y="-43" width="46" height="46" TRANSLATE_CONTROL_POINTS="1" relative="0" as="geometry">
        <mxPoint x="0" y="40" as="offset"/>
      </mxGeometry>
      <Resource name="Black" color="#000000" travelTime="0" as="resource"/>
    </mxPoolShapeCell>
    <mxPoolShapeCell id="60" style="shape=pool-shape;whiteSpace=wrap;html=1;strokeWidth=2;aspect=fixed;resizable=0;fontSize=16;fontColor=#000000;strokeColor=#000000;align=center;" title="Pool" vertex="1" edge="0" activation="passive" actionMode="push-any" number="0" capacity="-1" displayCapacity="25" overflow="block" isMachination="1" blinkStatus="0" connectable="1" visible="1" collapsed="0" label="" parent="2">
      <mxGeometry x="-83.5" y="17" width="46" height="46" TRANSLATE_CONTROL_POINTS="1" relative="0" as="geometry">
        <mxPoint x="0" y="40" as="offset"/>
      </mxGeometry>
      <Resource name="Black" color="#000000" travelTime="0" as="resource"/>
    </mxPoolShapeCell>
    <mxPoolShapeCell id="61" style="shape=pool-shape;whiteSpace=wrap;html=1;strokeWidth=2;aspect=fixed;resizable=0;fontSize=16;fontColor=#000000;strokeColor=#000000;align=center;" title="Pool" vertex="1" edge="0" activation="passive" actionMode="push-any" number="0" capacity="-1" displayCapacity="25" overflow="block" isMachination="1" blinkStatus="0" connectable="1" visible="1" collapsed="0" label="" parent="2">
      <mxGeometry x="-143.5" y="37" width="46" height="46" TRANSLATE_CONTROL_POINTS="1" relative="0" as="geometry">
        <mxPoint x="0" y="40" as="offset"/>
      </mxGeometry>
      <Resource name="Black" color="#000000" travelTime="0" as="resource"/>
    </mxPoolShapeCell>
    <mxResourceConnectionCell id="62" value="&lt;span&gt;1&lt;/span&gt;&lt;span&gt;&lt;/span&gt;&lt;span&gt;&lt;/span&gt;&lt;span&gt;&lt;/span&gt;&lt;span&gt;&lt;/span&gt;" style="shape=resource-connection;endArrow=classic;html=1;strokeWidth=2;fontSize=16;fontColor=#000000;strokeColor=#000000;" title="Resource Connection" vertex="0" edge="1" type="plain-arrow" resourceTransfer="interval-based" colorCoding="1" minValue="-9999" maxValue="9999" shuffleSource="0" isMachination="1" width="60" height="60" activation="passive" blinkStatus="0" connectable="1" visible="1" collapsed="0" label="&lt;span&gt;1&lt;/span&gt;&lt;span&gt;&lt;/span&gt;&lt;span&gt;&lt;/span&gt;&lt;span&gt;&lt;/span&gt;&lt;span&gt;&lt;/span&gt;" parent="2" source="67" target="57">
      <mxGeometry x="0" y="0" width="60" height="60" relative="1" TRANSLATE_CONTROL_POINTS="1" as="geometry">
        <mxPoint x="-229" y="-39.200000000000045" as="sourcePoint"/>
        <mxPoint x="-109.1471862576143" y="-20" as="targetPoint"/>
        <mxPoint x="20" y="10" as="offset"/>
      </mxGeometry>
      <Resource name="Black" color="#000000" travelTime="0" as="resource"/>
    </mxResourceConnectionCell>
    <mxResourceConnectionCell id="63" value="&lt;span&gt;1&lt;/span&gt;&lt;span&gt;&lt;/span&gt;&lt;span&gt;&lt;/span&gt;&lt;span&gt;&lt;/span&gt;&lt;span&gt;&lt;/span&gt;" style="shape=resource-connection;endArrow=classic;html=1;strokeWidth=2;fontSize=16;fontColor=#0060e0;strokeColor=#0060e0;" title="Resource Connection" vertex="0" edge="1" type="plain-arrow" resourceTransfer="interval-based" colorCoding="1" minValue="-9999" maxValue="9999" shuffleSource="0" isMachination="1" width="60" height="60" activation="passive" blinkStatus="0" connectable="1" visible="1" collapsed="0" label="&lt;span&gt;1&lt;/span&gt;&lt;span&gt;&lt;/span&gt;&lt;span&gt;&lt;/span&gt;&lt;span&gt;&lt;/span&gt;&lt;span&gt;&lt;/span&gt;" parent="2" source="67" target="58">
      <mxGeometry x="0" y="0" width="60" height="60" relative="1" TRANSLATE_CONTROL_POINTS="1" as="geometry">
        <mxPoint x="-229" y="-29.729729729729797" as="sourcePoint"/>
        <mxPoint x="-109.1471862576143" y="-20" as="targetPoint"/>
        <mxPoint x="20" y="10" as="offset"/>
      </mxGeometry>
      <Resource name="Blue" color="#0060e0" travelTime="0" as="resource"/>
    </mxResourceConnectionCell>
    <mxResourceConnectionCell id="64" value="&lt;span&gt;1&lt;/span&gt;&lt;span&gt;&lt;/span&gt;&lt;span&gt;&lt;/span&gt;&lt;span&gt;&lt;/span&gt;&lt;span&gt;&lt;/span&gt;" style="shape=resource-connection;endArrow=classic;html=1;strokeWidth=2;fontSize=16;fontColor=#009900;strokeColor=#009900;" title="Resource Connection" vertex="0" edge="1" type="plain-arrow" resourceTransfer="interval-based" colorCoding="1" minValue="-9999" maxValue="9999" shuffleSource="0" isMachination="1" width="60" height="60" activation="passive" blinkStatus="0" connectable="1" visible="1" collapsed="0" label="&lt;span&gt;1&lt;/span&gt;&lt;span&gt;&lt;/span&gt;&lt;span&gt;&lt;/span&gt;&lt;span&gt;&lt;/span&gt;&lt;span&gt;&lt;/span&gt;" parent="2" source="67" target="59">
      <mxGeometry x="0" y="0" width="60" height="60" relative="1" TRANSLATE_CONTROL_POINTS="1" as="geometry">
        <mxPoint x="-229" y="-20" as="sourcePoint"/>
        <mxPoint x="-109.1471862576143" y="-20" as="targetPoint"/>
        <mxPoint x="0" y="20" as="offset"/>
      </mxGeometry>
      <Resource name="Green" color="#009900" travelTime="0" as="resource"/>
    </mxResourceConnectionCell>
    <mxResourceConnectionCell id="65" value="&lt;span&gt;1&lt;/span&gt;&lt;span&gt;&lt;/span&gt;&lt;span&gt;&lt;/span&gt;&lt;span&gt;&lt;/span&gt;&lt;span&gt;&lt;/span&gt;" style="shape=resource-connection;endArrow=classic;html=1;strokeWidth=2;fontSize=16;fontColor=#ff9900;strokeColor=#ff9900;" title="Resource Connection" vertex="0" edge="1" type="plain-arrow" resourceTransfer="interval-based" colorCoding="1" minValue="-9999" maxValue="9999" shuffleSource="0" isMachination="1" width="60" height="60" activation="passive" blinkStatus="0" connectable="1" visible="1" collapsed="0" label="&lt;span&gt;1&lt;/span&gt;&lt;span&gt;&lt;/span&gt;&lt;span&gt;&lt;/span&gt;&lt;span&gt;&lt;/span&gt;&lt;span&gt;&lt;/span&gt;" parent="2" source="67" target="60">
      <mxGeometry x="0" y="0" width="60" height="60" relative="1" TRANSLATE_CONTROL_POINTS="1" as="geometry">
        <mxPoint x="-229" y="-10.270270270270203" as="sourcePoint"/>
        <mxPoint x="-109.1471862576143" y="-20" as="targetPoint"/>
        <mxPoint x="-10" y="10" as="offset"/>
      </mxGeometry>
      <Resource name="Orange" color="#ff9900" travelTime="0" as="resource"/>
    </mxResourceConnectionCell>
    <mxResourceConnectionCell id="66" value="&lt;span&gt;1&lt;/span&gt;&lt;span&gt;&lt;/span&gt;&lt;span&gt;&lt;/span&gt;&lt;span&gt;&lt;/span&gt;&lt;span&gt;&lt;/span&gt;" style="shape=resource-connection;endArrow=classic;html=1;strokeWidth=2;fontSize=16;fontColor=#e00000;strokeColor=#e00000;" title="Resource Connection" vertex="0" edge="1" type="plain-arrow" resourceTransfer="interval-based" colorCoding="1" minValue="-9999" maxValue="9999" shuffleSource="0" isMachination="1" width="60" height="60" activation="passive" blinkStatus="0" connectable="1" visible="1" collapsed="0" label="&lt;span&gt;1&lt;/span&gt;&lt;span&gt;&lt;/span&gt;&lt;span&gt;&lt;/span&gt;&lt;span&gt;&lt;/span&gt;&lt;span&gt;&lt;/span&gt;" parent="2" source="67" target="61">
      <mxGeometry x="0" y="0" width="60" height="60" relative="1" TRANSLATE_CONTROL_POINTS="1" as="geometry">
        <mxPoint x="-229" y="-0.7999999999999545" as="sourcePoint"/>
        <mxPoint x="-109.1471862576143" y="-20" as="targetPoint"/>
        <mxPoint x="-10" y="10" as="offset"/>
      </mxGeometry>
      <Resource name="Red" color="#e00000" travelTime="0" as="resource"/>
    </mxResourceConnectionCell>
    <mxGateShapeCell id="67" style="shape=gate-shape;whiteSpace=wrap;html=1;strokeWidth=2;aspect=fixed;resizable=0;fontSize=16;fontColor=#000000;strokeColor=#000000;align=left;" title="Gate" vertex="1" edge="0" actionMode="pull-any" distributionMode="deterministic" isMachination="1" activation="automatic" blinkStatus="0" connectable="1" visible="1" collapsed="0" label="" parent="2">
      <mxGeometry x="-283.5" y="-43" width="46" height="46" TRANSLATE_CONTROL_POINTS="1" relative="0" as="geometry">
        <mxPoint x="0" y="40" as="offset"/>
      </mxGeometry>
    </mxGateShapeCell>
    <mxMachinationRegisterCell id="68" style="shape=register;whiteSpace=wrap;html=1;strokeWidth=2;aspect=fixed;resizable=0;fontSize=16;fontColor=#000000;strokeColor=#000000;align=left;" title="Register" vertex="1" edge="0" isInteractive="0" initialValue="0" step="1" maxValue="9999" minValue="-9999" isMachination="1" activation="passive" blinkStatus="0" connectable="1" visible="1" collapsed="0" label="larger(a,0) +larger(b,0) +larger(c,0)" parent="2">
      <mxGeometry x="157" y="-123" width="46" height="46" TRANSLATE_CONTROL_POINTS="1" relative="0" vertexOrientation="bottomRight" as="geometry">
        <mxPoint x="66.75" y="38.25" as="offset"/>
      </mxGeometry>
    </mxMachinationRegisterCell>
    <mxMachinationRegisterCell id="69" style="shape=register;whiteSpace=wrap;html=1;strokeWidth=2;aspect=fixed;resizable=0;fontSize=16;fontColor=#000000;strokeColor=#000000;align=left;" title="Register" vertex="1" edge="0" isInteractive="0" initialValue="0" step="1" maxValue="9999" minValue="-9999" isMachination="1" activation="passive" blinkStatus="0" connectable="1" visible="1" collapsed="0" label="larger(b,0) +larger(c,0) +larger(d,0)" parent="2">
      <mxGeometry x="157" y="-43" width="46" height="46" TRANSLATE_CONTROL_POINTS="1" relative="0" vertexOrientation="bottomRight" as="geometry">
        <mxPoint x="68.75" y="35.25" as="offset"/>
      </mxGeometry>
    </mxMachinationRegisterCell>
    <mxMachinationRegisterCell id="70" style="shape=register;whiteSpace=wrap;html=1;strokeWidth=2;aspect=fixed;resizable=0;fontSize=16;fontColor=#000000;strokeColor=#000000;align=left;" title="Register" vertex="1" edge="0" isInteractive="0" initialValue="0" step="1" maxValue="9999" minValue="-9999" isMachination="1" activation="passive" blinkStatus="0" connectable="1" visible="1" collapsed="0" label="larger(b,0) +larger(d,0) +larger(e,0)" parent="2">
      <mxGeometry x="157" y="37" width="46" height="46" TRANSLATE_CONTROL_POINTS="1" relative="0" vertexOrientation="bottomRight" as="geometry">
        <mxPoint x="66.75" y="38.25" as="offset"/>
      </mxGeometry>
    </mxMachinationRegisterCell>
    <mxPoolShapeCell id="71" style="shape=pool-shape;whiteSpace=wrap;html=1;strokeWidth=3;aspect=fixed;resizable=0;fontSize=16;fontColor=#000000;strokeColor=#000000;fontStyle=1;align=left;" title="Pool" vertex="1" edge="0" activation="interactive" actionMode="pull-any" number="0" capacity="3" displayCapacity="25" overflow="block" isMachination="1" blinkStatus="0" connectable="1" visible="1" collapsed="0" label="Method 1" parent="2">
      <mxGeometry x="-400.5" y="-343" width="46" height="46" TRANSLATE_CONTROL_POINTS="1" relative="0" vertexOrientation="bottom" as="geometry">
        <mxPoint x="-15.25" y="55.75" as="offset"/>
      </mxGeometry>
      <Resource name="Black" color="#000000" travelTime="0" as="resource"/>
    </mxPoolShapeCell>
    <mxResourceConnectionCell id="72" value="&lt;span&gt;3&lt;/span&gt;&lt;span&gt;&lt;/span&gt;&lt;span&gt;&lt;/span&gt;&lt;span&gt;&lt;/span&gt;&lt;span&gt;&lt;/span&gt;" style="shape=resource-connection;endArrow=classic;html=1;strokeWidth=2;fontSize=16;fontColor=#000000;strokeColor=#000000;" title="Resource Connection" vertex="0" edge="1" type="plain-arrow" resourceTransfer="interval-based" colorCoding="0" minValue="-9999" maxValue="9999" shuffleSource="0" isMachination="1" width="60" height="60" activation="passive" blinkStatus="0" connectable="1" visible="1" collapsed="0" label="&lt;span&gt;3&lt;/span&gt;&lt;span&gt;&lt;/span&gt;&lt;span&gt;&lt;/span&gt;&lt;span&gt;&lt;/span&gt;&lt;span&gt;&lt;/span&gt;" parent="2" source="71" target="56">
      <mxGeometry x="0" y="0" width="60" height="60" relative="1" TRANSLATE_CONTROL_POINTS="1" as="geometry">
        <mxPoint x="-347.5" y="-260" as="sourcePoint"/>
        <mxPoint x="-262.6471862576143" y="-320" as="targetPoint"/>
        <mxPoint x="0" y="20" as="offset"/>
      </mxGeometry>
      <Resource name="Black" color="#000000" travelTime="0" as="resource"/>
    </mxResourceConnectionCell>
    <mxPoolShapeCell id="73" style="shape=pool-shape;whiteSpace=wrap;html=1;strokeWidth=3;aspect=fixed;resizable=0;fontSize=16;fontColor=#000000;strokeColor=#000000;fontStyle=1;align=left;" title="Pool" vertex="1" edge="0" activation="interactive" actionMode="pull-any" number="0" capacity="3" displayCapacity="25" overflow="block" isMachination="1" blinkStatus="0" connectable="1" visible="1" collapsed="0" label="Method 2" parent="2">
      <mxGeometry x="-403" y="-43" width="46" height="46" TRANSLATE_CONTROL_POINTS="1" relative="0" vertexOrientation="top" as="geometry">
        <mxPoint x="-13.75" y="-57.25" as="offset"/>
      </mxGeometry>
      <Resource name="Black" color="#000000" travelTime="0" as="resource"/>
    </mxPoolShapeCell>
    <mxResourceConnectionCell id="74" value="&lt;span&gt;3&lt;/span&gt;&lt;span&gt;&lt;/span&gt;&lt;span&gt;&lt;/span&gt;&lt;span&gt;&lt;/span&gt;&lt;span&gt;&lt;/span&gt;" style="shape=resource-connection;endArrow=classic;html=1;strokeWidth=2;fontSize=16;fontColor=#000000;strokeColor=#000000;align=center;" title="Resource Connection" vertex="0" edge="1" type="plain-arrow" resourceTransfer="interval-based" colorCoding="0" minValue="-9999" maxValue="9999" shuffleSource="0" isMachination="1" width="60" height="60" activation="passive" blinkStatus="0" connectable="1" visible="1" collapsed="0" label="&lt;span&gt;3&lt;/span&gt;&lt;span&gt;&lt;/span&gt;&lt;span&gt;&lt;/span&gt;&lt;span&gt;&lt;/span&gt;&lt;span&gt;&lt;/span&gt;" parent="2" source="73" target="67">
      <mxGeometry x="-0.14099018513655462" y="19.5" width="60" height="60" relative="1" TRANSLATE_CONTROL_POINTS="1" as="geometry">
        <mxPoint x="-340" y="5" as="sourcePoint"/>
        <mxPoint x="-255.1471862576143" y="-55" as="targetPoint"/>
        <mxPoint x="0" y="0" as="offset"/>
      </mxGeometry>
      <Resource name="Black" color="#000000" travelTime="0" as="resource"/>
    </mxResourceConnectionCell>
    <mxStateConnectionCell id="75" value="&lt;span&gt;a&lt;/span&gt;&lt;span&gt;&lt;/span&gt;&lt;span&gt;&lt;/span&gt;&lt;span&gt;&lt;/span&gt;&lt;span&gt;&lt;/span&gt;" style="shape=state-connection;endArrow=classic;dashed=1;dashPattern=4 3;html=1;strokeWidth=2;fontSize=16;fontColor=#000000;strokeColor=#000000;" title="State Connection" vertex="0" edge="1" type="0" colorCoding="0" isMachination="1" width="60" height="60" activation="passive" blinkStatus="0" connectable="1" visible="1" collapsed="0" label="&lt;span&gt;a&lt;/span&gt;&lt;span&gt;&lt;/span&gt;&lt;span&gt;&lt;/span&gt;&lt;span&gt;&lt;/span&gt;&lt;span&gt;&lt;/span&gt;" parent="2" source="57" target="68">
      <mxGeometry x="0" y="0" width="60" height="60" relative="1" TRANSLATE_CONTROL_POINTS="1" as="geometry">
        <mxPoint x="-90.5" y="-50" as="sourcePoint"/>
        <mxPoint x="-40" y="-140" as="targetPoint"/>
        <Array as="points">
          <mxPoint x="-40.26833333333332" y="-139.89999999999998"/>
        </Array>
        <mxPoint x="20" y="10" as="offset"/>
      </mxGeometry>
      <Resource name="Black" color="#000000" travelTime="0" as="resource"/>
    </mxStateConnectionCell>
    <mxStateConnectionCell id="76" value="&lt;span&gt;b&lt;/span&gt;&lt;span&gt;&lt;/span&gt;&lt;span&gt;&lt;/span&gt;&lt;span&gt;&lt;/span&gt;&lt;span&gt;&lt;/span&gt;" style="shape=state-connection;endArrow=classic;dashed=1;dashPattern=4 3;html=1;strokeWidth=2;fontSize=16;fontColor=#0066CC;strokeColor=#0066CC;" title="State Connection" vertex="0" edge="1" type="0" colorCoding="0" isMachination="1" width="60" height="60" activation="passive" blinkStatus="0" connectable="1" visible="1" collapsed="0" label="&lt;span&gt;b&lt;/span&gt;&lt;span&gt;&lt;/span&gt;&lt;span&gt;&lt;/span&gt;&lt;span&gt;&lt;/span&gt;&lt;span&gt;&lt;/span&gt;" parent="2" source="58" target="68">
      <mxGeometry x="0" y="0" width="60" height="60" relative="1" TRANSLATE_CONTROL_POINTS="1" as="geometry">
        <mxPoint x="-30.5" y="-20" as="sourcePoint"/>
        <mxPoint x="54.352813742385706" y="-80" as="targetPoint"/>
        <mxPoint x="20" y="10" as="offset"/>
      </mxGeometry>
      <Resource name="Black" color="#000000" travelTime="0" as="resource"/>
    </mxStateConnectionCell>
    <mxStateConnectionCell id="77" value="&lt;span&gt;c&lt;/span&gt;&lt;span&gt;&lt;/span&gt;&lt;span&gt;&lt;/span&gt;&lt;span&gt;&lt;/span&gt;&lt;span&gt;&lt;/span&gt;" style="shape=state-connection;endArrow=classic;dashed=1;dashPattern=4 3;html=1;strokeWidth=2;fontSize=16;fontColor=#009900;strokeColor=#009900;" title="State Connection" vertex="0" edge="1" type="0" colorCoding="0" isMachination="1" width="60" height="60" activation="passive" blinkStatus="0" connectable="1" visible="1" collapsed="0" label="&lt;span&gt;c&lt;/span&gt;&lt;span&gt;&lt;/span&gt;&lt;span&gt;&lt;/span&gt;&lt;span&gt;&lt;/span&gt;&lt;span&gt;&lt;/span&gt;" parent="2" source="59" target="68">
      <mxGeometry x="0" y="0" width="60" height="60" relative="1" TRANSLATE_CONTROL_POINTS="1" as="geometry">
        <mxPoint x="-10.5" y="40" as="sourcePoint"/>
        <mxPoint x="74.3528137423857" y="-20" as="targetPoint"/>
        <mxPoint x="20" y="10" as="offset"/>
      </mxGeometry>
      <Resource name="Black" color="#000000" travelTime="0" as="resource"/>
    </mxStateConnectionCell>
    <mxStateConnectionCell id="78" value="&lt;span&gt;d&lt;/span&gt;&lt;span&gt;&lt;/span&gt;&lt;span&gt;&lt;/span&gt;&lt;span&gt;&lt;/span&gt;&lt;span&gt;&lt;/span&gt;" style="shape=state-connection;endArrow=classic;dashed=1;dashPattern=4 3;html=1;strokeWidth=2;fontSize=16;fontColor=#CC6600;strokeColor=#CC6600;" title="State Connection" vertex="0" edge="1" type="0" colorCoding="0" isMachination="1" width="60" height="60" activation="passive" blinkStatus="0" connectable="1" visible="1" collapsed="0" label="&lt;span&gt;d&lt;/span&gt;&lt;span&gt;&lt;/span&gt;&lt;span&gt;&lt;/span&gt;&lt;span&gt;&lt;/span&gt;&lt;span&gt;&lt;/span&gt;" parent="2" source="60" target="69">
      <mxGeometry x="0" y="0" width="60" height="60" relative="1" TRANSLATE_CONTROL_POINTS="1" as="geometry">
        <mxPoint x="-30.5" y="100" as="sourcePoint"/>
        <mxPoint x="54.352813742385706" y="40" as="targetPoint"/>
        <mxPoint x="20" y="10" as="offset"/>
      </mxGeometry>
      <Resource name="Black" color="#000000" travelTime="0" as="resource"/>
    </mxStateConnectionCell>
    <mxStateConnectionCell id="79" value="&lt;span&gt;e&lt;/span&gt;&lt;span&gt;&lt;/span&gt;&lt;span&gt;&lt;/span&gt;&lt;span&gt;&lt;/span&gt;&lt;span&gt;&lt;/span&gt;" style="shape=state-connection;endArrow=classic;dashed=1;dashPattern=4 3;html=1;strokeWidth=2;fontSize=16;fontColor=#CC0000;strokeColor=#CC0000;" title="State Connection" vertex="0" edge="1" type="0" colorCoding="0" isMachination="1" width="60" height="60" activation="passive" blinkStatus="0" connectable="1" visible="1" collapsed="0" label="&lt;span&gt;e&lt;/span&gt;&lt;span&gt;&lt;/span&gt;&lt;span&gt;&lt;/span&gt;&lt;span&gt;&lt;/span&gt;&lt;span&gt;&lt;/span&gt;" parent="2" source="61" target="70">
      <mxGeometry x="0" y="0" width="60" height="60" relative="1" TRANSLATE_CONTROL_POINTS="1" as="geometry">
        <mxPoint x="-90.5" y="120" as="sourcePoint"/>
        <mxPoint x="290" y="60" as="targetPoint"/>
        <Array as="points">
          <mxPoint x="-40" y="100"/>
        </Array>
        <mxPoint x="0" y="20" as="offset"/>
      </mxGeometry>
      <Resource name="Black" color="#000000" travelTime="0" as="resource"/>
    </mxStateConnectionCell>
    <mxStateConnectionCell id="80" value="&lt;span&gt;b&lt;/span&gt;&lt;span&gt;&lt;/span&gt;&lt;span&gt;&lt;/span&gt;&lt;span&gt;&lt;/span&gt;&lt;span&gt;&lt;/span&gt;" style="shape=state-connection;endArrow=classic;dashed=1;dashPattern=4 3;html=1;strokeWidth=2;fontSize=16;fontColor=#0066CC;strokeColor=#0066CC;" title="State Connection" vertex="0" edge="1" type="0" colorCoding="0" isMachination="1" width="60" height="60" activation="passive" blinkStatus="0" connectable="1" visible="1" collapsed="0" label="&lt;span&gt;b&lt;/span&gt;&lt;span&gt;&lt;/span&gt;&lt;span&gt;&lt;/span&gt;&lt;span&gt;&lt;/span&gt;&lt;span&gt;&lt;/span&gt;" parent="2" source="58" target="69">
      <mxGeometry x="0" y="0" width="60" height="60" relative="1" TRANSLATE_CONTROL_POINTS="1" as="geometry">
        <mxPoint x="-30.5" y="-20" as="sourcePoint"/>
        <mxPoint x="54.352813742385706" y="-80" as="targetPoint"/>
        <mxPoint x="-10" y="10" as="offset"/>
      </mxGeometry>
      <Resource name="Black" color="#000000" travelTime="0" as="resource"/>
    </mxStateConnectionCell>
    <mxStateConnectionCell id="81" value="&lt;span&gt;c&lt;/span&gt;&lt;span&gt;&lt;/span&gt;&lt;span&gt;&lt;/span&gt;&lt;span&gt;&lt;/span&gt;&lt;span&gt;&lt;/span&gt;" style="shape=state-connection;endArrow=classic;dashed=1;dashPattern=4 3;html=1;strokeWidth=2;fontSize=16;fontColor=#009900;strokeColor=#009900;" title="State Connection" vertex="0" edge="1" type="0" colorCoding="0" isMachination="1" width="60" height="60" activation="passive" blinkStatus="0" connectable="1" visible="1" collapsed="0" label="&lt;span&gt;c&lt;/span&gt;&lt;span&gt;&lt;/span&gt;&lt;span&gt;&lt;/span&gt;&lt;span&gt;&lt;/span&gt;&lt;span&gt;&lt;/span&gt;" parent="2" source="59" target="69">
      <mxGeometry x="0" y="0" width="60" height="60" relative="1" TRANSLATE_CONTROL_POINTS="1" as="geometry">
        <mxPoint x="-10.5" y="40" as="sourcePoint"/>
        <mxPoint x="74.3528137423857" y="-20" as="targetPoint"/>
        <mxPoint x="0" y="20" as="offset"/>
      </mxGeometry>
      <Resource name="Black" color="#000000" travelTime="0" as="resource"/>
    </mxStateConnectionCell>
    <mxStateConnectionCell id="82" value="&lt;span&gt;b&lt;/span&gt;&lt;span&gt;&lt;/span&gt;&lt;span&gt;&lt;/span&gt;&lt;span&gt;&lt;/span&gt;&lt;span&gt;&lt;/span&gt;" style="shape=state-connection;endArrow=classic;dashed=1;dashPattern=4 3;html=1;strokeWidth=2;fontSize=16;fontColor=#0066CC;strokeColor=#0066CC;" title="State Connection" vertex="0" edge="1" type="0" colorCoding="0" isMachination="1" width="60" height="60" activation="passive" blinkStatus="0" connectable="1" visible="1" collapsed="0" label="&lt;span&gt;b&lt;/span&gt;&lt;span&gt;&lt;/span&gt;&lt;span&gt;&lt;/span&gt;&lt;span&gt;&lt;/span&gt;&lt;span&gt;&lt;/span&gt;" parent="2" source="58" target="70">
      <mxGeometry x="0" y="0" width="60" height="60" relative="1" TRANSLATE_CONTROL_POINTS="1" as="geometry">
        <mxPoint x="-30.5" y="-20" as="sourcePoint"/>
        <mxPoint x="54.352813742385706" y="-80" as="targetPoint"/>
        <mxPoint x="-10" y="10" as="offset"/>
      </mxGeometry>
      <Resource name="Black" color="#000000" travelTime="0" as="resource"/>
    </mxStateConnectionCell>
    <mxStateConnectionCell id="83" value="&lt;span&gt;d&lt;/span&gt;&lt;span&gt;&lt;/span&gt;&lt;span&gt;&lt;/span&gt;&lt;span&gt;&lt;/span&gt;&lt;span&gt;&lt;/span&gt;" style="shape=state-connection;endArrow=classic;dashed=1;dashPattern=4 3;html=1;strokeWidth=2;fontSize=16;fontColor=#CC6600;strokeColor=#CC6600;" title="State Connection" vertex="0" edge="1" type="0" colorCoding="0" isMachination="1" width="60" height="60" activation="passive" blinkStatus="0" connectable="1" visible="1" collapsed="0" label="&lt;span&gt;d&lt;/span&gt;&lt;span&gt;&lt;/span&gt;&lt;span&gt;&lt;/span&gt;&lt;span&gt;&lt;/span&gt;&lt;span&gt;&lt;/span&gt;" parent="2" source="60" target="70">
      <mxGeometry x="0" y="0" width="60" height="60" relative="1" TRANSLATE_CONTROL_POINTS="1" as="geometry">
        <mxPoint x="-30.5" y="100" as="sourcePoint"/>
        <mxPoint x="54.352813742385706" y="40" as="targetPoint"/>
        <mxPoint x="-10" y="10" as="offset"/>
      </mxGeometry>
      <Resource name="Black" color="#000000" travelTime="0" as="resource"/>
    </mxStateConnectionCell>
    <mxPoolShapeCell id="84" style="shape=pool-shape;whiteSpace=wrap;html=1;strokeWidth=5;aspect=fixed;resizable=0;fontSize=18;fontColor=#B266FF;strokeColor=#B266FF;fontStyle=1;align=left;" title="Pool" vertex="1" edge="0" activation="passive" actionMode="push-any" number="0" capacity="-1" displayCapacity="25" overflow="block" isMachination="1" blinkStatus="0" connectable="1" visible="1" collapsed="0" label="Stop" parent="2">
      <mxGeometry x="357" y="-123" width="46" height="46" TRANSLATE_CONTROL_POINTS="1" relative="0" vertexOrientation="right" as="geometry">
        <mxPoint x="58.749999999999524" y="0.25000000000019146" as="offset"/>
      </mxGeometry>
      <Resource name="Black" color="#000000" travelTime="0" as="resource"/>
    </mxPoolShapeCell>
    <mxPoolShapeCell id="85" style="shape=pool-shape;whiteSpace=wrap;html=1;strokeWidth=5;aspect=fixed;resizable=0;fontSize=18;fontColor=#B266FF;strokeColor=#B266FF;fontStyle=1;align=left;" title="Pool" vertex="1" edge="0" activation="passive" actionMode="push-any" number="0" capacity="-1" displayCapacity="25" overflow="block" isMachination="1" blinkStatus="0" connectable="1" visible="1" collapsed="0" label="Contact" parent="2">
      <mxGeometry x="357" y="-43" width="46" height="46" TRANSLATE_CONTROL_POINTS="1" relative="0" vertexOrientation="right" as="geometry">
        <mxPoint x="66.75" y="2.25" as="offset"/>
      </mxGeometry>
      <Resource name="Black" color="#000000" travelTime="0" as="resource"/>
    </mxPoolShapeCell>
    <mxPoolShapeCell id="86" style="shape=pool-shape;whiteSpace=wrap;html=1;strokeWidth=5;aspect=fixed;resizable=0;fontSize=18;fontColor=#B266FF;strokeColor=#B266FF;fontStyle=1;align=left;" title="Pool" vertex="1" edge="0" activation="passive" actionMode="push-any" number="0" capacity="-1" displayCapacity="25" overflow="block" isMachination="1" blinkStatus="0" connectable="1" visible="1" collapsed="0" label="Proceed" parent="2">
      <mxGeometry x="357" y="37" width="46" height="46" TRANSLATE_CONTROL_POINTS="1" relative="0" vertexOrientation="right" as="geometry">
        <mxPoint x="68.25" y="0.25" as="offset"/>
      </mxGeometry>
      <Resource name="Black" color="#000000" travelTime="0" as="resource"/>
    </mxPoolShapeCell>
    <mxStateConnectionCell id="87" value="&lt;span&gt;&gt;2&lt;/span&gt;&lt;span&gt;&lt;/span&gt;&lt;span&gt;&lt;/span&gt;&lt;span&gt;&lt;/span&gt;&lt;span&gt;&lt;/span&gt;" style="shape=state-connection;endArrow=classic;dashed=1;dashPattern=4 3;html=1;strokeWidth=2;fontSize=16;fontColor=#000000;strokeColor=#000000;align=center;" title="State Connection" vertex="0" edge="1" type="0" colorCoding="0" isMachination="1" width="60" height="60" activation="passive" blinkStatus="0" connectable="1" visible="1" collapsed="0" label="&lt;span&gt;&amp;gt;2&lt;/span&gt;&lt;span&gt;&lt;/span&gt;&lt;span&gt;&lt;/span&gt;&lt;span&gt;&lt;/span&gt;&lt;span&gt;&lt;/span&gt;" parent="2" source="69" target="85">
      <mxGeometry x="0.5730154854910714" y="-19.5" width="60" height="60" relative="1" TRANSLATE_CONTROL_POINTS="1" as="geometry">
        <mxPoint x="210" y="40" as="sourcePoint"/>
        <mxPoint x="294.8528137423857" y="-20" as="targetPoint"/>
        <mxPoint x="0" y="0" as="offset"/>
      </mxGeometry>
      <Resource name="Black" color="#000000" travelTime="0" as="resource"/>
    </mxStateConnectionCell>
    <mxStateConnectionCell id="88" value="&lt;span&gt;&gt;2&lt;/span&gt;&lt;span&gt;&lt;/span&gt;&lt;span&gt;&lt;/span&gt;&lt;span&gt;&lt;/span&gt;&lt;span&gt;&lt;/span&gt;" style="shape=state-connection;endArrow=classic;dashed=1;dashPattern=4 3;html=1;strokeWidth=2;fontSize=16;fontColor=#000000;strokeColor=#000000;align=center;" title="State Connection" vertex="0" edge="1" type="0" colorCoding="0" isMachination="1" width="60" height="60" activation="passive" blinkStatus="0" connectable="1" visible="1" collapsed="0" label="&lt;span&gt;&amp;gt;2&lt;/span&gt;&lt;span&gt;&lt;/span&gt;&lt;span&gt;&lt;/span&gt;&lt;span&gt;&lt;/span&gt;&lt;span&gt;&lt;/span&gt;" parent="2" source="68" target="84">
      <mxGeometry x="0.4920636858258929" y="-19.5" width="60" height="60" relative="1" TRANSLATE_CONTROL_POINTS="1" as="geometry">
        <mxPoint x="210" y="-50" as="sourcePoint"/>
        <mxPoint x="294.8528137423857" y="-110" as="targetPoint"/>
        <mxPoint x="0" y="0" as="offset"/>
      </mxGeometry>
      <Resource name="Black" color="#000000" travelTime="0" as="resource"/>
    </mxStateConnectionCell>
    <mxStateConnectionCell id="89" value="&lt;span&gt;&gt;2&lt;/span&gt;&lt;span&gt;&lt;/span&gt;&lt;span&gt;&lt;/span&gt;&lt;span&gt;&lt;/span&gt;&lt;span&gt;&lt;/span&gt;" style="shape=state-connection;endArrow=classic;dashed=1;dashPattern=4 3;html=1;strokeWidth=2;fontSize=16;fontColor=#000000;strokeColor=#000000;align=center;" title="State Connection" vertex="0" edge="1" type="0" colorCoding="0" isMachination="1" width="60" height="60" activation="passive" blinkStatus="0" connectable="1" visible="1" collapsed="0" label="&lt;span&gt;&amp;gt;2&lt;/span&gt;&lt;span&gt;&lt;/span&gt;&lt;span&gt;&lt;/span&gt;&lt;span&gt;&lt;/span&gt;&lt;span&gt;&lt;/span&gt;" parent="2" source="70" target="86">
      <mxGeometry x="0.55555419921875" y="-19.5" width="60" height="60" relative="1" TRANSLATE_CONTROL_POINTS="1" as="geometry">
        <mxPoint x="210" y="120" as="sourcePoint"/>
        <mxPoint x="294.8528137423857" y="60" as="targetPoint"/>
        <mxPoint x="0" y="0" as="offset"/>
      </mxGeometry>
      <Resource name="Black" color="#000000" travelTime="0" as="resource"/>
    </mxStateConnectionCell>
    <mxPoolShapeCell id="90" style="shape=pool-shape;whiteSpace=wrap;html=1;strokeWidth=2;aspect=fixed;resizable=0;fontSize=16;fontColor=#000000;strokeColor=#000000;align=left;" title="Pool" vertex="1" edge="0" activation="automatic" actionMode="pull-any" number="0" capacity="-1" displayCapacity="25" overflow="block" isMachination="1" blinkStatus="0" connectable="1" visible="1" collapsed="0" label="" parent="2">
      <mxGeometry x="217" y="-203" width="46" height="46" TRANSLATE_CONTROL_POINTS="1" relative="0" as="geometry">
        <mxPoint x="0" y="40" as="offset"/>
      </mxGeometry>
      <Resource name="Black" color="#000000" travelTime="0" as="resource"/>
    </mxPoolShapeCell>
    <mxPoolShapeCell id="91" style="shape=pool-shape;whiteSpace=wrap;html=1;strokeWidth=2;aspect=fixed;resizable=0;fontSize=16;fontColor=#000000;strokeColor=#000000;align=left;" title="Pool" vertex="1" edge="0" activation="automatic" actionMode="pull-any" number="0" capacity="-1" displayCapacity="25" overflow="block" isMachination="1" blinkStatus="0" connectable="1" visible="1" collapsed="0" label="" parent="2">
      <mxGeometry x="237" y="-343" width="46" height="46" TRANSLATE_CONTROL_POINTS="1" relative="0" as="geometry">
        <mxPoint x="0" y="40" as="offset"/>
      </mxGeometry>
      <Resource name="Black" color="#000000" travelTime="0" as="resource"/>
    </mxPoolShapeCell>
    <mxPoolShapeCell id="92" style="shape=pool-shape;whiteSpace=wrap;html=1;strokeWidth=2;aspect=fixed;resizable=0;fontSize=16;fontColor=#000000;strokeColor=#000000;align=left;" title="Pool" vertex="1" edge="0" activation="automatic" actionMode="pull-any" number="0" capacity="-1" displayCapacity="25" overflow="block" isMachination="1" blinkStatus="0" connectable="1" visible="1" collapsed="0" label="" parent="2">
      <mxGeometry x="217" y="-483" width="46" height="46" TRANSLATE_CONTROL_POINTS="1" relative="0" as="geometry">
        <mxPoint x="0" y="40" as="offset"/>
      </mxGeometry>
      <Resource name="Black" color="#000000" travelTime="0" as="resource"/>
    </mxPoolShapeCell>
    <mxStateConnectionCell id="93" value="&lt;span&gt;&gt;0&lt;/span&gt;&lt;span&gt;&lt;/span&gt;&lt;span&gt;&lt;/span&gt;&lt;span&gt;&lt;/span&gt;&lt;span&gt;&lt;/span&gt;" style="shape=state-connection;endArrow=classic;dashed=1;dashPattern=4 3;html=1;strokeWidth=2;fontSize=16;fontColor=#000000;strokeColor=#000000;" title="State Connection" vertex="0" edge="1" type="0" colorCoding="0" isMachination="1" width="60" height="60" activation="passive" blinkStatus="0" connectable="1" visible="1" collapsed="0" label="&lt;span&gt;&amp;gt;0&lt;/span&gt;&lt;span&gt;&lt;/span&gt;&lt;span&gt;&lt;/span&gt;&lt;span&gt;&lt;/span&gt;&lt;span&gt;&lt;/span&gt;" parent="2" source="92" target="50">
      <mxGeometry x="0" y="0" width="60" height="60" relative="1" TRANSLATE_CONTROL_POINTS="1" as="geometry">
        <mxPoint x="270" y="-400" as="sourcePoint"/>
        <mxPoint x="354.8528137423857" y="-460" as="targetPoint"/>
        <mxPoint x="0" y="20" as="offset"/>
      </mxGeometry>
      <Resource name="Black" color="#000000" travelTime="0" as="resource"/>
    </mxStateConnectionCell>
    <mxStateConnectionCell id="94" value="&lt;span&gt;&gt;0&lt;/span&gt;&lt;span&gt;&lt;/span&gt;&lt;span&gt;&lt;/span&gt;&lt;span&gt;&lt;/span&gt;&lt;span&gt;&lt;/span&gt;" style="shape=state-connection;endArrow=classic;dashed=1;dashPattern=4 3;html=1;strokeWidth=2;fontSize=16;fontColor=#000000;strokeColor=#000000;" title="State Connection" vertex="0" edge="1" type="0" colorCoding="0" isMachination="1" width="60" height="60" activation="passive" blinkStatus="0" connectable="1" visible="1" collapsed="0" label="&lt;span&gt;&amp;gt;0&lt;/span&gt;&lt;span&gt;&lt;/span&gt;&lt;span&gt;&lt;/span&gt;&lt;span&gt;&lt;/span&gt;&lt;span&gt;&lt;/span&gt;" parent="2" source="91" target="53">
      <mxGeometry x="0" y="0" width="60" height="60" relative="1" TRANSLATE_CONTROL_POINTS="1" as="geometry">
        <mxPoint x="290" y="-260" as="sourcePoint"/>
        <mxPoint x="374.8528137423857" y="-320" as="targetPoint"/>
        <mxPoint x="0" y="20" as="offset"/>
      </mxGeometry>
      <Resource name="Black" color="#000000" travelTime="0" as="resource"/>
    </mxStateConnectionCell>
    <mxStateConnectionCell id="95" value="&lt;span&gt;&gt;0&lt;/span&gt;&lt;span&gt;&lt;/span&gt;&lt;span&gt;&lt;/span&gt;&lt;span&gt;&lt;/span&gt;&lt;span&gt;&lt;/span&gt;" style="shape=state-connection;endArrow=classic;dashed=1;dashPattern=4 3;html=1;strokeWidth=2;fontSize=16;fontColor=#000000;strokeColor=#000000;" title="State Connection" vertex="0" edge="1" type="0" colorCoding="0" isMachination="1" width="60" height="60" activation="passive" blinkStatus="0" connectable="1" visible="1" collapsed="0" label="&lt;span&gt;&amp;gt;0&lt;/span&gt;&lt;span&gt;&lt;/span&gt;&lt;span&gt;&lt;/span&gt;&lt;span&gt;&lt;/span&gt;&lt;span&gt;&lt;/span&gt;" parent="2" source="90" target="47">
      <mxGeometry x="0" y="0" width="60" height="60" relative="1" TRANSLATE_CONTROL_POINTS="1" as="geometry">
        <mxPoint x="270" y="-120" as="sourcePoint"/>
        <mxPoint x="354.8528137423857" y="-180" as="targetPoint"/>
        <mxPoint x="20" y="10" as="offset"/>
      </mxGeometry>
      <Resource name="Black" color="#000000" travelTime="0" as="resource"/>
    </mxStateConnectionCell>
    <mxTextCell id="96" style="shape=text-shape;html=1;resizable=0;align=left;verticalAlign=top;whiteSpace=wrap;rounded=0;fontSize=16;fontColor=#000000;strokeColor=#000000;fillColor=#ffffff;spacing=10;strokeWidth=1;" title="Text" vertex="1" edge="0" label="&lt;span&gt;Encrypt and decrypt key words by using the resources color coding.&lt;/span&gt;" prevLabel="&lt;span&gt;Encrypt and decrypt key words by using the resources color coding.&lt;/span&gt;" isMachination="0" defaultSpacing="10" activation="passive" blinkStatus="0" connectable="1" visible="1" collapsed="0" parent="2">
      <mxGeometry x="-830" y="-556" width="499" height="41" TRANSLATE_CONTROL_POINTS="1" relative="0" as="geometry">
        <mxPoint x="0" y="0" as="offset"/>
      </mxGeometry>
    </mxTextCell>
    <mxTextCell id="97" style="shape=text-shape;html=1;resizable=0;align=left;verticalAlign=top;whiteSpace=wrap;rounded=0;fontSize=16;fontColor=#000000;strokeColor=none;fillColor=#ffffff;spacing=10;strokeWidth=0;" title="Text" vertex="1" edge="0" label="&lt;span&gt;&amp;nbsp;- Key words can be encrypted by using color combinations;&lt;/span&gt;&lt;br&gt;&lt;span&gt;&amp;nbsp;- Decrypting the color combinations can be done by using pools that exclude possibilities&lt;/span&gt;&lt;br&gt;&lt;span&gt;&amp;nbsp; &amp;nbsp;or by using registers which count the correct elements in order to detect the key word.&lt;/span&gt;" prevLabel="&lt;span&gt;&amp;nbsp;- Key words can be encrypted by using color combinations;&lt;/span&gt;&lt;br&gt;&lt;span&gt;&amp;nbsp;- Decrypting the color combinations can be done by using pools that exclude possibilities&lt;/span&gt;&lt;br&gt;&lt;span&gt;&amp;nbsp; &amp;nbsp;or by using registers which count the correct elements in order to detect the key word.&lt;/span&gt;" isMachination="0" defaultSpacing="10" activation="passive" blinkStatus="0" connectable="1" visible="1" collapsed="0" parent="2">
      <mxGeometry x="-830" y="-488" width="655" height="78" TRANSLATE_CONTROL_POINTS="1" relative="0" as="geometry">
        <mxPoint x="0" y="0" as="offset"/>
      </mxGeometry>
    </mxTextCell>
  </root>
  <chart/>
</mxGraphModel>
