{
    "seed": 0,
    "resourceTagColor": {},
    "graph": {
        "stateEdges": {},
        "vertices": {
            "2017": {
                "nodeColor": "black",
                "nodeLabel": "",
                "nodeTy": {
                    "resourceTypes": [
                        "Black"
                    ],
                    "activation": "Automatic",
                    "tag": "Source"
                }
            },
            "2016": {
                "nodeColor": "black",
                "nodeLabel": "",
                "nodeTy": {
                    "activation": "Passive",
                    "overflow": "OverflowBlock",
                    "resources": [],
                    "pushPullAction": {
                        "contents": "PullAny",
                        "tag": "Pulling"
                    },
                    "tag": "Pool"
                }
            }
        },
        "resourceEdges": {
            "13024": {
                "to": 2016,
                "interval": {
                    "counter": 0,
                    "formula": {
                        "contents": 1,
                        "tag": "RFConstant"
                    }
                },
                "resourceFormula": {
                    "contents": [
                        {
                            "contents": 3,
                            "tag": "RFConstant"
                        },
                        {
                            "contents": [
                                {
                                    "contents": 1,
                                    "tag": "RFConstant"
                                },
                                {
                                    "contents": 5,
                                    "tag": "RFConstant"
                                }
                            ],
                            "tag": "RFDice"
                        }
                    ],
                    "tag": "RFMultiply"
                },
                "from": 2017,
                "limits": {
                    "lower": null,
                    "upper": null
                },
                "shuffleOrigin": false,
                "transfer": "IntervalTransfer"
            }
        }
    },
    "time": 0
}