{
    "seed": 0,
    "resourceTagColor": {},
    "pendingTriggers": [],
    "graph": {
        "stateEdges": {
            "151": {
                "stateFormula": {
                    "contents": {
                        "contents": 1,
                        "tag": "SFConstant"
                    },
                    "tag": "SFAdd"
                },
                "to": 59,
                "active": false,
                "from": 148
            }
        },
        "vertices": {
            "148": {
                "nodeColor": "black",
                "nodeLabel": "",
                "nodeTy": {
                    "activation": {
                        "tag": "Passive"
                    },
                    "overflow": "OverflowBlock",
                    "resources": [],
                    "pushPullAction": {
                        "contents": "PullAny",
                        "tag": "Pulling"
                    },
                    "tag": "Pool"
                }
            },
            "147": {
                "nodeColor": "black",
                "nodeLabel": "",
                "nodeTy": {
                    "resourceTypes": [
                        "Black"
                    ],
                    "activation": {
                        "tag": "Automatic"
                    },
                    "tag": "Source"
                }
            },
            "150": {
                "nodeColor": "black",
                "nodeLabel": "",
                "nodeTy": {
                    "activation": {
                        "tag": "Passive"
                    },
                    "overflow": "OverflowBlock",
                    "resources": [],
                    "pushPullAction": {
                        "contents": "PullAny",
                        "tag": "Pulling"
                    },
                    "tag": "Pool"
                }
            },
            "145": {
                "nodeColor": "black",
                "nodeLabel": "",
                "nodeTy": {
                    "resourceTypes": [
                        "Black"
                    ],
                    "activation": {
                        "tag": "Automatic"
                    },
                    "tag": "Source"
                }
            }
        },
        "resourceEdges": {
            "59": {
                "to": 150,
                "interval": {
                    "counter": 0,
                    "formula": {
                        "contents": 1,
                        "tag": "RFConstant"
                    }
                },
                "resourceFormula": {
                    "contents": 1,
                    "tag": "RFConstant"
                },
                "from": 145,
                "limits": {},
                "shuffleOrigin": false,
                "transfer": "IntervalTransfer"
            },
            "149": {
                "to": 148,
                "interval": {
                    "counter": 0,
                    "formula": {
                        "contents": 2,
                        "tag": "RFConstant"
                    }
                },
                "resourceFormula": {
                    "contents": 1,
                    "tag": "RFConstant"
                },
                "from": 147,
                "limits": {},
                "shuffleOrigin": false,
                "transfer": "IntervalTransfer"
            }
        }
    },
    "time": 0
}