{
    "seed": 0,
    "resourceTagColor": {},
    "pendingTriggers": [],
    "graph": {
        "stateEdges": {},
        "vertices": {
            "473": {
                "nodeColor": "black",
                "nodeLabel": "",
                "nodeTy": {
                    "pullAction": "PullAny",
                    "activation": {
                        "tag": "Interactive"
                    },
                    "tag": "Drain"
                }
            },
            "476": {
                "nodeColor": "black",
                "nodeLabel": "",
                "nodeTy": {
                    "activation": {
                        "tag": "Passive"
                    },
                    "overflow": "OverflowBlock",
                    "resources": [
                        {
                            "uUID": "0fa44e74-8699-447e-b79e-65958a103a78",
                            "tag": "Black"
                        },
                        {
                            "uUID": "1ce99f20-b80b-49c8-afb9-4c679be95974",
                            "tag": "Black"
                        },
                        {
                            "uUID": "2d01f9a1-69f6-4071-8505-2e67a18f4e5c",
                            "tag": "Black"
                        },
                        {
                            "uUID": "522d02a5-c424-4729-a030-7d78aa65c1b3",
                            "tag": "Black"
                        },
                        {
                            "uUID": "590a4cee-8e25-4a30-9a47-9a571acdb374",
                            "tag": "Black"
                        },
                        {
                            "uUID": "6aa4ba99-60c3-4ec4-a073-1db333bef339",
                            "tag": "Black"
                        },
                        {
                            "uUID": "7b5592e5-33e5-4e50-be20-77b81aa06494",
                            "tag": "Black"
                        },
                        {
                            "uUID": "a27f1da4-5eda-4f4b-a397-bc6528d776fc",
                            "tag": "Black"
                        },
                        {
                            "uUID": "b4623d69-27fb-4032-9bd2-919fc6fc0a72",
                            "tag": "Black"
                        },
                        {
                            "uUID": "cd8001b7-75f7-4d3b-b7c8-d33ba16a1d22",
                            "tag": "Black"
                        }
                    ],
                    "pushPullAction": {
                        "contents": "PullAny",
                        "tag": "Pulling"
                    },
                    "tag": "Pool"
                }
            }
        },
        "resourceEdges": {
            "478": {
                "to": 473,
                "interval": {
                    "counter": 0,
                    "formula": {
                        "contents": 1,
                        "tag": "RFConstant"
                    }
                },
                "resourceFormula": {
                    "contents": 1,
                    "tag": "RFConstant"
                },
                "from": 476,
                "limits": {},
                "shuffleOrigin": false,
                "transfer": "IntervalTransfer"
            }
        }
    },
    "time": 0
}